{
  "title": {},
  "utterances": [
    {
      "words": [
        {
          "tags": {
            "pos": "NNP"
          },
          "transcription": "Party"
        },
        {
          "tags": {
            "pos": "IN"
          },
          "transcription": "of"
        },
        {
          "tags": {
            "pos": "CD"
          },
          "transcription": "One"
        },
        {
          "tags": {
            "pos": "PRP"
          },
          "transcription": "I"
        },
        {
          "tags": {
            "pos": "VBP"
          },
          "transcription": "wish"
        },
        {
          "tags": {
            "pos": "PRP"
          },
          "transcription": "we"
        },
        {
          "tags": {
            "pos": "MD"
          },
          "transcription": "could"
        },
        {
          "tags": {
            "pos": "VB"
          },
          "transcription": "sit"
        },
        {
          "tags": {
            "pos": "IN"
          },
          "transcription": "around"
        },
        {
          "tags": {
            "pos": "PRP$"
          },
          "transcription": "my"
        },
        {
          "tags": {
            "pos": "NN"
          },
          "transcription": "kitchen"
        },
        {
          "tags": {
            "pos": "JJ"
          },
          "transcription": "table--just"
        },
        {
          "tags": {
            "pos": "NNP"
          },
          "transcription": "Bill"
        },
        {
          "tags": {
            "pos": "NNP"
          },
          "transcription": "Bob"
        },
        {
          "tags": {
            "pos": "NNP"
          },
          "transcription": "Hillary"
        },
        {
          "tags": {
            "pos": "NNP"
          },
          "transcription": "Liddy"
        },
        {
          "tags": {
            "pos": "CC"
          },
          "transcription": "and"
        },
        {
          "tags": {
            "pos": "PRP"
          },
          "transcription": "me"
        }
      ]
    },
    {
      "words": [
        {
          "tags": {
            "pos": "RB"
          },
          "transcription": "Actually"
        },
        {
          "tags": {
            "pos": "PRP"
          },
          "transcription": "I"
        },
        {
          "tags": {
            "pos": "MD"
          },
          "transcription": "might"
        },
        {
          "tags": {
            "pos": "VB"
          },
          "transcription": "be"
        },
        {
          "tags": {
            "pos": "VBN"
          },
          "transcription": "pressed"
        },
        {
          "tags": {
            "pos": "IN"
          },
          "transcription": "for"
        },
        {
          "tags": {
            "pos": "NN"
          },
          "transcription": "time"
        },
        {
          "tags": {
            "pos": "IN"
          },
          "transcription": "so"
        },
        {
          "tags": {
            "pos": "PRP"
          },
          "transcription": "it"
        },
        {
          "tags": {
            "pos": "MD"
          },
          "transcription": "would"
        },
        {
          "tags": {
            "pos": "VB"
          },
          "transcription": "work"
        },
        {
          "tags": {
            "pos": "JJR"
          },
          "transcription": "better"
        },
        {
          "tags": {
            "pos": "IN"
          },
          "transcription": "if"
        },
        {
          "tags": {
            "pos": "PRP"
          },
          "transcription": "we"
        },
        {
          "tags": {
            "pos": "MD"
          },
          "transcription": "could"
        },
        {
          "tags": {
            "pos": "VB"
          },
          "transcription": "stand"
        },
        {
          "tags": {
            "pos": "IN"
          },
          "transcription": "around"
        },
        {
          "tags": {
            "pos": "PRP$"
          },
          "transcription": "my"
        },
        {
          "tags": {
            "pos": "NN"
          },
          "transcription": "kitchen"
        },
        {
          "tags": {
            "pos": "NN"
          },
          "transcription": "table"
        },
        {
          "tags": {
            "pos": "IN"
          },
          "transcription": "while"
        },
        {
          "tags": {
            "pos": "PRP"
          },
          "transcription": "I"
        },
        {
          "tags": {
            "pos": "VBP"
          },
          "transcription": "chug"
        },
        {
          "tags": {
            "pos": "PDT"
          },
          "transcription": "half"
        },
        {
          "tags": {
            "pos": "DT"
          },
          "transcription": "a"
        },
        {
          "tags": {
            "pos": "NN"
          },
          "transcription": "pint"
        },
        {
          "tags": {
            "pos": "IN"
          },
          "transcription": "of"
        },
        {
          "tags": {
            "pos": "NN"
          },
          "transcription": "takeout"
        },
        {
          "tags": {
            "pos": "NNP"
          },
          "transcription": "Szechwan"
        },
        {
          "tags": {
            "pos": "NN"
          },
          "transcription": "shrimp"
        },
        {
          "tags": {
            "pos": "DT"
          },
          "transcription": "no"
        },
        {
          "tags": {
            "pos": "NNP"
          },
          "transcription": "MSG"
        },
        {
          "tags": {
            "pos": "IN"
          },
          "transcription": "before"
        },
        {
          "tags": {
            "pos": "PRP"
          },
          "transcription": "I"
        },
        {
          "tags": {
            "pos": "VBP"
          },
          "transcription": "run"
        },
        {
          "tags": {
            "pos": "IN"
          },
          "transcription": "out"
        },
        {
          "tags": {
            "pos": "TO"
          },
          "transcription": "to"
        },
        {
          "tags": {
            "pos": "VB"
          },
          "transcription": "meet"
        },
        {
          "tags": {
            "pos": "DT"
          },
          "transcription": "a"
        },
        {
          "tags": {
            "pos": "NN"
          },
          "transcription": "friend"
        },
        {
          "tags": {
            "pos": "WP"
          },
          "transcription": "who"
        },
        {
          "tags": {
            "pos": "VBZ"
          },
          "transcription": "has"
        },
        {
          "tags": {
            "pos": "RB"
          },
          "transcription": "also"
        },
        {
          "tags": {
            "pos": "VBN"
          },
          "transcription": "come"
        },
        {
          "tags": {
            "pos": "NN"
          },
          "transcription": "home"
        },
        {
          "tags": {
            "pos": "RB"
          },
          "transcription": "late"
        },
        {
          "tags": {
            "pos": "IN"
          },
          "transcription": "from"
        },
        {
          "tags": {
            "pos": "NN"
          },
          "transcription": "work"
        },
        {
          "tags": {
            "pos": "TO"
          },
          "transcription": "to"
        },
        {
          "tags": {
            "pos": "NN"
          },
          "transcription": "gulp"
        },
        {
          "tags": {
            "pos": "NN"
          },
          "transcription": "something"
        },
        {
          "tags": {
            "pos": "IN"
          },
          "transcription": "before"
        },
        {
          "tags": {
            "pos": "PRP"
          },
          "transcription": "we"
        },
        {
          "tags": {
            "pos": "VBP"
          },
          "transcription": "connect"
        },
        {
          "tags": {
            "pos": "IN"
          },
          "transcription": "for"
        },
        {
          "tags": {
            "pos": "DT"
          },
          "transcription": "a"
        },
        {
          "tags": {
            "pos": "NN"
          },
          "transcription": "concert"
        },
        {
          "tags": {
            "pos": "CC"
          },
          "transcription": "and"
        },
        {
          "tags": {
            "pos": "NN"
          },
          "transcription": "dinner"
        }
      ]
    },
    {
      "words": [
        {
          "tags": {
            "pos": "CC"
          },
          "transcription": "But"
        },
        {
          "tags": {
            "pos": "IN"
          },
          "transcription": "in"
        },
        {
          "tags": {
            "pos": "PRP$"
          },
          "transcription": "my"
        },
        {
          "tags": {
            "pos": "JJ"
          },
          "transcription": "spare"
        },
        {
          "tags": {
            "pos": "CD"
          },
          "transcription": "10"
        },
        {
          "tags": {
            "pos": "NNS"
          },
          "transcription": "minutes"
        },
        {
          "tags": {
            "pos": "IN"
          },
          "transcription": "while"
        },
        {
          "tags": {
            "pos": "PRP"
          },
          "transcription": "I"
        },
        {
          "tags": {
            "pos": "VBP"
          },
          "transcription": "have"
        },
        {
          "tags": {
            "pos": "PDT"
          },
          "transcription": "all"
        },
        {
          "tags": {
            "pos": "DT"
          },
          "transcription": "the"
        },
        {
          "tags": {
            "pos": "JJ"
          },
          "transcription": "major"
        },
        {
          "tags": {
            "pos": "JJ"
          },
          "transcription": "presidential"
        },
        {
          "tags": {
            "pos": "NNS"
          },
          "transcription": "candidates"
        },
        {
          "tags": {
            "pos": "CC"
          },
          "transcription": "and"
        },
        {
          "tags": {
            "pos": "PRP$"
          },
          "transcription": "their"
        },
        {
          "tags": {
            "pos": "JJ"
          },
          "transcription": "significant"
        },
        {
          "tags": {
            "pos": "CC"
          },
          "transcription": "but"
        },
        {
          "tags": {
            "pos": "JJ"
          },
          "transcription": "loving"
        },
        {
          "tags": {
            "pos": "NNS"
          },
          "transcription": "spouses"
        },
        {
          "tags": {
            "pos": "VBD"
          },
          "transcription": "gathered"
        },
        {
          "tags": {
            "pos": "PRP"
          },
          "transcription": "I"
        },
        {
          "tags": {
            "pos": "MD"
          },
          "transcription": "'d"
        },
        {
          "tags": {
            "pos": "VB"
          },
          "transcription": "tackle"
        },
        {
          "tags": {
            "pos": "WP"
          },
          "transcription": "what"
        },
        {
          "tags": {
            "pos": "DT"
          },
          "transcription": "the"
        },
        {
          "tags": {
            "pos": "JJ"
          },
          "transcription": "first"
        },
        {
          "tags": {
            "pos": "NN"
          },
          "transcription": "lady"
        },
        {
          "tags": {
            "pos": "VBD"
          },
          "transcription": "told"
        },
        {
          "tags": {
            "pos": "DT"
          },
          "transcription": "the"
        },
        {
          "tags": {
            "pos": "NNP"
          },
          "transcription": "Democratic"
        },
        {
          "tags": {
            "pos": "NNP"
          },
          "transcription": "National"
        },
        {
          "tags": {
            "pos": "NNP"
          },
          "transcription": "Convention"
        }
      ]
    },
    {
      "words": [
        {
          "tags": {
            "pos": "NNS"
          },
          "transcription": "matters"
        },
        {
          "tags": {
            "pos": "JJS"
          },
          "transcription": "most"
        },
        {
          "tags": {
            "pos": "IN"
          },
          "transcription": "in"
        },
        {
          "tags": {
            "pos": "PRP$"
          },
          "transcription": "our"
        },
        {
          "tags": {
            "pos": "NNS"
          },
          "transcription": "lives"
        },
        {
          "tags": {
            "pos": "CC"
          },
          "transcription": "and"
        },
        {
          "tags": {
            "pos": "IN"
          },
          "transcription": "in"
        },
        {
          "tags": {
            "pos": "PRP$"
          },
          "transcription": "our"
        },
        {
          "tags": {
            "pos": "JJ"
          },
          "transcription": "nation--children"
        },
        {
          "tags": {
            "pos": "CC"
          },
          "transcription": "and"
        },
        {
          "tags": {
            "pos": "NNS"
          },
          "transcription": "families"
        }
      ]
    },
    {
      "words": [
        {
          "tags": {
            "pos": "IN"
          },
          "transcription": "Because"
        },
        {
          "tags": {
            "pos": "DT"
          },
          "transcription": "the"
        },
        {
          "tags": {
            "pos": "NNPS"
          },
          "transcription": "Democrats"
        },
        {
          "tags": {
            "pos": "VBD"
          },
          "transcription": "were"
        },
        {
          "tags": {
            "pos": "RB"
          },
          "transcription": "mostly"
        }
      ]
    },
    {
      "words": [
        {
          "tags": {
            "pos": "VBG"
          },
          "transcription": "triangulating"
        }
      ]
    },
    {
      "words": [
        {
          "tags": {
            "pos": "PRP$"
          },
          "transcription": "their"
        },
        {
          "tags": {
            "pos": "NNS"
          },
          "transcription": "children"
        },
        {
          "tags": {
            "pos": "CC"
          },
          "transcription": "and"
        },
        {
          "tags": {
            "pos": "NNS"
          },
          "transcription": "families"
        },
        {
          "tags": {
            "pos": "NN"
          },
          "transcription": "message"
        },
        {
          "tags": {
            "pos": "TO"
          },
          "transcription": "to"
        },
        {
          "tags": {
            "pos": "NN"
          },
          "transcription": "duel"
        },
        {
          "tags": {
            "pos": "IN"
          },
          "transcription": "with"
        },
        {
          "tags": {
            "pos": "DT"
          },
          "transcription": "the"
        },
        {
          "tags": {
            "pos": "JJ"
          },
          "transcription": "similar"
        },
        {
          "tags": {
            "pos": "NN"
          },
          "transcription": "message"
        },
        {
          "tags": {
            "pos": "WDT"
          },
          "transcription": "that"
        },
        {
          "tags": {
            "pos": "VBD"
          },
          "transcription": "came"
        },
        {
          "tags": {
            "pos": "IN"
          },
          "transcription": "out"
        },
        {
          "tags": {
            "pos": "IN"
          },
          "transcription": "of"
        },
        {
          "tags": {
            "pos": "DT"
          },
          "transcription": "the"
        },
        {
          "tags": {
            "pos": "NNP"
          },
          "transcription": "Republican"
        },
        {
          "tags": {
            "pos": "NNP"
          },
          "transcription": "National"
        },
        {
          "tags": {
            "pos": "NNP"
          },
          "transcription": "Convention"
        },
        {
          "tags": {
            "pos": "DT"
          },
          "transcription": "a"
        },
        {
          "tags": {
            "pos": "JJ"
          },
          "transcription": "few"
        },
        {
          "tags": {
            "pos": "NNS"
          },
          "transcription": "weeks"
        },
        {
          "tags": {
            "pos": "RB"
          },
          "transcription": "before"
        },
        {
          "tags": {
            "pos": "PRP"
          },
          "transcription": "I"
        },
        {
          "tags": {
            "pos": "MD"
          },
          "transcription": "'d"
        },
        {
          "tags": {
            "pos": "VB"
          },
          "transcription": "tackle"
        },
        {
          "tags": {
            "pos": "NNP"
          },
          "transcription": "Sen"
        }
      ]
    },
    {
      "words": [
        {
          "tags": {
            "pos": "NNP"
          },
          "transcription": "Dole"
        },
        {
          "tags": {
            "pos": "JJ"
          },
          "transcription": "next"
        }
      ]
    },
    {
      "words": [
        {
          "tags": {
            "pos": "NNP"
          },
          "transcription": "Dole"
        },
        {
          "tags": {
            "pos": "VBZ"
          },
          "transcription": "imagines"
        },
        {
          "tags": {
            "pos": "PRP"
          },
          "transcription": "himself"
        },
        {
          "tags": {
            "pos": "DT"
          },
          "transcription": "a"
        },
        {
          "tags": {
            "pos": "NN"
          },
          "transcription": "bridge"
        }
      ]
    },
    {
      "words": [
        {
          "tags": {
            "pos": "TO"
          },
          "transcription": "to"
        },
        {
          "tags": {
            "pos": "DT"
          },
          "transcription": "a"
        },
        {
          "tags": {
            "pos": "NN"
          },
          "transcription": "time"
        },
        {
          "tags": {
            "pos": "IN"
          },
          "transcription": "of"
        },
        {
          "tags": {
            "pos": "NN"
          },
          "transcription": "tranquillity"
        },
        {
          "tags": {
            "pos": "NN"
          },
          "transcription": "faith"
        },
        {
          "tags": {
            "pos": "CC"
          },
          "transcription": "and"
        },
        {
          "tags": {
            "pos": "NN"
          },
          "transcription": "confidence"
        }
      ]
    },
    {
      "words": [
        {
          "tags": {
            "pos": "IN"
          },
          "transcription": "so"
        },
        {
          "tags": {
            "pos": "PRP"
          },
          "transcription": "I"
        },
        {
          "tags": {
            "pos": "MD"
          },
          "transcription": "'d"
        },
        {
          "tags": {
            "pos": "VB"
          },
          "transcription": "ask"
        },
        {
          "tags": {
            "pos": "PRP"
          },
          "transcription": "him"
        },
        {
          "tags": {
            "pos": "TO"
          },
          "transcription": "to"
        },
        {
          "tags": {
            "pos": "WP"
          },
          "transcription": "what"
        },
        {
          "tags": {
            "pos": "NN"
          },
          "transcription": "village"
        },
        {
          "tags": {
            "pos": "CC"
          },
          "transcription": "or"
        },
        {
          "tags": {
            "pos": "NNP"
          },
          "transcription": "America"
        },
        {
          "tags": {
            "pos": "PRP$"
          },
          "transcription": "his"
        },
        {
          "tags": {
            "pos": "NN"
          },
          "transcription": "bridge"
        },
        {
          "tags": {
            "pos": "MD"
          },
          "transcription": "will"
        },
        {
          "tags": {
            "pos": "VB"
          },
          "transcription": "carry"
        },
        {
          "tags": {
            "pos": "NNS"
          },
          "transcription": "folks"
        },
        {
          "tags": {
            "pos": "IN"
          },
          "transcription": "like"
        },
        {
          "tags": {
            "pos": "JJ"
          },
          "transcription": "me--seeing"
        },
        {
          "tags": {
            "pos": "IN"
          },
          "transcription": "as"
        },
        {
          "tags": {
            "pos": "NNS"
          },
          "transcription": "folks"
        },
        {
          "tags": {
            "pos": "IN"
          },
          "transcription": "like"
        },
        {
          "tags": {
            "pos": "PRP"
          },
          "transcription": "me"
        },
        {
          "tags": {
            "pos": "VBP"
          },
          "transcription": "do"
        },
        {
          "tags": {
            "pos": "RB"
          },
          "transcription": "n't"
        },
        {
          "tags": {
            "pos": "VB"
          },
          "transcription": "have"
        },
        {
          "tags": {
            "pos": "NNS"
          },
          "transcription": "children"
        },
        {
          "tags": {
            "pos": "CC"
          },
          "transcription": "or"
        },
        {
          "tags": {
            "pos": "JJ"
          },
          "transcription": "traditional"
        },
        {
          "tags": {
            "pos": "NNS"
          },
          "transcription": "families"
        }
      ]
    },
    {
      "words": [
        {
          "tags": {
            "pos": "NNP"
          },
          "transcription": "Soccer"
        },
        {
          "tags": {
            "pos": "NNP"
          },
          "transcription": "Moms"
        }
      ]
    },
    {
      "words": [
        {
          "tags": {
            "pos": "VBP"
          },
          "transcription": "are"
        },
        {
          "tags": {
            "pos": "JJ"
          },
          "transcription": "desirable"
        },
        {
          "tags": {
            "pos": "NNS"
          },
          "transcription": "voters"
        },
        {
          "tags": {
            "pos": "DT"
          },
          "transcription": "this"
        },
        {
          "tags": {
            "pos": "NN"
          },
          "transcription": "election"
        },
        {
          "tags": {
            "pos": "NN"
          },
          "transcription": "year"
        },
        {
          "tags": {
            "pos": "CC"
          },
          "transcription": "but"
        },
        {
          "tags": {
            "pos": "JJ"
          },
          "transcription": "single"
        },
        {
          "tags": {
            "pos": "NNS"
          },
          "transcription": "women"
        },
        {
          "tags": {
            "pos": "VBP"
          },
          "transcription": "are"
        },
        {
          "tags": {
            "pos": "RP"
          },
          "transcription": "off"
        },
        {
          "tags": {
            "pos": "DT"
          },
          "transcription": "the"
        },
        {
          "tags": {
            "pos": "JJ"
          },
          "transcription": "charts--just"
        },
        {
          "tags": {
            "pos": "DT"
          },
          "transcription": "a"
        },
        {
          "tags": {
            "pos": "VBN"
          },
          "transcription": "rung"
        },
        {
          "tags": {
            "pos": "IN"
          },
          "transcription": "below"
        },
        {
          "tags": {
            "pos": "JJ"
          },
          "transcription": "homosexual"
        },
        {
          "tags": {
            "pos": "NNS"
          },
          "transcription": "men"
        },
        {
          "tags": {
            "pos": "WP"
          },
          "transcription": "who"
        },
        {
          "tags": {
            "pos": "VBP"
          },
          "transcription": "are"
        },
        {
          "tags": {
            "pos": "VBG"
          },
          "transcription": "contemplating"
        },
        {
          "tags": {
            "pos": "CC"
          },
          "transcription": "but"
        },
        {
          "tags": {
            "pos": "VBD"
          },
          "transcription": "denied"
        },
        {
          "tags": {
            "pos": "NN"
          },
          "transcription": "marriage"
        }
      ]
    },
    {
      "words": [
        {
          "tags": {
            "pos": "IN"
          },
          "transcription": "At"
        },
        {
          "tags": {
            "pos": "PRP$"
          },
          "transcription": "our"
        },
        {
          "tags": {
            "pos": "NN"
          },
          "transcription": "kitchen"
        },
        {
          "tags": {
            "pos": "NN"
          },
          "transcription": "confab"
        },
        {
          "tags": {
            "pos": "("
          },
          "transcription": "("
        },
        {
          "tags": {
            "pos": "WDT"
          },
          "transcription": "which"
        },
        {
          "tags": {
            "pos": "MD"
          },
          "transcription": "would"
        },
        {
          "tags": {
            "pos": "RB"
          },
          "transcription": "probably"
        },
        {
          "tags": {
            "pos": "PRP"
          },
          "transcription": "I"
        },
        {
          "tags": {
            "pos": "VBP"
          },
          "transcription": "'m"
        },
        {
          "tags": {
            "pos": "JJ"
          },
          "transcription": "sorry"
        },
        {
          "tags": {
            "pos": "TO"
          },
          "transcription": "to"
        },
        {
          "tags": {
            "pos": "VB"
          },
          "transcription": "say"
        },
        {
          "tags": {
            "pos": "VB"
          },
          "transcription": "take"
        },
        {
          "tags": {
            "pos": "NN"
          },
          "transcription": "place"
        },
        {
          "tags": {
            "pos": "RB"
          },
          "transcription": "not"
        },
        {
          "tags": {
            "pos": "IN"
          },
          "transcription": "around"
        },
        {
          "tags": {
            "pos": "DT"
          },
          "transcription": "the"
        },
        {
          "tags": {
            "pos": "JJ"
          },
          "transcription": "table--since"
        },
        {
          "tags": {
            "pos": "JJ"
          },
          "transcription": "many"
        },
        {
          "tags": {
            "pos": "JJ"
          },
          "transcription": "single"
        },
        {
          "tags": {
            "pos": "NNS"
          },
          "transcription": "people"
        },
        {
          "tags": {
            "pos": "JJ"
          },
          "transcription": "live"
        },
        {
          "tags": {
            "pos": "IN"
          },
          "transcription": "in"
        },
        {
          "tags": {
            "pos": "NNS"
          },
          "transcription": "apartments"
        },
        {
          "tags": {
            "pos": "WRB"
          },
          "transcription": "where"
        },
        {
          "tags": {
            "pos": "DT"
          },
          "transcription": "the"
        },
        {
          "tags": {
            "pos": "NN"
          },
          "transcription": "kitchen"
        },
        {
          "tags": {
            "pos": "VBZ"
          },
          "transcription": "is"
        },
        {
          "tags": {
            "pos": "DT"
          },
          "transcription": "the"
        },
        {
          "tags": {
            "pos": "NN"
          },
          "transcription": "size"
        },
        {
          "tags": {
            "pos": "IN"
          },
          "transcription": "of"
        },
        {
          "tags": {
            "pos": "DT"
          },
          "transcription": "a"
        },
        {
          "tags": {
            "pos": "NN"
          },
          "transcription": "linen"
        },
        {
          "tags": {
            "pos": "JJ"
          },
          "transcription": "closet--but"
        },
        {
          "tags": {
            "pos": "IN"
          },
          "transcription": "around"
        },
        {
          "tags": {
            "pos": "DT"
          },
          "transcription": "the"
        },
        {
          "tags": {
            "pos": "NN"
          },
          "transcription": "counter"
        },
        {
          "tags": {
            "pos": ")"
          },
          "transcription": ")"
        },
        {
          "tags": {
            "pos": "PRP"
          },
          "transcription": "I"
        },
        {
          "tags": {
            "pos": "MD"
          },
          "transcription": "might"
        },
        {
          "tags": {
            "pos": "VB"
          },
          "transcription": "suggest"
        },
        {
          "tags": {
            "pos": "IN"
          },
          "transcription": "that"
        },
        {
          "tags": {
            "pos": "DT"
          },
          "transcription": "the"
        },
        {
          "tags": {
            "pos": "JJ"
          },
          "transcription": "first"
        },
        {
          "tags": {
            "pos": "NN"
          },
          "transcription": "lady"
        },
        {
          "tags": {
            "pos": "VB"
          },
          "transcription": "ask"
        },
        {
          "tags": {
            "pos": "NNP"
          },
          "transcription": "Janet"
        },
        {
          "tags": {
            "pos": "NNP"
          },
          "transcription": "Reno"
        },
        {
          "tags": {
            "pos": "CC"
          },
          "transcription": "or"
        },
        {
          "tags": {
            "pos": "NNP"
          },
          "transcription": "Donna"
        },
        {
          "tags": {
            "pos": "NNP"
          },
          "transcription": "Shalala"
        },
        {
          "tags": {
            "pos": "IN"
          },
          "transcription": "if"
        },
        {
          "tags": {
            "pos": "PRP"
          },
          "transcription": "they"
        },
        {
          "tags": {
            "pos": "RB"
          },
          "transcription": "ever"
        },
        {
          "tags": {
            "pos": "VBP"
          },
          "transcription": "feel"
        },
        {
          "tags": {
            "pos": "VBN"
          },
          "transcription": "stressed"
        },
        {
          "tags": {
            "pos": "IN"
          },
          "transcription": "out"
        },
        {
          "tags": {
            "pos": "CC"
          },
          "transcription": "or"
        },
        {
          "tags": {
            "pos": "JJ"
          },
          "transcription": "over-committed"
        },
        {
          "tags": {
            "pos": "RB"
          },
          "transcription": "even"
        },
        {
          "tags": {
            "pos": "IN"
          },
          "transcription": "though"
        },
        {
          "tags": {
            "pos": "PRP"
          },
          "transcription": "they"
        },
        {
          "tags": {
            "pos": "VBP"
          },
          "transcription": "are"
        },
        {
          "tags": {
            "pos": "RB"
          },
          "transcription": "n't"
        }
      ]
    },
    {
      "words": [
        {
          "tags": {
            "pos": "VBG"
          },
          "transcription": "packing"
        },
        {
          "tags": {
            "pos": "NNS"
          },
          "transcription": "lunches"
        },
        {
          "tags": {
            "pos": "VBG"
          },
          "transcription": "dropping"
        },
        {
          "tags": {
            "pos": "DT"
          },
          "transcription": "the"
        },
        {
          "tags": {
            "pos": "NNS"
          },
          "transcription": "kids"
        },
        {
          "tags": {
            "pos": "IN"
          },
          "transcription": "off"
        },
        {
          "tags": {
            "pos": "IN"
          },
          "transcription": "at"
        },
        {
          "tags": {
            "pos": "NN"
          },
          "transcription": "school"
        },
        {
          "tags": {
            "pos": "CC"
          },
          "transcription": "and"
        },
        {
          "tags": {
            "pos": "VBG"
          },
          "transcription": "going"
        },
        {
          "tags": {
            "pos": "TO"
          },
          "transcription": "to"
        },
        {
          "tags": {
            "pos": "VB"
          },
          "transcription": "work"
        }
      ]
    },
    {
      "words": [
        {
          "tags": {
            "pos": "DT"
          },
          "transcription": "The"
        },
        {
          "tags": {
            "pos": "JJ"
          },
          "transcription": "first"
        },
        {
          "tags": {
            "pos": "NN"
          },
          "transcription": "lady"
        },
        {
          "tags": {
            "pos": "WP"
          },
          "transcription": "who"
        },
        {
          "tags": {
            "pos": "JJ"
          },
          "transcription": "detailed"
        },
        {
          "tags": {
            "pos": "RB"
          },
          "transcription": "so"
        },
        {
          "tags": {
            "pos": "RB"
          },
          "transcription": "eloquently"
        },
        {
          "tags": {
            "pos": "DT"
          },
          "transcription": "the"
        },
        {
          "tags": {
            "pos": "NNS"
          },
          "transcription": "pressures"
        },
        {
          "tags": {
            "pos": "VBN"
          },
          "transcription": "faced"
        },
        {
          "tags": {
            "pos": "IN"
          },
          "transcription": "by"
        },
        {
          "tags": {
            "pos": "VBG"
          },
          "transcription": "working"
        },
        {
          "tags": {
            "pos": "NNS"
          },
          "transcription": "mothers"
        },
        {
          "tags": {
            "pos": "MD"
          },
          "transcription": "might"
        },
        {
          "tags": {
            "pos": "VB"
          },
          "transcription": "be"
        },
        {
          "tags": {
            "pos": "VBN"
          },
          "transcription": "surprised"
        },
        {
          "tags": {
            "pos": "TO"
          },
          "transcription": "to"
        },
        {
          "tags": {
            "pos": "VB"
          },
          "transcription": "know"
        },
        {
          "tags": {
            "pos": "IN"
          },
          "transcription": "that"
        },
        {
          "tags": {
            "pos": "DT"
          },
          "transcription": "the"
        },
        {
          "tags": {
            "pos": "JJ"
          },
          "transcription": "current"
        },
        {
          "tags": {
            "pos": "NN"
          },
          "transcription": "attorney"
        },
        {
          "tags": {
            "pos": "NN"
          },
          "transcription": "general"
        },
        {
          "tags": {
            "pos": "CC"
          },
          "transcription": "and"
        },
        {
          "tags": {
            "pos": "DT"
          },
          "transcription": "the"
        },
        {
          "tags": {
            "pos": "NN"
          },
          "transcription": "secretary"
        },
        {
          "tags": {
            "pos": "IN"
          },
          "transcription": "of"
        },
        {
          "tags": {
            "pos": "DT"
          },
          "transcription": "the"
        },
        {
          "tags": {
            "pos": "NNP"
          },
          "transcription": "Department"
        },
        {
          "tags": {
            "pos": "IN"
          },
          "transcription": "of"
        },
        {
          "tags": {
            "pos": "NNP"
          },
          "transcription": "Health"
        },
        {
          "tags": {
            "pos": "CC"
          },
          "transcription": "and"
        },
        {
          "tags": {
            "pos": "NNP"
          },
          "transcription": "Human"
        },
        {
          "tags": {
            "pos": "NNP"
          },
          "transcription": "Services--working"
        },
        {
          "tags": {
            "pos": "JJ"
          },
          "transcription": "singles--also"
        },
        {
          "tags": {
            "pos": "NN"
          },
          "transcription": "make"
        },
        {
          "tags": {
            "pos": "NN"
          },
          "transcription": "dinner"
        },
        {
          "tags": {
            "pos": "VBP"
          },
          "transcription": "pay"
        },
        {
          "tags": {
            "pos": "DT"
          },
          "transcription": "the"
        },
        {
          "tags": {
            "pos": "NNS"
          },
          "transcription": "bills"
        },
        {
          "tags": {
            "pos": "CC"
          },
          "transcription": "and"
        },
        {
          "tags": {
            "pos": "VBP"
          },
          "transcription": "feel"
        },
        {
          "tags": {
            "pos": "DT"
          },
          "transcription": "a"
        },
        {
          "tags": {
            "pos": "RB"
          },
          "transcription": "little"
        },
        {
          "tags": {
            "pos": "JJ"
          },
          "transcription": "tired"
        },
        {
          "tags": {
            "pos": "WRB"
          },
          "transcription": "when"
        },
        {
          "tags": {
            "pos": "IN"
          },
          "transcription": "on"
        },
        {
          "tags": {
            "pos": "NN"
          },
          "transcription": "top"
        },
        {
          "tags": {
            "pos": "IN"
          },
          "transcription": "of"
        },
        {
          "tags": {
            "pos": "DT"
          },
          "transcription": "all"
        },
        {
          "tags": {
            "pos": "PRP$"
          },
          "transcription": "their"
        },
        {
          "tags": {
            "pos": "JJ"
          },
          "transcription": "other"
        },
        {
          "tags": {
            "pos": "NNS"
          },
          "transcription": "responsibilities"
        },
        {
          "tags": {
            "pos": "PRP"
          },
          "transcription": "they"
        },
        {
          "tags": {
            "pos": "VBP"
          },
          "transcription": "have"
        },
        {
          "tags": {
            "pos": "TO"
          },
          "transcription": "to"
        },
        {
          "tags": {
            "pos": "VB"
          },
          "transcription": "take"
        },
        {
          "tags": {
            "pos": "DT"
          },
          "transcription": "the"
        },
        {
          "tags": {
            "pos": "NN"
          },
          "transcription": "dog"
        },
        {
          "tags": {
            "pos": "TO"
          },
          "transcription": "to"
        },
        {
          "tags": {
            "pos": "DT"
          },
          "transcription": "the"
        },
        {
          "tags": {
            "pos": "NN"
          },
          "transcription": "vet"
        }
      ]
    },
    {
      "words": [
        {
          "tags": {
            "pos": "JJ"
          },
          "transcription": "American"
        },
        {
          "tags": {
            "pos": "NNS"
          },
          "transcription": "politics"
        },
        {
          "tags": {
            "pos": "VBD"
          },
          "transcription": "were"
        },
        {
          "tags": {
            "pos": "DT"
          },
          "transcription": "a"
        },
        {
          "tags": {
            "pos": "JJ"
          },
          "transcription": "little"
        },
        {
          "tags": {
            "pos": "RBR"
          },
          "transcription": "more"
        },
        {
          "tags": {
            "pos": "JJ"
          },
          "transcription": "inclusive"
        },
        {
          "tags": {
            "pos": "WRB"
          },
          "transcription": "when"
        },
        {
          "tags": {
            "pos": "NN"
          },
          "transcription": "campaign"
        },
        {
          "tags": {
            "pos": "NN"
          },
          "transcription": "rhetoric"
        },
        {
          "tags": {
            "pos": "JJ"
          },
          "transcription": "revolved"
        },
        {
          "tags": {
            "pos": "IN"
          },
          "transcription": "around"
        }
      ]
    },
    {
      "words": [
        {
          "tags": {
            "pos": "PRP"
          },
          "transcription": "it"
        },
        {
          "tags": {
            "pos": "VBZ"
          },
          "transcription": "'s"
        },
        {
          "tags": {
            "pos": "DT"
          },
          "transcription": "the"
        },
        {
          "tags": {
            "pos": "NN"
          },
          "transcription": "economy"
        },
        {
          "tags": {
            "pos": "JJ"
          },
          "transcription": "stupid"
        }
      ]
    },
    {
      "words": [
        {
          "tags": {
            "pos": "UH"
          },
          "transcription": "Yes"
        },
        {
          "tags": {
            "pos": "NNPS"
          },
          "transcription": "Americans"
        },
        {
          "tags": {
            "pos": "MD"
          },
          "transcription": "must"
        },
        {
          "tags": {
            "pos": "VB"
          },
          "transcription": "feed"
        },
        {
          "tags": {
            "pos": "PRP$"
          },
          "transcription": "their"
        },
        {
          "tags": {
            "pos": "NNS"
          },
          "transcription": "children"
        },
        {
          "tags": {
            "pos": "CC"
          },
          "transcription": "but"
        },
        {
          "tags": {
            "pos": "NNP"
          },
          "transcription": "Americans--married"
        },
        {
          "tags": {
            "pos": "CC"
          },
          "transcription": "and"
        },
        {
          "tags": {
            "pos": "JJ"
          },
          "transcription": "single--must"
        },
        {
          "tags": {
            "pos": "NN"
          },
          "transcription": "feed"
        },
        {
          "tags": {
            "pos": "PRP"
          },
          "transcription": "themselves"
        },
        {
          "tags": {
            "pos": "RB"
          },
          "transcription": "too"
        }
      ]
    },
    {
      "words": [
        {
          "tags": {
            "pos": "CC"
          },
          "transcription": "But"
        },
        {
          "tags": {
            "pos": "RB"
          },
          "transcription": "once"
        },
        {
          "tags": {
            "pos": "DT"
          },
          "transcription": "the"
        },
        {
          "tags": {
            "pos": "NNPS"
          },
          "transcription": "Republicans"
        },
        {
          "tags": {
            "pos": "CC"
          },
          "transcription": "and"
        },
        {
          "tags": {
            "pos": "NNPS"
          },
          "transcription": "Democrats"
        },
        {
          "tags": {
            "pos": "VBD"
          },
          "transcription": "decided"
        },
        {
          "tags": {
            "pos": "IN"
          },
          "transcription": "that"
        },
        {
          "tags": {
            "pos": "DT"
          },
          "transcription": "the"
        },
        {
          "tags": {
            "pos": "NN"
          },
          "transcription": "goal"
        },
        {
          "tags": {
            "pos": "IN"
          },
          "transcription": "of"
        },
        {
          "tags": {
            "pos": "DT"
          },
          "transcription": "all"
        },
        {
          "tags": {
            "pos": "NNPS"
          },
          "transcription": "Americans"
        },
        {
          "tags": {
            "pos": "MD"
          },
          "transcription": "must"
        },
        {
          "tags": {
            "pos": "VB"
          },
          "transcription": "be"
        },
        {
          "tags": {
            "pos": "NN"
          },
          "transcription": "family"
        },
        {
          "tags": {
            "pos": "CC"
          },
          "transcription": "and"
        },
        {
          "tags": {
            "pos": "NN"
          },
          "transcription": "child"
        },
        {
          "tags": {
            "pos": "NN"
          },
          "transcription": "rearing"
        },
        {
          "tags": {
            "pos": "DT"
          },
          "transcription": "an"
        },
        {
          "tags": {
            "pos": "JJ"
          },
          "transcription": "unpremeditated"
        },
        {
          "tags": {
            "pos": "JJ"
          },
          "transcription": "exclusionary"
        },
        {
          "tags": {
            "pos": "NN"
          },
          "transcription": "process"
        },
        {
          "tags": {
            "pos": "VBD"
          },
          "transcription": "began"
        }
      ]
    },
    {
      "words": [
        {
          "tags": {
            "pos": "IN"
          },
          "transcription": "At"
        },
        {
          "tags": {
            "pos": "DT"
          },
          "transcription": "the"
        },
        {
          "tags": {
            "pos": "NNP"
          },
          "transcription": "Republican"
        },
        {
          "tags": {
            "pos": "NNP"
          },
          "transcription": "Convention"
        },
        {
          "tags": {
            "pos": "NNP"
          },
          "transcription": "Dole"
        },
        {
          "tags": {
            "pos": "VBD"
          },
          "transcription": "urged"
        },
        {
          "tags": {
            "pos": "PRP"
          },
          "transcription": "us"
        },
        {
          "tags": {
            "pos": "TO"
          },
          "transcription": "to"
        },
        {
          "tags": {
            "pos": "VB"
          },
          "transcription": "practice"
        }
      ]
    },
    {
      "words": [
        {
          "tags": {
            "pos": "JJ"
          },
          "transcription": "right"
        },
        {
          "tags": {
            "pos": "NN"
          },
          "transcription": "conduct"
        }
      ]
    },
    {
      "words": [
        {
          "tags": {
            "pos": "DT"
          },
          "transcription": "every"
        },
        {
          "tags": {
            "pos": "NN"
          },
          "transcription": "day"
        }
      ]
    },
    {
      "words": [
        {
          "tags": {
            "pos": "RB"
          },
          "transcription": "Well"
        },
        {
          "tags": {
            "pos": "PRP"
          },
          "transcription": "it"
        },
        {
          "tags": {
            "pos": "VBZ"
          },
          "transcription": "'s"
        },
        {
          "tags": {
            "pos": "RB"
          },
          "transcription": "pretty"
        },
        {
          "tags": {
            "pos": "JJ"
          },
          "transcription": "hard"
        },
        {
          "tags": {
            "pos": "TO"
          },
          "transcription": "to"
        },
        {
          "tags": {
            "pos": "VB"
          },
          "transcription": "practice"
        }
      ]
    },
    {
      "words": [
        {
          "tags": {
            "pos": "JJ"
          },
          "transcription": "right"
        },
        {
          "tags": {
            "pos": "NN"
          },
          "transcription": "conduct"
        }
      ]
    },
    {
      "words": [
        {
          "tags": {
            "pos": "WRB"
          },
          "transcription": "when"
        },
        {
          "tags": {
            "pos": "DT"
          },
          "transcription": "the"
        },
        {
          "tags": {
            "pos": "JJ"
          },
          "transcription": "very"
        },
        {
          "tags": {
            "pos": "NN"
          },
          "transcription": "fabric"
        },
        {
          "tags": {
            "pos": "IN"
          },
          "transcription": "of"
        },
        {
          "tags": {
            "pos": "PRP$"
          },
          "transcription": "your"
        },
        {
          "tags": {
            "pos": "JJ"
          },
          "transcription": "personal"
        },
        {
          "tags": {
            "pos": "NN"
          },
          "transcription": "life"
        },
        {
          "tags": {
            "pos": "VBZ"
          },
          "transcription": "is"
        },
        {
          "tags": {
            "pos": "VBN"
          },
          "transcription": "judged"
        },
        {
          "tags": {
            "pos": "TO"
          },
          "transcription": "to"
        },
        {
          "tags": {
            "pos": "VB"
          },
          "transcription": "be"
        },
        {
          "tags": {
            "pos": "JJ"
          },
          "transcription": "second-rate"
        }
      ]
    },
    {
      "words": [
        {
          "tags": {
            "pos": "CC"
          },
          "transcription": "But"
        },
        {
          "tags": {
            "pos": "PRP"
          },
          "transcription": "it"
        },
        {
          "tags": {
            "pos": "VBZ"
          },
          "transcription": "'s"
        },
        {
          "tags": {
            "pos": "RB"
          },
          "transcription": "not"
        },
        {
          "tags": {
            "pos": "RB"
          },
          "transcription": "too"
        },
        {
          "tags": {
            "pos": "JJ"
          },
          "transcription": "late"
        },
        {
          "tags": {
            "pos": "TO"
          },
          "transcription": "to"
        },
        {
          "tags": {
            "pos": "VB"
          },
          "transcription": "redeem"
        },
        {
          "tags": {
            "pos": "JJ"
          },
          "transcription": "single"
        },
        {
          "tags": {
            "pos": "NNS"
          },
          "transcription": "nonparents"
        }
      ]
    },
    {
      "words": [
        {
          "tags": {
            "pos": "PRP"
          },
          "transcription": "We"
        },
        {
          "tags": {
            "pos": "MD"
          },
          "transcription": "could"
        },
        {
          "tags": {
            "pos": "VB"
          },
          "transcription": "change"
        },
        {
          "tags": {
            "pos": "DT"
          },
          "transcription": "the"
        },
        {
          "tags": {
            "pos": "NN"
          },
          "transcription": "tax"
        },
        {
          "tags": {
            "pos": "NN"
          },
          "transcription": "code"
        },
        {
          "tags": {
            "pos": "TO"
          },
          "transcription": "to"
        },
        {
          "tags": {
            "pos": "VB"
          },
          "transcription": "deter"
        },
        {
          "tags": {
            "pos": "PRP$"
          },
          "transcription": "their"
        },
        {
          "tags": {
            "pos": "NN"
          },
          "transcription": "behavior"
        },
        {
          "tags": {
            "pos": "("
          },
          "transcription": "("
        },
        {
          "tags": {
            "pos": "CC"
          },
          "transcription": "and"
        },
        {
          "tags": {
            "pos": "VB"
          },
          "transcription": "balance"
        },
        {
          "tags": {
            "pos": "DT"
          },
          "transcription": "the"
        },
        {
          "tags": {
            "pos": "NN"
          },
          "transcription": "budget"
        },
        {
          "tags": {
            "pos": ")"
          },
          "transcription": ")"
        },
        {
          "tags": {
            "pos": "IN"
          },
          "transcription": "by"
        },
        {
          "tags": {
            "pos": "NN"
          },
          "transcription": "slapping"
        },
        {
          "tags": {
            "pos": "DT"
          },
          "transcription": "a"
        },
        {
          "tags": {
            "pos": "CD"
          },
          "transcription": "15"
        },
        {
          "tags": {
            "pos": "NN"
          },
          "transcription": "percent"
        },
        {
          "tags": {
            "pos": "NN"
          },
          "transcription": "tax"
        },
        {
          "tags": {
            "pos": "NN"
          },
          "transcription": "hike"
        },
        {
          "tags": {
            "pos": "IN"
          },
          "transcription": "on"
        },
        {
          "tags": {
            "pos": "DT"
          },
          "transcription": "every"
        },
        {
          "tags": {
            "pos": "NNP"
          },
          "transcription": "American"
        },
        {
          "tags": {
            "pos": "WP"
          },
          "transcription": "who"
        },
        {
          "tags": {
            "pos": "VBZ"
          },
          "transcription": "has"
        },
        {
          "tags": {
            "pos": "RB"
          },
          "transcription": "not"
        },
        {
          "tags": {
            "pos": "JJ"
          },
          "transcription": "procreated"
        },
        {
          "tags": {
            "pos": "CC"
          },
          "transcription": "and"
        },
        {
          "tags": {
            "pos": "VBN"
          },
          "transcription": "married"
        }
      ]
    },
    {
      "words": [
        {
          "tags": {
            "pos": "("
          },
          "transcription": "("
        },
        {
          "tags": {
            "pos": "VBP"
          },
          "transcription": "Are"
        },
        {
          "tags": {
            "pos": "PRP"
          },
          "transcription": "you"
        },
        {
          "tags": {
            "pos": "VBG"
          },
          "transcription": "listening"
        },
        {
          "tags": {
            "pos": "NNP"
          },
          "transcription": "Mr"
        }
      ]
    },
    {
      "words": [
        {
          "tags": {
            "pos": "NNP"
          },
          "transcription": "Dole"
        }
      ]
    },
    {
      "words": [
        {
          "tags": {
            "pos": "PRP"
          },
          "transcription": "You"
        },
        {
          "tags": {
            "pos": "MD"
          },
          "transcription": "could"
        },
        {
          "tags": {
            "pos": "RB"
          },
          "transcription": "even"
        },
        {
          "tags": {
            "pos": "VB"
          },
          "transcription": "punish"
        },
        {
          "tags": {
            "pos": "DT"
          },
          "transcription": "the"
        },
        {
          "tags": {
            "pos": "NNS"
          },
          "transcription": "teachers"
        }
      ]
    },
    {
      "words": [
        {
          "tags": {
            "pos": "NNS"
          },
          "transcription": "unions"
        },
        {
          "tags": {
            "pos": "IN"
          },
          "transcription": "for"
        },
        {
          "tags": {
            "pos": "PRP$"
          },
          "transcription": "their"
        },
        {
          "tags": {
            "pos": "JJ"
          },
          "transcription": "sinful"
        },
        {
          "tags": {
            "pos": "NNS"
          },
          "transcription": "ways"
        },
        {
          "tags": {
            "pos": "IN"
          },
          "transcription": "with"
        },
        {
          "tags": {
            "pos": "DT"
          },
          "transcription": "a"
        },
        {
          "tags": {
            "pos": "CD"
          },
          "transcription": "15"
        },
        {
          "tags": {
            "pos": "NN"
          },
          "transcription": "percent"
        },
        {
          "tags": {
            "pos": "NN"
          },
          "transcription": "tax"
        },
        {
          "tags": {
            "pos": "NN"
          },
          "transcription": "hike"
        },
        {
          "tags": {
            "pos": "IN"
          },
          "transcription": "of"
        },
        {
          "tags": {
            "pos": "PRP$"
          },
          "transcription": "their"
        },
        {
          "tags": {
            "pos": "JJ"
          },
          "transcription": "own"
        }
      ]
    },
    {
      "words": [
        {
          "tags": {
            "pos": "NNP"
          },
          "transcription": "Single"
        },
        {
          "tags": {
            "pos": "NN"
          },
          "transcription": "nonparent"
        },
        {
          "tags": {
            "pos": "NNS"
          },
          "transcription": "members"
        },
        {
          "tags": {
            "pos": "IN"
          },
          "transcription": "of"
        },
        {
          "tags": {
            "pos": "DT"
          },
          "transcription": "these"
        },
        {
          "tags": {
            "pos": "NNS"
          },
          "transcription": "unions"
        },
        {
          "tags": {
            "pos": "MD"
          },
          "transcription": "could"
        },
        {
          "tags": {
            "pos": "VB"
          },
          "transcription": "be"
        },
        {
          "tags": {
            "pos": "VBN"
          },
          "transcription": "slapped"
        },
        {
          "tags": {
            "pos": "IN"
          },
          "transcription": "with"
        },
        {
          "tags": {
            "pos": "DT"
          },
          "transcription": "a"
        },
        {
          "tags": {
            "pos": "CD"
          },
          "transcription": "30"
        },
        {
          "tags": {
            "pos": "NN"
          },
          "transcription": "percent"
        },
        {
          "tags": {
            "pos": "NN"
          },
          "transcription": "tax"
        },
        {
          "tags": {
            "pos": "NN"
          },
          "transcription": "hike"
        }
      ]
    },
    {
      "words": [
        {
          "tags": {
            "pos": ")"
          },
          "transcription": ")"
        },
        {
          "tags": {
            "pos": "WRB"
          },
          "transcription": "Why"
        },
        {
          "tags": {
            "pos": "VBP"
          },
          "transcription": "are"
        },
        {
          "tags": {
            "pos": "JJ"
          },
          "transcription": "single"
        },
        {
          "tags": {
            "pos": "NNS"
          },
          "transcription": "people"
        },
        {
          "tags": {
            "pos": "VBP"
          },
          "transcription": "are"
        },
        {
          "tags": {
            "pos": "RB"
          },
          "transcription": "so"
        },
        {
          "tags": {
            "pos": "JJ"
          },
          "transcription": "vilified"
        }
      ]
    },
    {
      "words": [
        {
          "tags": {
            "pos": "JJ"
          },
          "transcription": "Many"
        },
        {
          "tags": {
            "pos": "IN"
          },
          "transcription": "of"
        },
        {
          "tags": {
            "pos": "PRP"
          },
          "transcription": "them"
        },
        {
          "tags": {
            "pos": "VBP"
          },
          "transcription": "have"
        },
        {
          "tags": {
            "pos": "JJR"
          },
          "transcription": "more"
        },
        {
          "tags": {
            "pos": "NN"
          },
          "transcription": "time"
        },
        {
          "tags": {
            "pos": "IN"
          },
          "transcription": "than"
        },
        {
          "tags": {
            "pos": "DT"
          },
          "transcription": "the"
        },
        {
          "tags": {
            "pos": "JJ"
          },
          "transcription": "married-with-children"
        },
        {
          "tags": {
            "pos": "NN"
          },
          "transcription": "crowd"
        },
        {
          "tags": {
            "pos": "TO"
          },
          "transcription": "to"
        },
        {
          "tags": {
            "pos": "VB"
          },
          "transcription": "contribute"
        },
        {
          "tags": {
            "pos": "TO"
          },
          "transcription": "to"
        },
        {
          "tags": {
            "pos": "DT"
          },
          "transcription": "the"
        },
        {
          "tags": {
            "pos": "NN"
          },
          "transcription": "community"
        },
        {
          "tags": {
            "pos": ":"
          },
          "transcription": ":"
        },
        {
          "tags": {
            "pos": "PRP"
          },
          "transcription": "I"
        },
        {
          "tags": {
            "pos": "VBP"
          },
          "transcription": "wonder"
        },
        {
          "tags": {
            "pos": "WRB"
          },
          "transcription": "how"
        },
        {
          "tags": {
            "pos": "JJ"
          },
          "transcription": "many"
        },
        {
          "tags": {
            "pos": "IN"
          },
          "transcription": "from"
        },
        {
          "tags": {
            "pos": "DT"
          },
          "transcription": "each"
        },
        {
          "tags": {
            "pos": "NN"
          },
          "transcription": "group"
        },
        {
          "tags": {
            "pos": "NN"
          },
          "transcription": "volunteer"
        },
        {
          "tags": {
            "pos": "IN"
          },
          "transcription": "for"
        },
        {
          "tags": {
            "pos": "DT"
          },
          "transcription": "the"
        },
        {
          "tags": {
            "pos": "NNP"
          },
          "transcription": "Republican"
        },
        {
          "tags": {
            "pos": "CC"
          },
          "transcription": "and"
        },
        {
          "tags": {
            "pos": "JJ"
          },
          "transcription": "Democratic"
        },
        {
          "tags": {
            "pos": "NNS"
          },
          "transcription": "campaigns"
        },
        {
          "tags": {
            "pos": "CC"
          },
          "transcription": "and"
        },
        {
          "tags": {
            "pos": "WRB"
          },
          "transcription": "how"
        },
        {
          "tags": {
            "pos": "DT"
          },
          "transcription": "the"
        },
        {
          "tags": {
            "pos": "NNS"
          },
          "transcription": "figures"
        },
        {
          "tags": {
            "pos": "VBP"
          },
          "transcription": "compare"
        }
      ]
    },
    {
      "words": [
        {
          "tags": {
            "pos": "VBZ"
          },
          "transcription": "Does"
        },
        {
          "tags": {
            "pos": "NNP"
          },
          "transcription": "Dick"
        },
        {
          "tags": {
            "pos": "NNP"
          },
          "transcription": "Morris"
        },
        {
          "tags": {
            "pos": "VB"
          },
          "transcription": "know"
        }
      ]
    },
    {
      "words": [
        {
          "tags": {
            "pos": "NNP"
          },
          "transcription": "Mr"
        }
      ]
    },
    {
      "words": [
        {
          "tags": {
            "pos": "NNP"
          },
          "transcription": "Morris"
        },
        {
          "tags": {
            "pos": "NN"
          },
          "transcription": "architect"
        },
        {
          "tags": {
            "pos": "IN"
          },
          "transcription": "of"
        },
        {
          "tags": {
            "pos": "NN"
          },
          "transcription": "triangulation"
        },
        {
          "tags": {
            "pos": "RB"
          },
          "transcription": "as"
        },
        {
          "tags": {
            "pos": "RB"
          },
          "transcription": "well"
        },
        {
          "tags": {
            "pos": "IN"
          },
          "transcription": "as"
        },
        {
          "tags": {
            "pos": "IN"
          },
          "transcription": "of"
        },
        {
          "tags": {
            "pos": "DT"
          },
          "transcription": "the"
        },
        {
          "tags": {
            "pos": "NN"
          },
          "transcription": "vice"
        },
        {
          "tags": {
            "pos": "NN"
          },
          "transcription": "president"
        },
        {
          "tags": {
            "pos": "POS"
          },
          "transcription": "'s"
        },
        {
          "tags": {
            "pos": "CC"
          },
          "transcription": "and"
        },
        {
          "tags": {
            "pos": "JJ"
          },
          "transcription": "first"
        },
        {
          "tags": {
            "pos": "NN"
          },
          "transcription": "lady"
        },
        {
          "tags": {
            "pos": "POS"
          },
          "transcription": "'s"
        },
        {
          "tags": {
            "pos": "JJ"
          },
          "transcription": "family-values"
        },
        {
          "tags": {
            "pos": "NNS"
          },
          "transcription": "speeches"
        },
        {
          "tags": {
            "pos": "MD"
          },
          "transcription": "might"
        },
        {
          "tags": {
            "pos": "VB"
          },
          "transcription": "have"
        },
        {
          "tags": {
            "pos": "VBN"
          },
          "transcription": "consulted"
        },
        {
          "tags": {
            "pos": "PRP$"
          },
          "transcription": "his"
        },
        {
          "tags": {
            "pos": "NN"
          },
          "transcription": "companion"
        },
        {
          "tags": {
            "pos": "NNP"
          },
          "transcription": "Miss"
        },
        {
          "tags": {
            "pos": "NNP"
          },
          "transcription": "Rowlands"
        },
        {
          "tags": {
            "pos": "IN"
          },
          "transcription": "during"
        },
        {
          "tags": {
            "pos": "PRP$"
          },
          "transcription": "his"
        }
      ]
    },
    {
      "words": [
        {
          "tags": {
            "pos": "RP"
          },
          "transcription": "off"
        }
      ]
    },
    {
      "words": [
        {
          "tags": {
            "pos": "NNS"
          },
          "transcription": "hours"
        },
        {
          "tags": {
            "pos": "IN"
          },
          "transcription": "at"
        },
        {
          "tags": {
            "pos": "DT"
          },
          "transcription": "the"
        },
        {
          "tags": {
            "pos": "NNP"
          },
          "transcription": "Jefferson"
        },
        {
          "tags": {
            "pos": "NNP"
          },
          "transcription": "Hotel"
        },
        {
          "tags": {
            "pos": "IN"
          },
          "transcription": "about"
        },
        {
          "tags": {
            "pos": "IN"
          },
          "transcription": "whether"
        },
        {
          "tags": {
            "pos": "PRP"
          },
          "transcription": "she"
        },
        {
          "tags": {
            "pos": "VBD"
          },
          "transcription": "felt"
        },
        {
          "tags": {
            "pos": "VBN"
          },
          "transcription": "included"
        },
        {
          "tags": {
            "pos": "IN"
          },
          "transcription": "in"
        },
        {
          "tags": {
            "pos": "DT"
          },
          "transcription": "the"
        },
        {
          "tags": {
            "pos": "NNPS"
          },
          "transcription": "Democrats"
        }
      ]
    },
    {
      "words": [
        {
          "tags": {
            "pos": "NN"
          },
          "transcription": "agenda"
        }
      ]
    },
    {
      "words": [
        {
          "tags": {
            "pos": "PRP"
          },
          "transcription": "It"
        },
        {
          "tags": {
            "pos": "VBZ"
          },
          "transcription": "is"
        },
        {
          "tags": {
            "pos": "RB"
          },
          "transcription": "precisely"
        },
        {
          "tags": {
            "pos": "PRP$"
          },
          "transcription": "our"
        },
        {
          "tags": {
            "pos": "JJ"
          },
          "transcription": "current"
        },
        {
          "tags": {
            "pos": "NN"
          },
          "transcription": "president"
        },
        {
          "tags": {
            "pos": "POS"
          },
          "transcription": "'s"
        },
        {
          "tags": {
            "pos": "NN"
          },
          "transcription": "generation"
        },
        {
          "tags": {
            "pos": "DT"
          },
          "transcription": "the"
        }
      ]
    },
    {
      "words": [
        {
          "tags": {
            "pos": "JJ"
          },
          "transcription": "me-boomers"
        }
      ]
    },
    {
      "words": [
        {
          "tags": {
            "pos": "WP"
          },
          "transcription": "who"
        },
        {
          "tags": {
            "pos": "IN"
          },
          "transcription": "in"
        },
        {
          "tags": {
            "pos": "JJ"
          },
          "transcription": "unprecedented"
        },
        {
          "tags": {
            "pos": "NNS"
          },
          "transcription": "numbers"
        },
        {
          "tags": {
            "pos": "VBD"
          },
          "transcription": "opened"
        },
        {
          "tags": {
            "pos": "DT"
          },
          "transcription": "the"
        },
        {
          "tags": {
            "pos": "NNS"
          },
          "transcription": "doors"
        },
        {
          "tags": {
            "pos": "IN"
          },
          "transcription": "for"
        },
        {
          "tags": {
            "pos": "JJ"
          },
          "transcription": "gay"
        },
        {
          "tags": {
            "pos": "CC"
          },
          "transcription": "and"
        },
        {
          "tags": {
            "pos": "NNS"
          },
          "transcription": "women"
        },
        {
          "tags": {
            "pos": "POS"
          },
          "transcription": "'s"
        },
        {
          "tags": {
            "pos": "NNS"
          },
          "transcription": "rights"
        },
        {
          "tags": {
            "pos": "CC"
          },
          "transcription": "and"
        },
        {
          "tags": {
            "pos": "RB"
          },
          "transcription": "therefore"
        },
        {
          "tags": {
            "pos": "VBN"
          },
          "transcription": "postponed"
        },
        {
          "tags": {
            "pos": "CC"
          },
          "transcription": "or"
        },
        {
          "tags": {
            "pos": "VBN"
          },
          "transcription": "rejected"
        },
        {
          "tags": {
            "pos": "JJ"
          },
          "transcription": "traditional"
        },
        {
          "tags": {
            "pos": "NN"
          },
          "transcription": "family"
        },
        {
          "tags": {
            "pos": "NNS"
          },
          "transcription": "values"
        }
      ]
    },
    {
      "words": [
        {
          "tags": {
            "pos": "PRP"
          },
          "transcription": "It"
        },
        {
          "tags": {
            "pos": "VBZ"
          },
          "transcription": "seems"
        },
        {
          "tags": {
            "pos": "JJ"
          },
          "transcription": "disloyal"
        },
        {
          "tags": {
            "pos": "RB"
          },
          "transcription": "even"
        },
        {
          "tags": {
            "pos": "DT"
          },
          "transcription": "a"
        },
        {
          "tags": {
            "pos": "NN"
          },
          "transcription": "sign"
        },
        {
          "tags": {
            "pos": "IN"
          },
          "transcription": "of"
        },
        {
          "tags": {
            "pos": "JJ"
          },
          "transcription": "self-loathing"
        },
        {
          "tags": {
            "pos": "IN"
          },
          "transcription": "for"
        },
        {
          "tags": {
            "pos": "DT"
          },
          "transcription": "this"
        },
        {
          "tags": {
            "pos": "NN"
          },
          "transcription": "president"
        },
        {
          "tags": {
            "pos": "POS"
          },
          "transcription": "'s"
        },
        {
          "tags": {
            "pos": "NN"
          },
          "transcription": "campaign"
        },
        {
          "tags": {
            "pos": "NN"
          },
          "transcription": "strategy"
        },
        {
          "tags": {
            "pos": "TO"
          },
          "transcription": "to"
        },
        {
          "tags": {
            "pos": "VB"
          },
          "transcription": "work"
        },
        {
          "tags": {
            "pos": "NN"
          },
          "transcription": "overtime"
        },
        {
          "tags": {
            "pos": "TO"
          },
          "transcription": "to"
        },
        {
          "tags": {
            "pos": "VB"
          },
          "transcription": "gain"
        },
        {
          "tags": {
            "pos": "DT"
          },
          "transcription": "the"
        },
        {
          "tags": {
            "pos": "NN"
          },
          "transcription": "admiration"
        },
        {
          "tags": {
            "pos": "CC"
          },
          "transcription": "and"
        },
        {
          "tags": {
            "pos": "NN"
          },
          "transcription": "respect"
        },
        {
          "tags": {
            "pos": "IN"
          },
          "transcription": "of"
        },
        {
          "tags": {
            "pos": "DT"
          },
          "transcription": "the"
        },
        {
          "tags": {
            "pos": "NN"
          },
          "transcription": "center"
        },
        {
          "tags": {
            "pos": "IN"
          },
          "transcription": "while"
        },
        {
          "tags": {
            "pos": "VBG"
          },
          "transcription": "ignoring"
        },
        {
          "tags": {
            "pos": "PRP$"
          },
          "transcription": "his"
        },
        {
          "tags": {
            "pos": "JJ"
          },
          "transcription": "own"
        },
        {
          "tags": {
            "pos": "NN"
          },
          "transcription": "backyard"
        }
      ]
    },
    {
      "words": [
        {
          "tags": {
            "pos": "IN"
          },
          "transcription": "If"
        },
        {
          "tags": {
            "pos": "NNP"
          },
          "transcription": "Mr"
        }
      ]
    },
    {
      "words": [
        {
          "tags": {
            "pos": "NNP"
          },
          "transcription": "Dole"
        },
        {
          "tags": {
            "pos": "VBZ"
          },
          "transcription": "insists"
        },
        {
          "tags": {
            "pos": "IN"
          },
          "transcription": "on"
        },
        {
          "tags": {
            "pos": "VBG"
          },
          "transcription": "playing"
        },
        {
          "tags": {
            "pos": "NN"
          },
          "transcription": "footsie"
        },
        {
          "tags": {
            "pos": "IN"
          },
          "transcription": "with"
        },
        {
          "tags": {
            "pos": "DT"
          },
          "transcription": "the"
        },
        {
          "tags": {
            "pos": "JJ"
          },
          "transcription": "religious"
        },
        {
          "tags": {
            "pos": "NN"
          },
          "transcription": "right"
        },
        {
          "tags": {
            "pos": "MD"
          },
          "transcription": "should"
        },
        {
          "tags": {
            "pos": "RB"
          },
          "transcription": "n't"
        },
        {
          "tags": {
            "pos": "NNP"
          },
          "transcription": "Mr"
        }
      ]
    },
    {
      "words": [
        {
          "tags": {
            "pos": "NNP"
          },
          "transcription": "Clinton"
        },
        {
          "tags": {
            "pos": "VBP"
          },
          "transcription": "acknowledge"
        },
        {
          "tags": {
            "pos": "PRP$"
          },
          "transcription": "his"
        },
        {
          "tags": {
            "pos": "NN"
          },
          "transcription": "lifestyle"
        },
        {
          "tags": {
            "pos": "VBD"
          },
          "transcription": "left"
        }
      ]
    },
    {
      "words": [
        {
          "tags": {
            "pos": "RB"
          },
          "transcription": "Perhaps"
        },
        {
          "tags": {
            "pos": "PRP"
          },
          "transcription": "it"
        },
        {
          "tags": {
            "pos": "VBZ"
          },
          "transcription": "'s"
        },
        {
          "tags": {
            "pos": "NN"
          },
          "transcription": "time"
        },
        {
          "tags": {
            "pos": "IN"
          },
          "transcription": "for"
        },
        {
          "tags": {
            "pos": "DT"
          },
          "transcription": "both"
        },
        {
          "tags": {
            "pos": "NNS"
          },
          "transcription": "parties"
        },
        {
          "tags": {
            "pos": "TO"
          },
          "transcription": "to"
        },
        {
          "tags": {
            "pos": "VB"
          },
          "transcription": "consider"
        }
      ]
    },
    {
      "words": [
        {
          "tags": {
            "pos": "NN"
          },
          "transcription": "rectangularization"
        }
      ]
    },
    {
      "words": [
        {
          "tags": {
            "pos": ":"
          },
          "transcription": "-"
        },
        {
          "tags": {
            "pos": ":"
          },
          "transcription": "-"
        },
        {
          "tags": {
            "pos": "TO"
          },
          "transcription": "to"
        },
        {
          "tags": {
            "pos": "VB"
          },
          "transcription": "include"
        },
        {
          "tags": {
            "pos": "IN"
          },
          "transcription": "in"
        },
        {
          "tags": {
            "pos": "PRP$"
          },
          "transcription": "their"
        },
        {
          "tags": {
            "pos": "NN"
          },
          "transcription": "focus"
        },
        {
          "tags": {
            "pos": "NNS"
          },
          "transcription": "groups"
        },
        {
          "tags": {
            "pos": "NNS"
          },
          "transcription": "voters"
        },
        {
          "tags": {
            "pos": "WP"
          },
          "transcription": "who"
        },
        {
          "tags": {
            "pos": "VBP"
          },
          "transcription": "care"
        },
        {
          "tags": {
            "pos": "IN"
          },
          "transcription": "about"
        },
        {
          "tags": {
            "pos": "NN"
          },
          "transcription": "health"
        },
        {
          "tags": {
            "pos": "NN"
          },
          "transcription": "care"
        },
        {
          "tags": {
            "pos": "CC"
          },
          "transcription": "and"
        },
        {
          "tags": {
            "pos": "NN"
          },
          "transcription": "education"
        },
        {
          "tags": {
            "pos": "CC"
          },
          "transcription": "but"
        },
        {
          "tags": {
            "pos": "RB"
          },
          "transcription": "not"
        },
        {
          "tags": {
            "pos": "RB"
          },
          "transcription": "necessarily"
        },
        {
          "tags": {
            "pos": "IN"
          },
          "transcription": "about"
        },
        {
          "tags": {
            "pos": "VBG"
          },
          "transcription": "getting"
        },
        {
          "tags": {
            "pos": "VBN"
          },
          "transcription": "married"
        },
        {
          "tags": {
            "pos": "CC"
          },
          "transcription": "or"
        },
        {
          "tags": {
            "pos": "VBG"
          },
          "transcription": "having"
        },
        {
          "tags": {
            "pos": "NNS"
          },
          "transcription": "children"
        }
      ]
    },
    {
      "words": [
        {
          "tags": {
            "pos": "IN"
          },
          "transcription": "At"
        },
        {
          "tags": {
            "pos": "DT"
          },
          "transcription": "the"
        },
        {
          "tags": {
            "pos": "NNP"
          },
          "transcription": "Republican"
        },
        {
          "tags": {
            "pos": "NNP"
          },
          "transcription": "Convention"
        },
        {
          "tags": {
            "pos": "NNP"
          },
          "transcription": "Bob"
        },
        {
          "tags": {
            "pos": "NNP"
          },
          "transcription": "Dole"
        },
        {
          "tags": {
            "pos": "JJ"
          },
          "transcription": "commended"
        },
        {
          "tags": {
            "pos": "IN"
          },
          "transcription": "as"
        },
        {
          "tags": {
            "pos": "JJ"
          },
          "transcription": "right"
        },
        {
          "tags": {
            "pos": "NN"
          },
          "transcription": "conduct"
        }
      ]
    },
    {
      "words": [
        {
          "tags": {
            "pos": "DT"
          },
          "transcription": "any"
        },
        {
          "tags": {
            "pos": "NN"
          },
          "transcription": "screenwriter"
        },
        {
          "tags": {
            "pos": "WP"
          },
          "transcription": "who"
        },
        {
          "tags": {
            "pos": "VBZ"
          },
          "transcription": "refuses"
        },
        {
          "tags": {
            "pos": "TO"
          },
          "transcription": "to"
        },
        {
          "tags": {
            "pos": "VB"
          },
          "transcription": "contribute"
        },
        {
          "tags": {
            "pos": "TO"
          },
          "transcription": "to"
        },
        {
          "tags": {
            "pos": "DT"
          },
          "transcription": "the"
        },
        {
          "tags": {
            "pos": "NNS"
          },
          "transcription": "mountains"
        },
        {
          "tags": {
            "pos": "IN"
          },
          "transcription": "of"
        },
        {
          "tags": {
            "pos": "NN"
          },
          "transcription": "trash"
        }
      ]
    },
    {
      "words": [
        {
          "tags": {
            "pos": "RB"
          },
          "transcription": "Well"
        },
        {
          "tags": {
            "pos": "PRP"
          },
          "transcription": "I"
        },
        {
          "tags": {
            "pos": "VBP"
          },
          "transcription": "'m"
        },
        {
          "tags": {
            "pos": "CD"
          },
          "transcription": "one"
        },
        {
          "tags": {
            "pos": "NN"
          },
          "transcription": "writer"
        },
        {
          "tags": {
            "pos": "WP"
          },
          "transcription": "who"
        },
        {
          "tags": {
            "pos": "MD"
          },
          "transcription": "would"
        },
        {
          "tags": {
            "pos": "VB"
          },
          "transcription": "promise"
        },
        {
          "tags": {
            "pos": "NNP"
          },
          "transcription": "Bill"
        },
        {
          "tags": {
            "pos": "NNP"
          },
          "transcription": "Bob"
        },
        {
          "tags": {
            "pos": "NNP"
          },
          "transcription": "Hillary"
        },
        {
          "tags": {
            "pos": "CC"
          },
          "transcription": "and"
        },
        {
          "tags": {
            "pos": "NNP"
          },
          "transcription": "Liddy"
        },
        {
          "tags": {
            "pos": "RB"
          },
          "transcription": "personally"
        },
        {
          "tags": {
            "pos": "IN"
          },
          "transcription": "at"
        },
        {
          "tags": {
            "pos": "PRP$"
          },
          "transcription": "my"
        },
        {
          "tags": {
            "pos": "NN"
          },
          "transcription": "kitchen"
        },
        {
          "tags": {
            "pos": "NN"
          },
          "transcription": "table"
        },
        {
          "tags": {
            "pos": "("
          },
          "transcription": "("
        },
        {
          "tags": {
            "pos": "RB"
          },
          "transcription": "well"
        },
        {
          "tags": {
            "pos": "NN"
          },
          "transcription": "kitchen"
        },
        {
          "tags": {
            "pos": "NN"
          },
          "transcription": "counter"
        },
        {
          "tags": {
            "pos": ")"
          },
          "transcription": ")"
        },
        {
          "tags": {
            "pos": "RB"
          },
          "transcription": "not"
        },
        {
          "tags": {
            "pos": "TO"
          },
          "transcription": "to"
        },
        {
          "tags": {
            "pos": "VB"
          },
          "transcription": "contribute"
        },
        {
          "tags": {
            "pos": "JJ"
          },
          "transcription": "further"
        },
        {
          "tags": {
            "pos": "TO"
          },
          "transcription": "to"
        },
        {
          "tags": {
            "pos": "DT"
          },
          "transcription": "the"
        },
        {
          "tags": {
            "pos": "NN"
          },
          "transcription": "trash"
        },
        {
          "tags": {
            "pos": "DT"
          },
          "transcription": "this"
        },
        {
          "tags": {
            "pos": "NN"
          },
          "transcription": "year"
        }
      ]
    },
    {
      "words": [
        {
          "tags": {
            "pos": "CC"
          },
          "transcription": "But"
        },
        {
          "tags": {
            "pos": "IN"
          },
          "transcription": "on"
        },
        {
          "tags": {
            "pos": "CD"
          },
          "transcription": "one"
        },
        {
          "tags": {
            "pos": "NN"
          },
          "transcription": "condition"
        },
        {
          "tags": {
            "pos": ":"
          },
          "transcription": ":"
        },
        {
          "tags": {
            "pos": "DT"
          },
          "transcription": "Both"
        },
        {
          "tags": {
            "pos": "NNS"
          },
          "transcription": "parties"
        },
        {
          "tags": {
            "pos": "MD"
          },
          "transcription": "must"
        },
        {
          "tags": {
            "pos": "VB"
          },
          "transcription": "return"
        },
        {
          "tags": {
            "pos": "TO"
          },
          "transcription": "to"
        },
        {
          "tags": {
            "pos": "DT"
          },
          "transcription": "a"
        },
        {
          "tags": {
            "pos": "JJ"
          },
          "transcription": "genuine"
        },
        {
          "tags": {
            "pos": "NN"
          },
          "transcription": "debate"
        },
        {
          "tags": {
            "pos": "CC"
          },
          "transcription": "and"
        },
        {
          "tags": {
            "pos": "VB"
          },
          "transcription": "stop"
        },
        {
          "tags": {
            "pos": "NN"
          },
          "transcription": "bickering"
        },
        {
          "tags": {
            "pos": "IN"
          },
          "transcription": "over"
        },
        {
          "tags": {
            "pos": "WP"
          },
          "transcription": "who"
        },
        {
          "tags": {
            "pos": "MD"
          },
          "transcription": "can"
        },
        {
          "tags": {
            "pos": "VB"
          },
          "transcription": "present"
        },
        {
          "tags": {
            "pos": "DT"
          },
          "transcription": "a"
        },
        {
          "tags": {
            "pos": "JJR"
          },
          "transcription": "better"
        },
        {
          "tags": {
            "pos": "NN"
          },
          "transcription": "image"
        },
        {
          "tags": {
            "pos": "IN"
          },
          "transcription": "of"
        },
        {
          "tags": {
            "pos": "JJ"
          },
          "transcription": "wistful"
        },
        {
          "tags": {
            "pos": "NN"
          },
          "transcription": "middle-"
        },
        {
          "tags": {
            "pos": "JJ"
          },
          "transcription": "American"
        },
        {
          "tags": {
            "pos": "NN"
          },
          "transcription": "family"
        },
        {
          "tags": {
            "pos": "NN"
          },
          "transcription": "life"
        }
      ]
    },
    {
      "words": [
        {
          "tags": {
            "pos": "PRP"
          },
          "transcription": "It"
        },
        {
          "tags": {
            "pos": "VBZ"
          },
          "transcription": "'s"
        },
        {
          "tags": {
            "pos": "VBG"
          },
          "transcription": "irritating"
        },
        {
          "tags": {
            "pos": "TO"
          },
          "transcription": "to"
        },
        {
          "tags": {
            "pos": "VB"
          },
          "transcription": "be"
        },
        {
          "tags": {
            "pos": "VBN"
          },
          "transcription": "ignored"
        }
      ]
    },
    {
      "words": [
        {
          "tags": {
            "pos": "CC"
          },
          "transcription": "But"
        },
        {
          "tags": {
            "pos": "PRP"
          },
          "transcription": "it"
        },
        {
          "tags": {
            "pos": "VBZ"
          },
          "transcription": "'s"
        },
        {
          "tags": {
            "pos": "JJ"
          },
          "transcription": "painful"
        },
        {
          "tags": {
            "pos": "TO"
          },
          "transcription": "to"
        },
        {
          "tags": {
            "pos": "VB"
          },
          "transcription": "be"
        },
        {
          "tags": {
            "pos": "VBG"
          },
          "transcription": "living"
        },
        {
          "tags": {
            "pos": "DT"
          },
          "transcription": "a"
        },
        {
          "tags": {
            "pos": "NN"
          },
          "transcription": "life"
        },
        {
          "tags": {
            "pos": "WDT"
          },
          "transcription": "which"
        },
        {
          "tags": {
            "pos": "DT"
          },
          "transcription": "both"
        },
        {
          "tags": {
            "pos": "JJ"
          },
          "transcription": "political"
        },
        {
          "tags": {
            "pos": "NNS"
          },
          "transcription": "spectrums"
        },
        {
          "tags": {
            "pos": "VBP"
          },
          "transcription": "deem"
        },
        {
          "tags": {
            "pos": "RB"
          },
          "transcription": "as"
        },
        {
          "tags": {
            "pos": "RB"
          },
          "transcription": "virtually"
        },
        {
          "tags": {
            "pos": "NN"
          },
          "transcription": "un-"
        },
        {
          "tags": {
            "pos": "NNP"
          },
          "transcription": "American"
        }
      ]
    },
    {
      "words": [
        {
          "tags": {
            "pos": "PRP"
          },
          "transcription": "It"
        },
        {
          "tags": {
            "pos": "VBZ"
          },
          "transcription": "takes"
        },
        {
          "tags": {
            "pos": "DT"
          },
          "transcription": "a"
        },
        {
          "tags": {
            "pos": "NN"
          },
          "transcription": "citizen"
        },
        {
          "tags": {
            "pos": "TO"
          },
          "transcription": "to"
        },
        {
          "tags": {
            "pos": "VB"
          },
          "transcription": "make"
        },
        {
          "tags": {
            "pos": "DT"
          },
          "transcription": "a"
        },
        {
          "tags": {
            "pos": "NN"
          },
          "transcription": "village"
        }
      ]
    },
    {
      "words": [
        {
          "tags": {
            "pos": "RB"
          },
          "transcription": "Not"
        },
        {
          "tags": {
            "pos": "RB"
          },
          "transcription": "just"
        },
        {
          "tags": {
            "pos": "DT"
          },
          "transcription": "a"
        },
        {
          "tags": {
            "pos": "NN"
          },
          "transcription": "parent"
        }
      ]
    }
  ]
}