<?xml version="1.0" encoding="UTF-8"?>
<graph xmlns="http://www.xces.org/ns/GrAF/1.0/">
    <header>
        <tagsDecl>
            <tagUsage gi="body" occurs="1"/>
            <tagUsage gi="turn" occurs="128"/>
            <tagUsage gi="u" occurs="159"/>
            <tagUsage gi="cesDoc" occurs="1"/>
        </tagsDecl>
        <annotationSets>
            <annotationSet name="xces" type="http://www.xces.org/schema/2003"/>
        </annotationSets>
    </header>
    <region xml:id="n-r0" anchors="0 8405"/>
    <node xml:id="n-n0">
        <link targets="n-r0"/>
    </node>
    <a label="cesDoc" ref="n-n0" as="xces">
        <fs>
            <f name="xmlns:xlink" value="http://www.w3.org/1999/xlink"/>
            <f name="xmlns:xsi" value="http://www.w3.org/2001/XMLSchema-instance"/>
            <f name="version" value="1.0"/>
            <f name="xmlns" value="http://www.xces.org/schema/2003"/>
        </fs>
    </a>
    <region xml:id="n-r1" anchors="10 8402"/>
    <node xml:id="n-n1">
        <link targets="n-r1"/>
    </node>
    <a label="body" ref="n-n1" as="xces"/>
    <region xml:id="n-r2" anchors="13 22"/>
    <node xml:id="n-n2">
        <link targets="n-r2"/>
    </node>
    <a label="turn" ref="n-n2" as="xces">
        <fs>
            <f name="who" value="A"/>
            <f name="id" value="t1"/>
        </fs>
    </a>
    <region xml:id="n-r3" anchors="17 19"/>
    <node xml:id="n-n3">
        <link targets="n-r3"/>
    </node>
    <a label="u" ref="n-n3" as="xces">
        <fs>
            <f name="id" value="sw3101A-0001"/>
            <f name="end" value="0.208000"/>
            <f name="start" value="0.000000"/>
        </fs>
    </a>
    <region xml:id="n-r4" anchors="25 34"/>
    <node xml:id="n-n4">
        <link targets="n-r4"/>
    </node>
    <a label="turn" ref="n-n4" as="xces">
        <fs>
            <f name="who" value="B"/>
            <f name="id" value="t2"/>
        </fs>
    </a>
    <region xml:id="n-r5" anchors="29 31"/>
    <node xml:id="n-n5">
        <link targets="n-r5"/>
    </node>
    <a label="u" ref="n-n5" as="xces">
        <fs>
            <f name="id" value="sw3101B-0001"/>
            <f name="end" value="0.401750"/>
            <f name="start" value="0.000000"/>
        </fs>
    </a>
    <region xml:id="n-r6" anchors="37 67"/>
    <node xml:id="n-n6">
        <link targets="n-r6"/>
    </node>
    <a label="turn" ref="n-n6" as="xces">
        <fs>
            <f name="who" value="A"/>
            <f name="id" value="t3"/>
        </fs>
    </a>
    <region xml:id="n-r7" anchors="41 64"/>
    <node xml:id="n-n7">
        <link targets="n-r7"/>
    </node>
    <a label="u" ref="n-n7" as="xces">
        <fs>
            <f name="id" value="sw3101A-0002"/>
            <f name="end" value="2.337375"/>
            <f name="start" value="0.208000"/>
        </fs>
    </a>
    <region xml:id="n-r8" anchors="70 79"/>
    <node xml:id="n-n8">
        <link targets="n-r8"/>
    </node>
    <a label="turn" ref="n-n8" as="xces">
        <fs>
            <f name="who" value="B"/>
            <f name="id" value="t4"/>
        </fs>
    </a>
    <region xml:id="n-r9" anchors="74 76"/>
    <node xml:id="n-n9">
        <link targets="n-r9"/>
    </node>
    <a label="u" ref="n-n9" as="xces">
        <fs>
            <f name="id" value="sw3101B-0003"/>
            <f name="end" value="2.832750"/>
            <f name="start" value="1.685875"/>
        </fs>
    </a>
    <region xml:id="n-r10" anchors="82 116"/>
    <node xml:id="n-n10">
        <link targets="n-r10"/>
    </node>
    <a label="turn" ref="n-n10" as="xces">
        <fs>
            <f name="who" value="A"/>
            <f name="id" value="t5"/>
        </fs>
    </a>
    <region xml:id="n-r11" anchors="86 113"/>
    <node xml:id="n-n11">
        <link targets="n-r11"/>
    </node>
    <a label="u" ref="n-n11" as="xces">
        <fs>
            <f name="id" value="sw3101A-0003"/>
            <f name="end" value="4.541125"/>
            <f name="start" value="2.337375"/>
        </fs>
    </a>
    <region xml:id="n-r12" anchors="119 191"/>
    <node xml:id="n-n12">
        <link targets="n-r12"/>
    </node>
    <a label="turn" ref="n-n12" as="xces">
        <fs>
            <f name="who" value="B"/>
            <f name="id" value="t6"/>
        </fs>
    </a>
    <region xml:id="n-r13" anchors="123 130"/>
    <node xml:id="n-n13">
        <link targets="n-r13"/>
    </node>
    <a label="u" ref="n-n13" as="xces">
        <fs>
            <f name="id" value="sw3101B-0004"/>
            <f name="end" value="4.580125"/>
            <f name="start" value="2.832750"/>
        </fs>
    </a>
    <region xml:id="n-r14" anchors="134 188"/>
    <node xml:id="n-n14">
        <link targets="n-r14"/>
    </node>
    <a label="u" ref="n-n14" as="xces">
        <fs>
            <f name="id" value="sw3101B-0005"/>
            <f name="end" value="7.729125"/>
            <f name="start" value="4.580125"/>
        </fs>
    </a>
    <region xml:id="n-r15" anchors="194 210"/>
    <node xml:id="n-n15">
        <link targets="n-r15"/>
    </node>
    <a label="turn" ref="n-n15" as="xces">
        <fs>
            <f name="who" value="A"/>
            <f name="id" value="t7"/>
        </fs>
    </a>
    <region xml:id="n-r16" anchors="198 207"/>
    <node xml:id="n-n16">
        <link targets="n-r16"/>
    </node>
    <a label="u" ref="n-n16" as="xces">
        <fs>
            <f name="id" value="sw3101A-0005"/>
            <f name="end" value="8.002375"/>
            <f name="start" value="6.522500"/>
        </fs>
    </a>
    <region xml:id="n-r17" anchors="213 303"/>
    <node xml:id="n-n17">
        <link targets="n-r17"/>
    </node>
    <a label="turn" ref="n-n17" as="xces">
        <fs>
            <f name="who" value="B"/>
            <f name="id" value="t8"/>
        </fs>
    </a>
    <region xml:id="n-r18" anchors="217 300"/>
    <node xml:id="n-n18">
        <link targets="n-r18"/>
    </node>
    <a label="u" ref="n-n18" as="xces">
        <fs>
            <f name="id" value="sw3101B-0006"/>
            <f name="end" value="11.474250"/>
            <f name="start" value="7.729125"/>
        </fs>
    </a>
    <region xml:id="n-r19" anchors="306 333"/>
    <node xml:id="n-n19">
        <link targets="n-r19"/>
    </node>
    <a label="turn" ref="n-n19" as="xces">
        <fs>
            <f name="who" value="A"/>
            <f name="id" value="t9"/>
        </fs>
    </a>
    <region xml:id="n-r20" anchors="310 330"/>
    <node xml:id="n-n20">
        <link targets="n-r20"/>
    </node>
    <a label="u" ref="n-n20" as="xces">
        <fs>
            <f name="id" value="sw3101A-0007"/>
            <f name="end" value="12.282000"/>
            <f name="start" value="10.699125"/>
        </fs>
    </a>
    <region xml:id="n-r21" anchors="336 373"/>
    <node xml:id="n-n21">
        <link targets="n-r21"/>
    </node>
    <a label="turn" ref="n-n21" as="xces">
        <fs>
            <f name="who" value="B"/>
            <f name="id" value="t10"/>
        </fs>
    </a>
    <region xml:id="n-r22" anchors="340 370"/>
    <node xml:id="n-n22">
        <link targets="n-r22"/>
    </node>
    <a label="u" ref="n-n22" as="xces">
        <fs>
            <f name="id" value="sw3101B-0007"/>
            <f name="end" value="14.363375"/>
            <f name="start" value="11.474250"/>
        </fs>
    </a>
    <region xml:id="n-r23" anchors="376 421"/>
    <node xml:id="n-n23">
        <link targets="n-r23"/>
    </node>
    <a label="turn" ref="n-n23" as="xces">
        <fs>
            <f name="who" value="A"/>
            <f name="id" value="t11"/>
        </fs>
    </a>
    <region xml:id="n-r24" anchors="380 382"/>
    <node xml:id="n-n24">
        <link targets="n-r24"/>
    </node>
    <a label="u" ref="n-n24" as="xces">
        <fs>
            <f name="id" value="sw3101A-0008"/>
            <f name="end" value="14.118000"/>
            <f name="start" value="12.282000"/>
        </fs>
    </a>
    <region xml:id="n-r25" anchors="386 418"/>
    <node xml:id="n-n25">
        <link targets="n-r25"/>
    </node>
    <a label="u" ref="n-n25" as="xces">
        <fs>
            <f name="id" value="sw3101A-0009"/>
            <f name="end" value="17.438125"/>
            <f name="start" value="14.118000"/>
        </fs>
    </a>
    <region xml:id="n-r26" anchors="424 446"/>
    <node xml:id="n-n26">
        <link targets="n-r26"/>
    </node>
    <a label="turn" ref="n-n26" as="xces">
        <fs>
            <f name="who" value="B"/>
            <f name="id" value="t12"/>
        </fs>
    </a>
    <region xml:id="n-r27" anchors="428 432"/>
    <node xml:id="n-n27">
        <link targets="n-r27"/>
    </node>
    <a label="u" ref="n-n27" as="xces">
        <fs>
            <f name="id" value="sw3101B-0008"/>
            <f name="end" value="15.405250"/>
            <f name="start" value="14.363375"/>
        </fs>
    </a>
    <region xml:id="n-r28" anchors="436 443"/>
    <node xml:id="n-n28">
        <link targets="n-r28"/>
    </node>
    <a label="u" ref="n-n28" as="xces">
        <fs>
            <f name="id" value="sw3101B-0010"/>
            <f name="end" value="18.258625"/>
            <f name="start" value="17.177000"/>
        </fs>
    </a>
    <region xml:id="n-r29" anchors="449 771"/>
    <node xml:id="n-n29">
        <link targets="n-r29"/>
    </node>
    <a label="turn" ref="n-n29" as="xces">
        <fs>
            <f name="who" value="A"/>
            <f name="id" value="t13"/>
        </fs>
    </a>
    <region xml:id="n-r30" anchors="453 634"/>
    <node xml:id="n-n30">
        <link targets="n-r30"/>
    </node>
    <a label="u" ref="n-n30" as="xces">
        <fs>
            <f name="id" value="sw3101A-0010"/>
            <f name="end" value="28.155500"/>
            <f name="start" value="17.438125"/>
        </fs>
    </a>
    <region xml:id="n-r31" anchors="638 768"/>
    <node xml:id="n-n31">
        <link targets="n-r31"/>
    </node>
    <a label="u" ref="n-n31" as="xces">
        <fs>
            <f name="id" value="sw3101A-0011"/>
            <f name="end" value="35.975000"/>
            <f name="start" value="28.155500"/>
        </fs>
    </a>
    <region xml:id="n-r32" anchors="774 797"/>
    <node xml:id="n-n32">
        <link targets="n-r32"/>
    </node>
    <a label="turn" ref="n-n32" as="xces">
        <fs>
            <f name="who" value="B"/>
            <f name="id" value="t14"/>
        </fs>
    </a>
    <region xml:id="n-r33" anchors="778 794"/>
    <node xml:id="n-n33">
        <link targets="n-r33"/>
    </node>
    <a label="u" ref="n-n33" as="xces">
        <fs>
            <f name="id" value="sw3101B-0012"/>
            <f name="end" value="36.609000"/>
            <f name="start" value="35.379625"/>
        </fs>
    </a>
    <region xml:id="n-r34" anchors="800 835"/>
    <node xml:id="n-n34">
        <link targets="n-r34"/>
    </node>
    <a label="turn" ref="n-n34" as="xces">
        <fs>
            <f name="who" value="A"/>
            <f name="id" value="t15"/>
        </fs>
    </a>
    <region xml:id="n-r35" anchors="804 832"/>
    <node xml:id="n-n35">
        <link targets="n-r35"/>
    </node>
    <a label="u" ref="n-n35" as="xces">
        <fs>
            <f name="id" value="sw3101A-0012"/>
            <f name="end" value="40.258125"/>
            <f name="start" value="35.975000"/>
        </fs>
    </a>
    <region xml:id="n-r36" anchors="838 886"/>
    <node xml:id="n-n36">
        <link targets="n-r36"/>
    </node>
    <a label="turn" ref="n-n36" as="xces">
        <fs>
            <f name="who" value="B"/>
            <f name="id" value="t16"/>
        </fs>
    </a>
    <region xml:id="n-r37" anchors="842 844"/>
    <node xml:id="n-n37">
        <link targets="n-r37"/>
    </node>
    <a label="u" ref="n-n37" as="xces">
        <fs>
            <f name="id" value="sw3101B-0013"/>
            <f name="end" value="37.633500"/>
            <f name="start" value="36.609000"/>
        </fs>
    </a>
    <region xml:id="n-r38" anchors="848 883"/>
    <node xml:id="n-n38">
        <link targets="n-r38"/>
    </node>
    <a label="u" ref="n-n38" as="xces">
        <fs>
            <f name="id" value="sw3101B-0015"/>
            <f name="end" value="41.957750"/>
            <f name="start" value="39.985625"/>
        </fs>
    </a>
    <region xml:id="n-r39" anchors="889 900"/>
    <node xml:id="n-n39">
        <link targets="n-r39"/>
    </node>
    <a label="turn" ref="n-n39" as="xces">
        <fs>
            <f name="who" value="A"/>
            <f name="id" value="t17"/>
        </fs>
    </a>
    <region xml:id="n-r40" anchors="893 897"/>
    <node xml:id="n-n40">
        <link targets="n-r40"/>
    </node>
    <a label="u" ref="n-n40" as="xces">
        <fs>
            <f name="id" value="sw3101A-0014"/>
            <f name="end" value="43.558500"/>
            <f name="start" value="41.452625"/>
        </fs>
    </a>
    <region xml:id="n-r41" anchors="903 912"/>
    <node xml:id="n-n41">
        <link targets="n-r41"/>
    </node>
    <a label="turn" ref="n-n41" as="xces">
        <fs>
            <f name="who" value="B"/>
            <f name="id" value="t18"/>
        </fs>
    </a>
    <region xml:id="n-r42" anchors="907 909"/>
    <node xml:id="n-n42">
        <link targets="n-r42"/>
    </node>
    <a label="u" ref="n-n42" as="xces">
        <fs>
            <f name="id" value="sw3101B-0016"/>
            <f name="end" value="43.360500"/>
            <f name="start" value="41.957750"/>
        </fs>
    </a>
    <region xml:id="n-r43" anchors="915 951"/>
    <node xml:id="n-n43">
        <link targets="n-r43"/>
    </node>
    <a label="turn" ref="n-n43" as="xces">
        <fs>
            <f name="who" value="A"/>
            <f name="id" value="t19"/>
        </fs>
    </a>
    <region xml:id="n-r44" anchors="919 948"/>
    <node xml:id="n-n44">
        <link targets="n-r44"/>
    </node>
    <a label="u" ref="n-n44" as="xces">
        <fs>
            <f name="id" value="sw3101A-0015"/>
            <f name="end" value="46.250250"/>
            <f name="start" value="43.558500"/>
        </fs>
    </a>
    <region xml:id="n-r45" anchors="954 1006"/>
    <node xml:id="n-n45">
        <link targets="n-r45"/>
    </node>
    <a label="turn" ref="n-n45" as="xces">
        <fs>
            <f name="who" value="B"/>
            <f name="id" value="t20"/>
        </fs>
    </a>
    <region xml:id="n-r46" anchors="958 1003"/>
    <node xml:id="n-n46">
        <link targets="n-r46"/>
    </node>
    <a label="u" ref="n-n46" as="xces">
        <fs>
            <f name="id" value="sw3101B-0018"/>
            <f name="end" value="48.201750"/>
            <f name="start" value="45.257375"/>
        </fs>
    </a>
    <region xml:id="n-r47" anchors="1009 1025"/>
    <node xml:id="n-n47">
        <link targets="n-r47"/>
    </node>
    <a label="turn" ref="n-n47" as="xces">
        <fs>
            <f name="who" value="A"/>
            <f name="id" value="t21"/>
        </fs>
    </a>
    <region xml:id="n-r48" anchors="1013 1022"/>
    <node xml:id="n-n48">
        <link targets="n-r48"/>
    </node>
    <a label="u" ref="n-n48" as="xces">
        <fs>
            <f name="id" value="sw3101A-0017"/>
            <f name="end" value="48.550500"/>
            <f name="start" value="47.659375"/>
        </fs>
    </a>
    <region xml:id="n-r49" anchors="1028 1149"/>
    <node xml:id="n-n49">
        <link targets="n-r49"/>
    </node>
    <a label="turn" ref="n-n49" as="xces">
        <fs>
            <f name="who" value="B"/>
            <f name="id" value="t22"/>
        </fs>
    </a>
    <region xml:id="n-r50" anchors="1032 1146"/>
    <node xml:id="n-n50">
        <link targets="n-r50"/>
    </node>
    <a label="u" ref="n-n50" as="xces">
        <fs>
            <f name="id" value="sw3101B-0019"/>
            <f name="end" value="56.148750"/>
            <f name="start" value="48.201750"/>
        </fs>
    </a>
    <region xml:id="n-r51" anchors="1152 1220"/>
    <node xml:id="n-n51">
        <link targets="n-r51"/>
    </node>
    <a label="turn" ref="n-n51" as="xces">
        <fs>
            <f name="who" value="A"/>
            <f name="id" value="t23"/>
        </fs>
    </a>
    <region xml:id="n-r52" anchors="1156 1158"/>
    <node xml:id="n-n52">
        <link targets="n-r52"/>
    </node>
    <a label="u" ref="n-n52" as="xces">
        <fs>
            <f name="id" value="sw3101A-0019"/>
            <f name="end" value="51.466875"/>
            <f name="start" value="49.574375"/>
        </fs>
    </a>
    <region xml:id="n-r53" anchors="1162 1217"/>
    <node xml:id="n-n53">
        <link targets="n-r53"/>
    </node>
    <a label="u" ref="n-n53" as="xces">
        <fs>
            <f name="id" value="sw3101A-0021"/>
            <f name="end" value="57.974375"/>
            <f name="start" value="54.665250"/>
        </fs>
    </a>
    <region xml:id="n-r54" anchors="1223 1263"/>
    <node xml:id="n-n54">
        <link targets="n-r54"/>
    </node>
    <a label="turn" ref="n-n54" as="xces">
        <fs>
            <f name="who" value="B"/>
            <f name="id" value="t24"/>
        </fs>
    </a>
    <region xml:id="n-r55" anchors="1227 1260"/>
    <node xml:id="n-n55">
        <link targets="n-r55"/>
    </node>
    <a label="u" ref="n-n55" as="xces">
        <fs>
            <f name="id" value="sw3101B-0021"/>
            <f name="end" value="60.268375"/>
            <f name="start" value="57.960000"/>
        </fs>
    </a>
    <region xml:id="n-r56" anchors="1266 1439"/>
    <node xml:id="n-n56">
        <link targets="n-r56"/>
    </node>
    <a label="turn" ref="n-n56" as="xces">
        <fs>
            <f name="who" value="A"/>
            <f name="id" value="t25"/>
        </fs>
    </a>
    <region xml:id="n-r57" anchors="1270 1383"/>
    <node xml:id="n-n57">
        <link targets="n-r57"/>
    </node>
    <a label="u" ref="n-n57" as="xces">
        <fs>
            <f name="id" value="sw3101A-0023"/>
            <f name="end" value="66.091500"/>
            <f name="start" value="59.732375"/>
        </fs>
    </a>
    <region xml:id="n-r58" anchors="1387 1436"/>
    <node xml:id="n-n58">
        <link targets="n-r58"/>
    </node>
    <a label="u" ref="n-n58" as="xces">
        <fs>
            <f name="id" value="sw3101A-0024"/>
            <f name="end" value="69.334875"/>
            <f name="start" value="66.091500"/>
        </fs>
    </a>
    <region xml:id="n-r59" anchors="1442 1472"/>
    <node xml:id="n-n59">
        <link targets="n-r59"/>
    </node>
    <a label="turn" ref="n-n59" as="xces">
        <fs>
            <f name="who" value="B"/>
            <f name="id" value="t26"/>
        </fs>
    </a>
    <region xml:id="n-r60" anchors="1446 1469"/>
    <node xml:id="n-n60">
        <link targets="n-r60"/>
    </node>
    <a label="u" ref="n-n60" as="xces">
        <fs>
            <f name="id" value="sw3101B-0023"/>
            <f name="end" value="69.744250"/>
            <f name="start" value="67.882875"/>
        </fs>
    </a>
    <region xml:id="n-r61" anchors="1475 1604"/>
    <node xml:id="n-n61">
        <link targets="n-r61"/>
    </node>
    <a label="turn" ref="n-n61" as="xces">
        <fs>
            <f name="who" value="A"/>
            <f name="id" value="t27"/>
        </fs>
    </a>
    <region xml:id="n-r62" anchors="1479 1601"/>
    <node xml:id="n-n62">
        <link targets="n-r62"/>
    </node>
    <a label="u" ref="n-n62" as="xces">
        <fs>
            <f name="id" value="sw3101A-0025"/>
            <f name="end" value="75.428625"/>
            <f name="start" value="69.334875"/>
        </fs>
    </a>
    <region xml:id="n-r63" anchors="1607 1632"/>
    <node xml:id="n-n63">
        <link targets="n-r63"/>
    </node>
    <a label="turn" ref="n-n63" as="xces">
        <fs>
            <f name="who" value="B"/>
            <f name="id" value="t28"/>
        </fs>
    </a>
    <region xml:id="n-r64" anchors="1611 1629"/>
    <node xml:id="n-n64">
        <link targets="n-r64"/>
    </node>
    <a label="u" ref="n-n64" as="xces">
        <fs>
            <f name="id" value="sw3101B-0025"/>
            <f name="end" value="76.672000"/>
            <f name="start" value="74.977250"/>
        </fs>
    </a>
    <region xml:id="n-r65" anchors="1635 1675"/>
    <node xml:id="n-n65">
        <link targets="n-r65"/>
    </node>
    <a label="turn" ref="n-n65" as="xces">
        <fs>
            <f name="who" value="A"/>
            <f name="id" value="t29"/>
        </fs>
    </a>
    <region xml:id="n-r66" anchors="1639 1672"/>
    <node xml:id="n-n66">
        <link targets="n-r66"/>
    </node>
    <a label="u" ref="n-n66" as="xces">
        <fs>
            <f name="id" value="sw3101A-0026"/>
            <f name="end" value="80.386250"/>
            <f name="start" value="75.428625"/>
        </fs>
    </a>
    <region xml:id="n-r67" anchors="1678 1687"/>
    <node xml:id="n-n67">
        <link targets="n-r67"/>
    </node>
    <a label="turn" ref="n-n67" as="xces">
        <fs>
            <f name="who" value="B"/>
            <f name="id" value="t30"/>
        </fs>
    </a>
    <region xml:id="n-r68" anchors="1682 1684"/>
    <node xml:id="n-n68">
        <link targets="n-r68"/>
    </node>
    <a label="u" ref="n-n68" as="xces">
        <fs>
            <f name="id" value="sw3101B-0027"/>
            <f name="end" value="81.058625"/>
            <f name="start" value="78.479875"/>
        </fs>
    </a>
    <region xml:id="n-r69" anchors="1690 1699"/>
    <node xml:id="n-n69">
        <link targets="n-r69"/>
    </node>
    <a label="turn" ref="n-n69" as="xces">
        <fs>
            <f name="who" value="A"/>
            <f name="id" value="t31"/>
        </fs>
    </a>
    <region xml:id="n-r70" anchors="1694 1696"/>
    <node xml:id="n-n70">
        <link targets="n-r70"/>
    </node>
    <a label="u" ref="n-n70" as="xces">
        <fs>
            <f name="id" value="sw3101A-0027"/>
            <f name="end" value="82.290750"/>
            <f name="start" value="80.386250"/>
        </fs>
    </a>
    <region xml:id="n-r71" anchors="1702 1745"/>
    <node xml:id="n-n71">
        <link targets="n-r71"/>
    </node>
    <a label="turn" ref="n-n71" as="xces">
        <fs>
            <f name="who" value="B"/>
            <f name="id" value="t32"/>
        </fs>
    </a>
    <region xml:id="n-r72" anchors="1706 1742"/>
    <node xml:id="n-n72">
        <link targets="n-r72"/>
    </node>
    <a label="u" ref="n-n72" as="xces">
        <fs>
            <f name="id" value="sw3101B-0028"/>
            <f name="end" value="82.840250"/>
            <f name="start" value="81.058625"/>
        </fs>
    </a>
    <region xml:id="n-r73" anchors="1748 1809"/>
    <node xml:id="n-n73">
        <link targets="n-r73"/>
    </node>
    <a label="turn" ref="n-n73" as="xces">
        <fs>
            <f name="who" value="A"/>
            <f name="id" value="t33"/>
        </fs>
    </a>
    <region xml:id="n-r74" anchors="1752 1806"/>
    <node xml:id="n-n74">
        <link targets="n-r74"/>
    </node>
    <a label="u" ref="n-n74" as="xces">
        <fs>
            <f name="id" value="sw3101A-0028"/>
            <f name="end" value="87.450250"/>
            <f name="start" value="82.290750"/>
        </fs>
    </a>
    <region xml:id="n-r75" anchors="1812 1829"/>
    <node xml:id="n-n75">
        <link targets="n-r75"/>
    </node>
    <a label="turn" ref="n-n75" as="xces">
        <fs>
            <f name="who" value="B"/>
            <f name="id" value="t34"/>
        </fs>
    </a>
    <region xml:id="n-r76" anchors="1816 1826"/>
    <node xml:id="n-n76">
        <link targets="n-r76"/>
    </node>
    <a label="u" ref="n-n76" as="xces">
        <fs>
            <f name="id" value="sw3101B-0030"/>
            <f name="end" value="86.375125"/>
            <f name="start" value="85.214875"/>
        </fs>
    </a>
    <region xml:id="n-r77" anchors="1832 2181"/>
    <node xml:id="n-n77">
        <link targets="n-r77"/>
    </node>
    <a label="turn" ref="n-n77" as="xces">
        <fs>
            <f name="who" value="A"/>
            <f name="id" value="t35"/>
        </fs>
    </a>
    <region xml:id="n-r78" anchors="1836 2076"/>
    <node xml:id="n-n78">
        <link targets="n-r78"/>
    </node>
    <a label="u" ref="n-n78" as="xces">
        <fs>
            <f name="id" value="sw3101A-0029"/>
            <f name="end" value="100.106875"/>
            <f name="start" value="87.450250"/>
        </fs>
    </a>
    <region xml:id="n-r79" anchors="2080 2178"/>
    <node xml:id="n-n79">
        <link targets="n-r79"/>
    </node>
    <a label="u" ref="n-n79" as="xces">
        <fs>
            <f name="id" value="sw3101A-0030"/>
            <f name="end" value="104.675125"/>
            <f name="start" value="100.106875"/>
        </fs>
    </a>
    <region xml:id="n-r80" anchors="2184 2211"/>
    <node xml:id="n-n80">
        <link targets="n-r80"/>
    </node>
    <a label="turn" ref="n-n80" as="xces">
        <fs>
            <f name="who" value="B"/>
            <f name="id" value="t36"/>
        </fs>
    </a>
    <region xml:id="n-r81" anchors="2188 2208"/>
    <node xml:id="n-n81">
        <link targets="n-r81"/>
    </node>
    <a label="u" ref="n-n81" as="xces">
        <fs>
            <f name="id" value="sw3101B-0032"/>
            <f name="end" value="105.945125"/>
            <f name="start" value="104.313250"/>
        </fs>
    </a>
    <region xml:id="n-r82" anchors="2214 2265"/>
    <node xml:id="n-n82">
        <link targets="n-r82"/>
    </node>
    <a label="turn" ref="n-n82" as="xces">
        <fs>
            <f name="who" value="A"/>
            <f name="id" value="t37"/>
        </fs>
    </a>
    <region xml:id="n-r83" anchors="2218 2262"/>
    <node xml:id="n-n83">
        <link targets="n-r83"/>
    </node>
    <a label="u" ref="n-n83" as="xces">
        <fs>
            <f name="id" value="sw3101A-0032"/>
            <f name="end" value="108.556125"/>
            <f name="start" value="105.770250"/>
        </fs>
    </a>
    <region xml:id="n-r84" anchors="2268 2304"/>
    <node xml:id="n-n84">
        <link targets="n-r84"/>
    </node>
    <a label="turn" ref="n-n84" as="xces">
        <fs>
            <f name="who" value="B"/>
            <f name="id" value="t38"/>
        </fs>
    </a>
    <region xml:id="n-r85" anchors="2272 2301"/>
    <node xml:id="n-n85">
        <link targets="n-r85"/>
    </node>
    <a label="u" ref="n-n85" as="xces">
        <fs>
            <f name="id" value="sw3101B-0034"/>
            <f name="end" value="109.606000"/>
            <f name="start" value="107.410000"/>
        </fs>
    </a>
    <region xml:id="n-r86" anchors="2307 2399"/>
    <node xml:id="n-n86">
        <link targets="n-r86"/>
    </node>
    <a label="turn" ref="n-n86" as="xces">
        <fs>
            <f name="who" value="A"/>
            <f name="id" value="t39"/>
        </fs>
    </a>
    <region xml:id="n-r87" anchors="2311 2396"/>
    <node xml:id="n-n87">
        <link targets="n-r87"/>
    </node>
    <a label="u" ref="n-n87" as="xces">
        <fs>
            <f name="id" value="sw3101A-0033"/>
            <f name="end" value="115.924250"/>
            <f name="start" value="108.556125"/>
        </fs>
    </a>
    <region xml:id="n-r88" anchors="2402 2469"/>
    <node xml:id="n-n88">
        <link targets="n-r88"/>
    </node>
    <a label="turn" ref="n-n88" as="xces">
        <fs>
            <f name="who" value="B"/>
            <f name="id" value="t40"/>
        </fs>
    </a>
    <region xml:id="n-r89" anchors="2406 2408"/>
    <node xml:id="n-n89">
        <link targets="n-r89"/>
    </node>
    <a label="u" ref="n-n89" as="xces">
        <fs>
            <f name="id" value="sw3101B-0035"/>
            <f name="end" value="111.073625"/>
            <f name="start" value="109.606000"/>
        </fs>
    </a>
    <region xml:id="n-r90" anchors="2412 2466"/>
    <node xml:id="n-n90">
        <link targets="n-r90"/>
    </node>
    <a label="u" ref="n-n90" as="xces">
        <fs>
            <f name="id" value="sw3101B-0037"/>
            <f name="end" value="117.640750"/>
            <f name="start" value="112.978125"/>
        </fs>
    </a>
    <region xml:id="n-r91" anchors="2472 2677"/>
    <node xml:id="n-n91">
        <link targets="n-r91"/>
    </node>
    <a label="turn" ref="n-n91" as="xces">
        <fs>
            <f name="who" value="A"/>
            <f name="id" value="t41"/>
        </fs>
    </a>
    <region xml:id="n-r92" anchors="2476 2483"/>
    <node xml:id="n-n92">
        <link targets="n-r92"/>
    </node>
    <a label="u" ref="n-n92" as="xces">
        <fs>
            <f name="id" value="sw3101A-0034"/>
            <f name="end" value="117.716250"/>
            <f name="start" value="115.924250"/>
        </fs>
    </a>
    <region xml:id="n-r93" anchors="2487 2674"/>
    <node xml:id="n-n93">
        <link targets="n-r93"/>
    </node>
    <a label="u" ref="n-n93" as="xces">
        <fs>
            <f name="id" value="sw3101A-0035"/>
            <f name="end" value="128.181125"/>
            <f name="start" value="117.716250"/>
        </fs>
    </a>
    <region xml:id="n-r94" anchors="2680 2701"/>
    <node xml:id="n-n94">
        <link targets="n-r94"/>
    </node>
    <a label="turn" ref="n-n94" as="xces">
        <fs>
            <f name="who" value="B"/>
            <f name="id" value="t42"/>
        </fs>
    </a>
    <region xml:id="n-r95" anchors="2684 2698"/>
    <node xml:id="n-n95">
        <link targets="n-r95"/>
    </node>
    <a label="u" ref="n-n95" as="xces">
        <fs>
            <f name="id" value="sw3101B-0039"/>
            <f name="end" value="128.676250"/>
            <f name="start" value="126.901125"/>
        </fs>
    </a>
    <region xml:id="n-r96" anchors="2704 2898"/>
    <node xml:id="n-n96">
        <link targets="n-r96"/>
    </node>
    <a label="turn" ref="n-n96" as="xces">
        <fs>
            <f name="who" value="A"/>
            <f name="id" value="t43"/>
        </fs>
    </a>
    <region xml:id="n-r97" anchors="2708 2895"/>
    <node xml:id="n-n97">
        <link targets="n-r97"/>
    </node>
    <a label="u" ref="n-n97" as="xces">
        <fs>
            <f name="id" value="sw3101A-0036"/>
            <f name="end" value="140.408125"/>
            <f name="start" value="128.181125"/>
        </fs>
    </a>
    <region xml:id="n-r98" anchors="2901 2960"/>
    <node xml:id="n-n98">
        <link targets="n-r98"/>
    </node>
    <a label="turn" ref="n-n98" as="xces">
        <fs>
            <f name="who" value="B"/>
            <f name="id" value="t44"/>
        </fs>
    </a>
    <region xml:id="n-r99" anchors="2905 2921"/>
    <node xml:id="n-n99">
        <link targets="n-r99"/>
    </node>
    <a label="u" ref="n-n99" as="xces">
        <fs>
            <f name="id" value="sw3101B-0041"/>
            <f name="end" value="134.955375"/>
            <f name="start" value="133.410000"/>
        </fs>
    </a>
    <region xml:id="n-r100" anchors="2925 2957"/>
    <node xml:id="n-n100">
        <link targets="n-r100"/>
    </node>
    <a label="u" ref="n-n100" as="xces">
        <fs>
            <f name="id" value="sw3101B-0043"/>
            <f name="end" value="142.112625"/>
            <f name="start" value="139.735000"/>
        </fs>
    </a>
    <region xml:id="n-r101" anchors="2963 3016"/>
    <node xml:id="n-n101">
        <link targets="n-r101"/>
    </node>
    <a label="turn" ref="n-n101" as="xces">
        <fs>
            <f name="who" value="A"/>
            <f name="id" value="t45"/>
        </fs>
    </a>
    <region xml:id="n-r102" anchors="2967 2969"/>
    <node xml:id="n-n102">
        <link targets="n-r102"/>
    </node>
    <a label="u" ref="n-n102" as="xces">
        <fs>
            <f name="id" value="sw3101A-0037"/>
            <f name="end" value="141.911625"/>
            <f name="start" value="140.408125"/>
        </fs>
    </a>
    <region xml:id="n-r103" anchors="2973 3013"/>
    <node xml:id="n-n103">
        <link targets="n-r103"/>
    </node>
    <a label="u" ref="n-n103" as="xces">
        <fs>
            <f name="id" value="sw3101A-0038"/>
            <f name="end" value="144.974625"/>
            <f name="start" value="141.911625"/>
        </fs>
    </a>
    <region xml:id="n-r104" anchors="3019 3030"/>
    <node xml:id="n-n104">
        <link targets="n-r104"/>
    </node>
    <a label="turn" ref="n-n104" as="xces">
        <fs>
            <f name="who" value="B"/>
            <f name="id" value="t46"/>
        </fs>
    </a>
    <region xml:id="n-r105" anchors="3023 3027"/>
    <node xml:id="n-n105">
        <link targets="n-r105"/>
    </node>
    <a label="u" ref="n-n105" as="xces">
        <fs>
            <f name="id" value="sw3101B-0045"/>
            <f name="end" value="145.671500"/>
            <f name="start" value="144.363000"/>
        </fs>
    </a>
    <region xml:id="n-r106" anchors="3033 3050"/>
    <node xml:id="n-n106">
        <link targets="n-r106"/>
    </node>
    <a label="turn" ref="n-n106" as="xces">
        <fs>
            <f name="who" value="A"/>
            <f name="id" value="t47"/>
        </fs>
    </a>
    <region xml:id="n-r107" anchors="3037 3047"/>
    <node xml:id="n-n107">
        <link targets="n-r107"/>
    </node>
    <a label="u" ref="n-n107" as="xces">
        <fs>
            <f name="id" value="sw3101A-0039"/>
            <f name="end" value="146.908250"/>
            <f name="start" value="144.974625"/>
        </fs>
    </a>
    <region xml:id="n-r108" anchors="3053 3067"/>
    <node xml:id="n-n108">
        <link targets="n-r108"/>
    </node>
    <a label="turn" ref="n-n108" as="xces">
        <fs>
            <f name="who" value="B"/>
            <f name="id" value="t48"/>
        </fs>
    </a>
    <region xml:id="n-r109" anchors="3057 3064"/>
    <node xml:id="n-n109">
        <link targets="n-r109"/>
    </node>
    <a label="u" ref="n-n109" as="xces">
        <fs>
            <f name="id" value="sw3101B-0046"/>
            <f name="end" value="147.306125"/>
            <f name="start" value="145.671500"/>
        </fs>
    </a>
    <region xml:id="n-r110" anchors="3070 3124"/>
    <node xml:id="n-n110">
        <link targets="n-r110"/>
    </node>
    <a label="turn" ref="n-n110" as="xces">
        <fs>
            <f name="who" value="A"/>
            <f name="id" value="t49"/>
        </fs>
    </a>
    <region xml:id="n-r111" anchors="3074 3121"/>
    <node xml:id="n-n111">
        <link targets="n-r111"/>
    </node>
    <a label="u" ref="n-n111" as="xces">
        <fs>
            <f name="id" value="sw3101A-0040"/>
            <f name="end" value="149.343000"/>
            <f name="start" value="146.908250"/>
        </fs>
    </a>
    <region xml:id="n-r112" anchors="3127 3148"/>
    <node xml:id="n-n112">
        <link targets="n-r112"/>
    </node>
    <a label="turn" ref="n-n112" as="xces">
        <fs>
            <f name="who" value="B"/>
            <f name="id" value="t50"/>
        </fs>
    </a>
    <region xml:id="n-r113" anchors="3131 3145"/>
    <node xml:id="n-n113">
        <link targets="n-r113"/>
    </node>
    <a label="u" ref="n-n113" as="xces">
        <fs>
            <f name="id" value="sw3101B-0048"/>
            <f name="end" value="151.324250"/>
            <f name="start" value="148.383875"/>
        </fs>
    </a>
    <region xml:id="n-r114" anchors="3151 3275"/>
    <node xml:id="n-n114">
        <link targets="n-r114"/>
    </node>
    <a label="turn" ref="n-n114" as="xces">
        <fs>
            <f name="who" value="A"/>
            <f name="id" value="t51"/>
        </fs>
    </a>
    <region xml:id="n-r115" anchors="3155 3272"/>
    <node xml:id="n-n115">
        <link targets="n-r115"/>
    </node>
    <a label="u" ref="n-n115" as="xces">
        <fs>
            <f name="id" value="sw3101A-0042"/>
            <f name="end" value="159.397125"/>
            <f name="start" value="150.595625"/>
        </fs>
    </a>
    <region xml:id="n-r116" anchors="3278 3287"/>
    <node xml:id="n-n116">
        <link targets="n-r116"/>
    </node>
    <a label="turn" ref="n-n116" as="xces">
        <fs>
            <f name="who" value="B"/>
            <f name="id" value="t52"/>
        </fs>
    </a>
    <region xml:id="n-r117" anchors="3282 3284"/>
    <node xml:id="n-n117">
        <link targets="n-r117"/>
    </node>
    <a label="u" ref="n-n117" as="xces">
        <fs>
            <f name="id" value="sw3101B-0050"/>
            <f name="end" value="161.685125"/>
            <f name="start" value="159.380250"/>
        </fs>
    </a>
    <region xml:id="n-r118" anchors="3290 3493"/>
    <node xml:id="n-n118">
        <link targets="n-r118"/>
    </node>
    <a label="turn" ref="n-n118" as="xces">
        <fs>
            <f name="who" value="A"/>
            <f name="id" value="t53"/>
        </fs>
    </a>
    <region xml:id="n-r119" anchors="3294 3490"/>
    <node xml:id="n-n119">
        <link targets="n-r119"/>
    </node>
    <a label="u" ref="n-n119" as="xces">
        <fs>
            <f name="id" value="sw3101A-0044"/>
            <f name="end" value="173.185250"/>
            <f name="start" value="160.732875"/>
        </fs>
    </a>
    <region xml:id="n-r120" anchors="3496 3512"/>
    <node xml:id="n-n120">
        <link targets="n-r120"/>
    </node>
    <a label="turn" ref="n-n120" as="xces">
        <fs>
            <f name="who" value="B"/>
            <f name="id" value="t54"/>
        </fs>
    </a>
    <region xml:id="n-r121" anchors="3500 3509"/>
    <node xml:id="n-n121">
        <link targets="n-r121"/>
    </node>
    <a label="u" ref="n-n121" as="xces">
        <fs>
            <f name="id" value="sw3101B-0052"/>
            <f name="end" value="174.325500"/>
            <f name="start" value="172.745500"/>
        </fs>
    </a>
    <region xml:id="n-r122" anchors="3515 3605"/>
    <node xml:id="n-n122">
        <link targets="n-r122"/>
    </node>
    <a label="turn" ref="n-n122" as="xces">
        <fs>
            <f name="who" value="A"/>
            <f name="id" value="t55"/>
        </fs>
    </a>
    <region xml:id="n-r123" anchors="3519 3602"/>
    <node xml:id="n-n123">
        <link targets="n-r123"/>
    </node>
    <a label="u" ref="n-n123" as="xces">
        <fs>
            <f name="id" value="sw3101A-0045"/>
            <f name="end" value="178.464000"/>
            <f name="start" value="173.185250"/>
        </fs>
    </a>
    <region xml:id="n-r124" anchors="3608 3618"/>
    <node xml:id="n-n124">
        <link targets="n-r124"/>
    </node>
    <a label="turn" ref="n-n124" as="xces">
        <fs>
            <f name="who" value="B"/>
            <f name="id" value="t56"/>
        </fs>
    </a>
    <region xml:id="n-r125" anchors="3612 3615"/>
    <node xml:id="n-n125">
        <link targets="n-r125"/>
    </node>
    <a label="u" ref="n-n125" as="xces">
        <fs>
            <f name="id" value="sw3101B-0054"/>
            <f name="end" value="177.197125"/>
            <f name="start" value="175.937000"/>
        </fs>
    </a>
    <region xml:id="n-r126" anchors="3621 3637"/>
    <node xml:id="n-n126">
        <link targets="n-r126"/>
    </node>
    <a label="turn" ref="n-n126" as="xces">
        <fs>
            <f name="who" value="A"/>
            <f name="id" value="t57"/>
        </fs>
    </a>
    <region xml:id="n-r127" anchors="3625 3634"/>
    <node xml:id="n-n127">
        <link targets="n-r127"/>
    </node>
    <a label="u" ref="n-n127" as="xces">
        <fs>
            <f name="id" value="sw3101A-0046"/>
            <f name="end" value="180.506250"/>
            <f name="start" value="178.464000"/>
        </fs>
    </a>
    <region xml:id="n-r128" anchors="3640 3671"/>
    <node xml:id="n-n128">
        <link targets="n-r128"/>
    </node>
    <a label="turn" ref="n-n128" as="xces">
        <fs>
            <f name="who" value="B"/>
            <f name="id" value="t58"/>
        </fs>
    </a>
    <region xml:id="n-r129" anchors="3644 3668"/>
    <node xml:id="n-n129">
        <link targets="n-r129"/>
    </node>
    <a label="u" ref="n-n129" as="xces">
        <fs>
            <f name="id" value="sw3101B-0056"/>
            <f name="end" value="180.936000"/>
            <f name="start" value="179.302000"/>
        </fs>
    </a>
    <region xml:id="n-r130" anchors="3674 3698"/>
    <node xml:id="n-n130">
        <link targets="n-r130"/>
    </node>
    <a label="turn" ref="n-n130" as="xces">
        <fs>
            <f name="who" value="A"/>
            <f name="id" value="t59"/>
        </fs>
    </a>
    <region xml:id="n-r131" anchors="3678 3695"/>
    <node xml:id="n-n131">
        <link targets="n-r131"/>
    </node>
    <a label="u" ref="n-n131" as="xces">
        <fs>
            <f name="id" value="sw3101A-0047"/>
            <f name="end" value="183.194250"/>
            <f name="start" value="180.506250"/>
        </fs>
    </a>
    <region xml:id="n-r132" anchors="3701 3823"/>
    <node xml:id="n-n132">
        <link targets="n-r132"/>
    </node>
    <a label="turn" ref="n-n132" as="xces">
        <fs>
            <f name="who" value="B"/>
            <f name="id" value="t60"/>
        </fs>
    </a>
    <region xml:id="n-r133" anchors="3705 3820"/>
    <node xml:id="n-n133">
        <link targets="n-r133"/>
    </node>
    <a label="u" ref="n-n133" as="xces">
        <fs>
            <f name="id" value="sw3101B-0058"/>
            <f name="end" value="188.280500"/>
            <f name="start" value="182.047500"/>
        </fs>
    </a>
    <region xml:id="n-r134" anchors="3826 3859"/>
    <node xml:id="n-n134">
        <link targets="n-r134"/>
    </node>
    <a label="turn" ref="n-n134" as="xces">
        <fs>
            <f name="who" value="A"/>
            <f name="id" value="t61"/>
        </fs>
    </a>
    <region xml:id="n-r135" anchors="3830 3856"/>
    <node xml:id="n-n135">
        <link targets="n-r135"/>
    </node>
    <a label="u" ref="n-n135" as="xces">
        <fs>
            <f name="id" value="sw3101A-0049"/>
            <f name="end" value="188.544250"/>
            <f name="start" value="186.091375"/>
        </fs>
    </a>
    <region xml:id="n-r136" anchors="3862 3983"/>
    <node xml:id="n-n136">
        <link targets="n-r136"/>
    </node>
    <a label="turn" ref="n-n136" as="xces">
        <fs>
            <f name="who" value="B"/>
            <f name="id" value="t62"/>
        </fs>
    </a>
    <region xml:id="n-r137" anchors="3866 3980"/>
    <node xml:id="n-n137">
        <link targets="n-r137"/>
    </node>
    <a label="u" ref="n-n137" as="xces">
        <fs>
            <f name="id" value="sw3101B-0059"/>
            <f name="end" value="196.296250"/>
            <f name="start" value="188.280500"/>
        </fs>
    </a>
    <region xml:id="n-r138" anchors="3986 3997"/>
    <node xml:id="n-n138">
        <link targets="n-r138"/>
    </node>
    <a label="turn" ref="n-n138" as="xces">
        <fs>
            <f name="who" value="A"/>
            <f name="id" value="t63"/>
        </fs>
    </a>
    <region xml:id="n-r139" anchors="3990 3994"/>
    <node xml:id="n-n139">
        <link targets="n-r139"/>
    </node>
    <a label="u" ref="n-n139" as="xces">
        <fs>
            <f name="id" value="sw3101A-0051"/>
            <f name="end" value="191.416500"/>
            <f name="start" value="189.897750"/>
        </fs>
    </a>
    <region xml:id="n-r140" anchors="4000 4034"/>
    <node xml:id="n-n140">
        <link targets="n-r140"/>
    </node>
    <a label="turn" ref="n-n140" as="xces">
        <fs>
            <f name="who" value="B"/>
            <f name="id" value="t64"/>
        </fs>
    </a>
    <region xml:id="n-r141" anchors="4004 4031"/>
    <node xml:id="n-n141">
        <link targets="n-r141"/>
    </node>
    <a label="u" ref="n-n141" as="xces">
        <fs>
            <f name="id" value="sw3101B-0060"/>
            <f name="end" value="198.724750"/>
            <f name="start" value="196.296250"/>
        </fs>
    </a>
    <region xml:id="n-r142" anchors="4037 4053"/>
    <node xml:id="n-n142">
        <link targets="n-r142"/>
    </node>
    <a label="turn" ref="n-n142" as="xces">
        <fs>
            <f name="who" value="A"/>
            <f name="id" value="t65"/>
        </fs>
    </a>
    <region xml:id="n-r143" anchors="4041 4050"/>
    <node xml:id="n-n143">
        <link targets="n-r143"/>
    </node>
    <a label="u" ref="n-n143" as="xces">
        <fs>
            <f name="id" value="sw3101A-0053"/>
            <f name="end" value="199.669500"/>
            <f name="start" value="197.970000"/>
        </fs>
    </a>
    <region xml:id="n-r144" anchors="4056 4102"/>
    <node xml:id="n-n144">
        <link targets="n-r144"/>
    </node>
    <a label="turn" ref="n-n144" as="xces">
        <fs>
            <f name="who" value="B"/>
            <f name="id" value="t66"/>
        </fs>
    </a>
    <region xml:id="n-r145" anchors="4060 4099"/>
    <node xml:id="n-n145">
        <link targets="n-r145"/>
    </node>
    <a label="u" ref="n-n145" as="xces">
        <fs>
            <f name="id" value="sw3101B-0061"/>
            <f name="end" value="201.792125"/>
            <f name="start" value="198.724750"/>
        </fs>
    </a>
    <region xml:id="n-r146" anchors="4105 4145"/>
    <node xml:id="n-n146">
        <link targets="n-r146"/>
    </node>
    <a label="turn" ref="n-n146" as="xces">
        <fs>
            <f name="who" value="A"/>
            <f name="id" value="t67"/>
        </fs>
    </a>
    <region xml:id="n-r147" anchors="4109 4112"/>
    <node xml:id="n-n147">
        <link targets="n-r147"/>
    </node>
    <a label="u" ref="n-n147" as="xces">
        <fs>
            <f name="id" value="sw3101A-0054"/>
            <f name="end" value="200.880750"/>
            <f name="start" value="199.669500"/>
        </fs>
    </a>
    <region xml:id="n-r148" anchors="4116 4142"/>
    <node xml:id="n-n148">
        <link targets="n-r148"/>
    </node>
    <a label="u" ref="n-n148" as="xces">
        <fs>
            <f name="id" value="sw3101A-0055"/>
            <f name="end" value="203.191625"/>
            <f name="start" value="200.880750"/>
        </fs>
    </a>
    <region xml:id="n-r149" anchors="4148 4166"/>
    <node xml:id="n-n149">
        <link targets="n-r149"/>
    </node>
    <a label="turn" ref="n-n149" as="xces">
        <fs>
            <f name="who" value="B"/>
            <f name="id" value="t68"/>
        </fs>
    </a>
    <region xml:id="n-r150" anchors="4152 4163"/>
    <node xml:id="n-n150">
        <link targets="n-r150"/>
    </node>
    <a label="u" ref="n-n150" as="xces">
        <fs>
            <f name="id" value="sw3101B-0062"/>
            <f name="end" value="203.460000"/>
            <f name="start" value="201.792125"/>
        </fs>
    </a>
    <region xml:id="n-r151" anchors="4169 4179"/>
    <node xml:id="n-n151">
        <link targets="n-r151"/>
    </node>
    <a label="turn" ref="n-n151" as="xces">
        <fs>
            <f name="who" value="A"/>
            <f name="id" value="t69"/>
        </fs>
    </a>
    <region xml:id="n-r152" anchors="4173 4176"/>
    <node xml:id="n-n152">
        <link targets="n-r152"/>
    </node>
    <a label="u" ref="n-n152" as="xces">
        <fs>
            <f name="id" value="sw3101A-0056"/>
            <f name="end" value="204.403750"/>
            <f name="start" value="203.191625"/>
        </fs>
    </a>
    <region xml:id="n-r153" anchors="4182 4311"/>
    <node xml:id="n-n153">
        <link targets="n-r153"/>
    </node>
    <a label="turn" ref="n-n153" as="xces">
        <fs>
            <f name="who" value="B"/>
            <f name="id" value="t70"/>
        </fs>
    </a>
    <region xml:id="n-r154" anchors="4186 4308"/>
    <node xml:id="n-n154">
        <link targets="n-r154"/>
    </node>
    <a label="u" ref="n-n154" as="xces">
        <fs>
            <f name="id" value="sw3101B-0063"/>
            <f name="end" value="208.289500"/>
            <f name="start" value="203.460000"/>
        </fs>
    </a>
    <region xml:id="n-r155" anchors="4314 4342"/>
    <node xml:id="n-n155">
        <link targets="n-r155"/>
    </node>
    <a label="turn" ref="n-n155" as="xces">
        <fs>
            <f name="who" value="A"/>
            <f name="id" value="t71"/>
        </fs>
    </a>
    <region xml:id="n-r156" anchors="4318 4333"/>
    <node xml:id="n-n156">
        <link targets="n-r156"/>
    </node>
    <a label="u" ref="n-n156" as="xces">
        <fs>
            <f name="id" value="sw3101A-0058"/>
            <f name="end" value="209.991875"/>
            <f name="start" value="207.809250"/>
        </fs>
    </a>
    <region xml:id="n-r157" anchors="4337 4339"/>
    <node xml:id="n-n157">
        <link targets="n-r157"/>
    </node>
    <a label="u" ref="n-n157" as="xces">
        <fs>
            <f name="id" value="sw3101A-0059"/>
            <f name="end" value="211.456625"/>
            <f name="start" value="209.991875"/>
        </fs>
    </a>
    <region xml:id="n-r158" anchors="4345 4372"/>
    <node xml:id="n-n158">
        <link targets="n-r158"/>
    </node>
    <a label="turn" ref="n-n158" as="xces">
        <fs>
            <f name="who" value="B"/>
            <f name="id" value="t72"/>
        </fs>
    </a>
    <region xml:id="n-r159" anchors="4349 4369"/>
    <node xml:id="n-n159">
        <link targets="n-r159"/>
    </node>
    <a label="u" ref="n-n159" as="xces">
        <fs>
            <f name="id" value="sw3101B-0065"/>
            <f name="end" value="212.293250"/>
            <f name="start" value="210.264875"/>
        </fs>
    </a>
    <region xml:id="n-r160" anchors="4375 4427"/>
    <node xml:id="n-n160">
        <link targets="n-r160"/>
    </node>
    <a label="turn" ref="n-n160" as="xces">
        <fs>
            <f name="who" value="A"/>
            <f name="id" value="t73"/>
        </fs>
    </a>
    <region xml:id="n-r161" anchors="4379 4424"/>
    <node xml:id="n-n161">
        <link targets="n-r161"/>
    </node>
    <a label="u" ref="n-n161" as="xces">
        <fs>
            <f name="id" value="sw3101A-0060"/>
            <f name="end" value="215.516750"/>
            <f name="start" value="211.456625"/>
        </fs>
    </a>
    <region xml:id="n-r162" anchors="4430 4499"/>
    <node xml:id="n-n162">
        <link targets="n-r162"/>
    </node>
    <a label="turn" ref="n-n162" as="xces">
        <fs>
            <f name="who" value="B"/>
            <f name="id" value="t74"/>
        </fs>
    </a>
    <region xml:id="n-r163" anchors="4434 4438"/>
    <node xml:id="n-n163">
        <link targets="n-r163"/>
    </node>
    <a label="u" ref="n-n163" as="xces">
        <fs>
            <f name="id" value="sw3101B-0066"/>
            <f name="end" value="213.708125"/>
            <f name="start" value="212.293250"/>
        </fs>
    </a>
    <region xml:id="n-r164" anchors="4442 4454"/>
    <node xml:id="n-n164">
        <link targets="n-r164"/>
    </node>
    <a label="u" ref="n-n164" as="xces">
        <fs>
            <f name="id" value="sw3101B-0067"/>
            <f name="end" value="215.041375"/>
            <f name="start" value="213.708125"/>
        </fs>
    </a>
    <region xml:id="n-r165" anchors="4458 4496"/>
    <node xml:id="n-n165">
        <link targets="n-r165"/>
    </node>
    <a label="u" ref="n-n165" as="xces">
        <fs>
            <f name="id" value="sw3101B-0068"/>
            <f name="end" value="217.551625"/>
            <f name="start" value="215.041375"/>
        </fs>
    </a>
    <region xml:id="n-r166" anchors="4502 4536"/>
    <node xml:id="n-n166">
        <link targets="n-r166"/>
    </node>
    <a label="turn" ref="n-n166" as="xces">
        <fs>
            <f name="who" value="A"/>
            <f name="id" value="t75"/>
        </fs>
    </a>
    <region xml:id="n-r167" anchors="4506 4533"/>
    <node xml:id="n-n167">
        <link targets="n-r167"/>
    </node>
    <a label="u" ref="n-n167" as="xces">
        <fs>
            <f name="id" value="sw3101A-0062"/>
            <f name="end" value="220.875000"/>
            <f name="start" value="217.943500"/>
        </fs>
    </a>
    <region xml:id="n-r168" anchors="4539 4550"/>
    <node xml:id="n-n168">
        <link targets="n-r168"/>
    </node>
    <a label="turn" ref="n-n168" as="xces">
        <fs>
            <f name="who" value="B"/>
            <f name="id" value="t76"/>
        </fs>
    </a>
    <region xml:id="n-r169" anchors="4543 4547"/>
    <node xml:id="n-n169">
        <link targets="n-r169"/>
    </node>
    <a label="u" ref="n-n169" as="xces">
        <fs>
            <f name="id" value="sw3101B-0070"/>
            <f name="end" value="220.949625"/>
            <f name="start" value="219.766625"/>
        </fs>
    </a>
    <region xml:id="n-r170" anchors="4553 4597"/>
    <node xml:id="n-n170">
        <link targets="n-r170"/>
    </node>
    <a label="turn" ref="n-n170" as="xces">
        <fs>
            <f name="who" value="A"/>
            <f name="id" value="t77"/>
        </fs>
    </a>
    <region xml:id="n-r171" anchors="4557 4594"/>
    <node xml:id="n-n171">
        <link targets="n-r171"/>
    </node>
    <a label="u" ref="n-n171" as="xces">
        <fs>
            <f name="id" value="sw3101A-0063"/>
            <f name="end" value="222.773125"/>
            <f name="start" value="220.875000"/>
        </fs>
    </a>
    <region xml:id="n-r172" anchors="4600 4691"/>
    <node xml:id="n-n172">
        <link targets="n-r172"/>
    </node>
    <a label="turn" ref="n-n172" as="xces">
        <fs>
            <f name="who" value="B"/>
            <f name="id" value="t78"/>
        </fs>
    </a>
    <region xml:id="n-r173" anchors="4604 4688"/>
    <node xml:id="n-n173">
        <link targets="n-r173"/>
    </node>
    <a label="u" ref="n-n173" as="xces">
        <fs>
            <f name="id" value="sw3101B-0072"/>
            <f name="end" value="228.246500"/>
            <f name="start" value="222.031375"/>
        </fs>
    </a>
    <region xml:id="n-r174" anchors="4694 4703"/>
    <node xml:id="n-n174">
        <link targets="n-r174"/>
    </node>
    <a label="turn" ref="n-n174" as="xces">
        <fs>
            <f name="who" value="A"/>
            <f name="id" value="t79"/>
        </fs>
    </a>
    <region xml:id="n-r175" anchors="4698 4700"/>
    <node xml:id="n-n175">
        <link targets="n-r175"/>
    </node>
    <a label="u" ref="n-n175" as="xces">
        <fs>
            <f name="id" value="sw3101A-0065"/>
            <f name="end" value="229.212375"/>
            <f name="start" value="225.433375"/>
        </fs>
    </a>
    <region xml:id="n-r176" anchors="4706 4733"/>
    <node xml:id="n-n176">
        <link targets="n-r176"/>
    </node>
    <a label="turn" ref="n-n176" as="xces">
        <fs>
            <f name="who" value="B"/>
            <f name="id" value="t80"/>
        </fs>
    </a>
    <region xml:id="n-r177" anchors="4710 4730"/>
    <node xml:id="n-n177">
        <link targets="n-r177"/>
    </node>
    <a label="u" ref="n-n177" as="xces">
        <fs>
            <f name="id" value="sw3101B-0073"/>
            <f name="end" value="229.675750"/>
            <f name="start" value="228.246500"/>
        </fs>
    </a>
    <region xml:id="n-r178" anchors="4736 4846"/>
    <node xml:id="n-n178">
        <link targets="n-r178"/>
    </node>
    <a label="turn" ref="n-n178" as="xces">
        <fs>
            <f name="who" value="A"/>
            <f name="id" value="t81"/>
        </fs>
    </a>
    <region xml:id="n-r179" anchors="4740 4843"/>
    <node xml:id="n-n179">
        <link targets="n-r179"/>
    </node>
    <a label="u" ref="n-n179" as="xces">
        <fs>
            <f name="id" value="sw3101A-0066"/>
            <f name="end" value="235.988375"/>
            <f name="start" value="229.212375"/>
        </fs>
    </a>
    <region xml:id="n-r180" anchors="4849 4870"/>
    <node xml:id="n-n180">
        <link targets="n-r180"/>
    </node>
    <a label="turn" ref="n-n180" as="xces">
        <fs>
            <f name="who" value="B"/>
            <f name="id" value="t82"/>
        </fs>
    </a>
    <region xml:id="n-r181" anchors="4853 4867"/>
    <node xml:id="n-n181">
        <link targets="n-r181"/>
    </node>
    <a label="u" ref="n-n181" as="xces">
        <fs>
            <f name="id" value="sw3101B-0075"/>
            <f name="end" value="236.246000"/>
            <f name="start" value="234.609750"/>
        </fs>
    </a>
    <region xml:id="n-r182" anchors="4873 5133"/>
    <node xml:id="n-n182">
        <link targets="n-r182"/>
    </node>
    <a label="turn" ref="n-n182" as="xces">
        <fs>
            <f name="who" value="A"/>
            <f name="id" value="t83"/>
        </fs>
    </a>
    <region xml:id="n-r183" anchors="4877 5130"/>
    <node xml:id="n-n183">
        <link targets="n-r183"/>
    </node>
    <a label="u" ref="n-n183" as="xces">
        <fs>
            <f name="id" value="sw3101A-0067"/>
            <f name="end" value="249.776875"/>
            <f name="start" value="235.988375"/>
        </fs>
    </a>
    <region xml:id="n-r184" anchors="5136 5189"/>
    <node xml:id="n-n184">
        <link targets="n-r184"/>
    </node>
    <a label="turn" ref="n-n184" as="xces">
        <fs>
            <f name="who" value="B"/>
            <f name="id" value="t84"/>
        </fs>
    </a>
    <region xml:id="n-r185" anchors="5140 5186"/>
    <node xml:id="n-n185">
        <link targets="n-r185"/>
    </node>
    <a label="u" ref="n-n185" as="xces">
        <fs>
            <f name="id" value="sw3101B-0077"/>
            <f name="end" value="251.373375"/>
            <f name="start" value="249.110000"/>
        </fs>
    </a>
    <region xml:id="n-r186" anchors="5192 5446"/>
    <node xml:id="n-n186">
        <link targets="n-r186"/>
    </node>
    <a label="turn" ref="n-n186" as="xces">
        <fs>
            <f name="who" value="A"/>
            <f name="id" value="t85"/>
        </fs>
    </a>
    <region xml:id="n-r187" anchors="5196 5443"/>
    <node xml:id="n-n187">
        <link targets="n-r187"/>
    </node>
    <a label="u" ref="n-n187" as="xces">
        <fs>
            <f name="id" value="sw3101A-0069"/>
            <f name="end" value="263.536625"/>
            <f name="start" value="251.284250"/>
        </fs>
    </a>
    <region xml:id="n-r188" anchors="5449 5468"/>
    <node xml:id="n-n188">
        <link targets="n-r188"/>
    </node>
    <a label="turn" ref="n-n188" as="xces">
        <fs>
            <f name="who" value="B"/>
            <f name="id" value="t86"/>
        </fs>
    </a>
    <region xml:id="n-r189" anchors="5453 5465"/>
    <node xml:id="n-n189">
        <link targets="n-r189"/>
    </node>
    <a label="u" ref="n-n189" as="xces">
        <fs>
            <f name="id" value="sw3101B-0079"/>
            <f name="end" value="263.534625"/>
            <f name="start" value="262.136750"/>
        </fs>
    </a>
    <region xml:id="n-r190" anchors="5471 5642"/>
    <node xml:id="n-n190">
        <link targets="n-r190"/>
    </node>
    <a label="turn" ref="n-n190" as="xces">
        <fs>
            <f name="who" value="A"/>
            <f name="id" value="t87"/>
        </fs>
    </a>
    <region xml:id="n-r191" anchors="5475 5639"/>
    <node xml:id="n-n191">
        <link targets="n-r191"/>
    </node>
    <a label="u" ref="n-n191" as="xces">
        <fs>
            <f name="id" value="sw3101A-0070"/>
            <f name="end" value="272.326500"/>
            <f name="start" value="263.536625"/>
        </fs>
    </a>
    <region xml:id="n-r192" anchors="5645 5668"/>
    <node xml:id="n-n192">
        <link targets="n-r192"/>
    </node>
    <a label="turn" ref="n-n192" as="xces">
        <fs>
            <f name="who" value="B"/>
            <f name="id" value="t88"/>
        </fs>
    </a>
    <region xml:id="n-r193" anchors="5649 5665"/>
    <node xml:id="n-n193">
        <link targets="n-r193"/>
    </node>
    <a label="u" ref="n-n193" as="xces">
        <fs>
            <f name="id" value="sw3101B-0081"/>
            <f name="end" value="272.843750"/>
            <f name="start" value="271.425875"/>
        </fs>
    </a>
    <region xml:id="n-r194" anchors="5671 5789"/>
    <node xml:id="n-n194">
        <link targets="n-r194"/>
    </node>
    <a label="turn" ref="n-n194" as="xces">
        <fs>
            <f name="who" value="A"/>
            <f name="id" value="t89"/>
        </fs>
    </a>
    <region xml:id="n-r195" anchors="5675 5786"/>
    <node xml:id="n-n195">
        <link targets="n-r195"/>
    </node>
    <a label="u" ref="n-n195" as="xces">
        <fs>
            <f name="id" value="sw3101A-0071"/>
            <f name="end" value="280.281875"/>
            <f name="start" value="272.326500"/>
        </fs>
    </a>
    <region xml:id="n-r196" anchors="5792 5908"/>
    <node xml:id="n-n196">
        <link targets="n-r196"/>
    </node>
    <a label="turn" ref="n-n196" as="xces">
        <fs>
            <f name="who" value="B"/>
            <f name="id" value="t90"/>
        </fs>
    </a>
    <region xml:id="n-r197" anchors="5796 5869"/>
    <node xml:id="n-n197">
        <link targets="n-r197"/>
    </node>
    <a label="u" ref="n-n197" as="xces">
        <fs>
            <f name="id" value="sw3101B-0083"/>
            <f name="end" value="284.504375"/>
            <f name="start" value="280.122750"/>
        </fs>
    </a>
    <region xml:id="n-r198" anchors="5873 5905"/>
    <node xml:id="n-n198">
        <link targets="n-r198"/>
    </node>
    <a label="u" ref="n-n198" as="xces">
        <fs>
            <f name="id" value="sw3101B-0085"/>
            <f name="end" value="288.046625"/>
            <f name="start" value="285.900750"/>
        </fs>
    </a>
    <region xml:id="n-r199" anchors="5911 5922"/>
    <node xml:id="n-n199">
        <link targets="n-r199"/>
    </node>
    <a label="turn" ref="n-n199" as="xces">
        <fs>
            <f name="who" value="A"/>
            <f name="id" value="t91"/>
        </fs>
    </a>
    <region xml:id="n-r200" anchors="5915 5919"/>
    <node xml:id="n-n200">
        <link targets="n-r200"/>
    </node>
    <a label="u" ref="n-n200" as="xces">
        <fs>
            <f name="id" value="sw3101A-0073"/>
            <f name="end" value="288.734750"/>
            <f name="start" value="287.420125"/>
        </fs>
    </a>
    <region xml:id="n-r201" anchors="5925 6012"/>
    <node xml:id="n-n201">
        <link targets="n-r201"/>
    </node>
    <a label="turn" ref="n-n201" as="xces">
        <fs>
            <f name="who" value="B"/>
            <f name="id" value="t92"/>
        </fs>
    </a>
    <region xml:id="n-r202" anchors="5929 6009"/>
    <node xml:id="n-n202">
        <link targets="n-r202"/>
    </node>
    <a label="u" ref="n-n202" as="xces">
        <fs>
            <f name="id" value="sw3101B-0086"/>
            <f name="end" value="292.917875"/>
            <f name="start" value="288.046625"/>
        </fs>
    </a>
    <region xml:id="n-r203" anchors="6015 6083"/>
    <node xml:id="n-n203">
        <link targets="n-r203"/>
    </node>
    <a label="turn" ref="n-n203" as="xces">
        <fs>
            <f name="who" value="A"/>
            <f name="id" value="t93"/>
        </fs>
    </a>
    <region xml:id="n-r204" anchors="6019 6053"/>
    <node xml:id="n-n204">
        <link targets="n-r204"/>
    </node>
    <a label="u" ref="n-n204" as="xces">
        <fs>
            <f name="id" value="sw3101A-0074"/>
            <f name="end" value="290.545500"/>
            <f name="start" value="288.734750"/>
        </fs>
    </a>
    <region xml:id="n-r205" anchors="6057 6059"/>
    <node xml:id="n-n205">
        <link targets="n-r205"/>
    </node>
    <a label="u" ref="n-n205" as="xces">
        <fs>
            <f name="id" value="sw3101A-0075"/>
            <f name="end" value="292.553375"/>
            <f name="start" value="290.545500"/>
        </fs>
    </a>
    <region xml:id="n-r206" anchors="6063 6080"/>
    <node xml:id="n-n206">
        <link targets="n-r206"/>
    </node>
    <a label="u" ref="n-n206" as="xces">
        <fs>
            <f name="id" value="sw3101A-0076"/>
            <f name="end" value="294.386375"/>
            <f name="start" value="292.553375"/>
        </fs>
    </a>
    <region xml:id="n-r207" anchors="6086 6115"/>
    <node xml:id="n-n207">
        <link targets="n-r207"/>
    </node>
    <a label="turn" ref="n-n207" as="xces">
        <fs>
            <f name="who" value="B"/>
            <f name="id" value="t94"/>
        </fs>
    </a>
    <region xml:id="n-r208" anchors="6090 6112"/>
    <node xml:id="n-n208">
        <link targets="n-r208"/>
    </node>
    <a label="u" ref="n-n208" as="xces">
        <fs>
            <f name="id" value="sw3101B-0088"/>
            <f name="end" value="296.110000"/>
            <f name="start" value="294.098000"/>
        </fs>
    </a>
    <region xml:id="n-r209" anchors="6118 6162"/>
    <node xml:id="n-n209">
        <link targets="n-r209"/>
    </node>
    <a label="turn" ref="n-n209" as="xces">
        <fs>
            <f name="who" value="A"/>
            <f name="id" value="t95"/>
        </fs>
    </a>
    <region xml:id="n-r210" anchors="6122 6159"/>
    <node xml:id="n-n210">
        <link targets="n-r210"/>
    </node>
    <a label="u" ref="n-n210" as="xces">
        <fs>
            <f name="id" value="sw3101A-0078"/>
            <f name="end" value="298.146875"/>
            <f name="start" value="295.706500"/>
        </fs>
    </a>
    <region xml:id="n-r211" anchors="6165 6201"/>
    <node xml:id="n-n211">
        <link targets="n-r211"/>
    </node>
    <a label="turn" ref="n-n211" as="xces">
        <fs>
            <f name="who" value="B"/>
            <f name="id" value="t96"/>
        </fs>
    </a>
    <region xml:id="n-r212" anchors="6169 6198"/>
    <node xml:id="n-n212">
        <link targets="n-r212"/>
    </node>
    <a label="u" ref="n-n212" as="xces">
        <fs>
            <f name="id" value="sw3101B-0090"/>
            <f name="end" value="299.408000"/>
            <f name="start" value="297.394000"/>
        </fs>
    </a>
    <region xml:id="n-r213" anchors="6204 6215"/>
    <node xml:id="n-n213">
        <link targets="n-r213"/>
    </node>
    <a label="turn" ref="n-n213" as="xces">
        <fs>
            <f name="who" value="A"/>
            <f name="id" value="t97"/>
        </fs>
    </a>
    <region xml:id="n-r214" anchors="6208 6212"/>
    <node xml:id="n-n214">
        <link targets="n-r214"/>
    </node>
    <a label="u" ref="n-n214" as="xces">
        <fs>
            <f name="id" value="sw3101A-0080"/>
            <f name="end" value="301.972500"/>
            <f name="start" value="299.151875"/>
        </fs>
    </a>
    <region xml:id="n-r215" anchors="6218 6255"/>
    <node xml:id="n-n215">
        <link targets="n-r215"/>
    </node>
    <a label="turn" ref="n-n215" as="xces">
        <fs>
            <f name="who" value="B"/>
            <f name="id" value="t98"/>
        </fs>
    </a>
    <region xml:id="n-r216" anchors="6222 6252"/>
    <node xml:id="n-n216">
        <link targets="n-r216"/>
    </node>
    <a label="u" ref="n-n216" as="xces">
        <fs>
            <f name="id" value="sw3101B-0091"/>
            <f name="end" value="302.039750"/>
            <f name="start" value="299.408000"/>
        </fs>
    </a>
    <region xml:id="n-r217" anchors="6258 6283"/>
    <node xml:id="n-n217">
        <link targets="n-r217"/>
    </node>
    <a label="turn" ref="n-n217" as="xces">
        <fs>
            <f name="who" value="A"/>
            <f name="id" value="t99"/>
        </fs>
    </a>
    <region xml:id="n-r218" anchors="6262 6280"/>
    <node xml:id="n-n218">
        <link targets="n-r218"/>
    </node>
    <a label="u" ref="n-n218" as="xces">
        <fs>
            <f name="id" value="sw3101A-0081"/>
            <f name="end" value="304.774000"/>
            <f name="start" value="301.972500"/>
        </fs>
    </a>
    <region xml:id="n-r219" anchors="6286 6336"/>
    <node xml:id="n-n219">
        <link targets="n-r219"/>
    </node>
    <a label="turn" ref="n-n219" as="xces">
        <fs>
            <f name="who" value="B"/>
            <f name="id" value="t100"/>
        </fs>
    </a>
    <region xml:id="n-r220" anchors="6290 6333"/>
    <node xml:id="n-n220">
        <link targets="n-r220"/>
    </node>
    <a label="u" ref="n-n220" as="xces">
        <fs>
            <f name="id" value="sw3101B-0093"/>
            <f name="end" value="307.310000"/>
            <f name="start" value="304.334375"/>
        </fs>
    </a>
    <region xml:id="n-r221" anchors="6339 6360"/>
    <node xml:id="n-n221">
        <link targets="n-r221"/>
    </node>
    <a label="turn" ref="n-n221" as="xces">
        <fs>
            <f name="who" value="A"/>
            <f name="id" value="t101"/>
        </fs>
    </a>
    <region xml:id="n-r222" anchors="6343 6357"/>
    <node xml:id="n-n222">
        <link targets="n-r222"/>
    </node>
    <a label="u" ref="n-n222" as="xces">
        <fs>
            <f name="id" value="sw3101A-0083"/>
            <f name="end" value="308.808125"/>
            <f name="start" value="306.188375"/>
        </fs>
    </a>
    <region xml:id="n-r223" anchors="6363 6398"/>
    <node xml:id="n-n223">
        <link targets="n-r223"/>
    </node>
    <a label="turn" ref="n-n223" as="xces">
        <fs>
            <f name="who" value="B"/>
            <f name="id" value="t102"/>
        </fs>
    </a>
    <region xml:id="n-r224" anchors="6367 6395"/>
    <node xml:id="n-n224">
        <link targets="n-r224"/>
    </node>
    <a label="u" ref="n-n224" as="xces">
        <fs>
            <f name="id" value="sw3101B-0094"/>
            <f name="end" value="309.579375"/>
            <f name="start" value="307.310000"/>
        </fs>
    </a>
    <region xml:id="n-r225" anchors="6401 6554"/>
    <node xml:id="n-n225">
        <link targets="n-r225"/>
    </node>
    <a label="turn" ref="n-n225" as="xces">
        <fs>
            <f name="who" value="A"/>
            <f name="id" value="t103"/>
        </fs>
    </a>
    <region xml:id="n-r226" anchors="6405 6508"/>
    <node xml:id="n-n226">
        <link targets="n-r226"/>
    </node>
    <a label="u" ref="n-n226" as="xces">
        <fs>
            <f name="id" value="sw3101A-0084"/>
            <f name="end" value="315.318125"/>
            <f name="start" value="308.808125"/>
        </fs>
    </a>
    <region xml:id="n-r227" anchors="6512 6551"/>
    <node xml:id="n-n227">
        <link targets="n-r227"/>
    </node>
    <a label="u" ref="n-n227" as="xces">
        <fs>
            <f name="id" value="sw3101A-0085"/>
            <f name="end" value="319.575625"/>
            <f name="start" value="315.318125"/>
        </fs>
    </a>
    <region xml:id="n-r228" anchors="6557 6566"/>
    <node xml:id="n-n228">
        <link targets="n-r228"/>
    </node>
    <a label="turn" ref="n-n228" as="xces">
        <fs>
            <f name="who" value="B"/>
            <f name="id" value="t104"/>
        </fs>
    </a>
    <region xml:id="n-r229" anchors="6561 6563"/>
    <node xml:id="n-n229">
        <link targets="n-r229"/>
    </node>
    <a label="u" ref="n-n229" as="xces">
        <fs>
            <f name="id" value="sw3101B-0096"/>
            <f name="end" value="319.542875"/>
            <f name="start" value="317.214875"/>
        </fs>
    </a>
    <region xml:id="n-r230" anchors="6569 6619"/>
    <node xml:id="n-n230">
        <link targets="n-r230"/>
    </node>
    <a label="turn" ref="n-n230" as="xces">
        <fs>
            <f name="who" value="A"/>
            <f name="id" value="t105"/>
        </fs>
    </a>
    <region xml:id="n-r231" anchors="6573 6616"/>
    <node xml:id="n-n231">
        <link targets="n-r231"/>
    </node>
    <a label="u" ref="n-n231" as="xces">
        <fs>
            <f name="id" value="sw3101A-0086"/>
            <f name="end" value="323.094000"/>
            <f name="start" value="319.575625"/>
        </fs>
    </a>
    <region xml:id="n-r232" anchors="6622 6719"/>
    <node xml:id="n-n232">
        <link targets="n-r232"/>
    </node>
    <a label="turn" ref="n-n232" as="xces">
        <fs>
            <f name="who" value="B"/>
            <f name="id" value="t106"/>
        </fs>
    </a>
    <region xml:id="n-r233" anchors="6626 6716"/>
    <node xml:id="n-n233">
        <link targets="n-r233"/>
    </node>
    <a label="u" ref="n-n233" as="xces">
        <fs>
            <f name="id" value="sw3101B-0098"/>
            <f name="end" value="326.197750"/>
            <f name="start" value="321.021125"/>
        </fs>
    </a>
    <region xml:id="n-r234" anchors="6722 6781"/>
    <node xml:id="n-n234">
        <link targets="n-r234"/>
    </node>
    <a label="turn" ref="n-n234" as="xces">
        <fs>
            <f name="who" value="A"/>
            <f name="id" value="t107"/>
        </fs>
    </a>
    <region xml:id="n-r235" anchors="6726 6730"/>
    <node xml:id="n-n235">
        <link targets="n-r235"/>
    </node>
    <a label="u" ref="n-n235" as="xces">
        <fs>
            <f name="id" value="sw3101A-0087"/>
            <f name="end" value="325.171375"/>
            <f name="start" value="323.094000"/>
        </fs>
    </a>
    <region xml:id="n-r236" anchors="6734 6778"/>
    <node xml:id="n-n236">
        <link targets="n-r236"/>
    </node>
    <a label="u" ref="n-n236" as="xces">
        <fs>
            <f name="id" value="sw3101A-0088"/>
            <f name="end" value="330.412375"/>
            <f name="start" value="325.171375"/>
        </fs>
    </a>
    <region xml:id="n-r237" anchors="6784 6823"/>
    <node xml:id="n-n237">
        <link targets="n-r237"/>
    </node>
    <a label="turn" ref="n-n237" as="xces">
        <fs>
            <f name="who" value="B"/>
            <f name="id" value="t108"/>
        </fs>
    </a>
    <region xml:id="n-r238" anchors="6788 6820"/>
    <node xml:id="n-n238">
        <link targets="n-r238"/>
    </node>
    <a label="u" ref="n-n238" as="xces">
        <fs>
            <f name="id" value="sw3101B-0100"/>
            <f name="end" value="331.643500"/>
            <f name="start" value="328.308000"/>
        </fs>
    </a>
    <region xml:id="n-r239" anchors="6826 7125"/>
    <node xml:id="n-n239">
        <link targets="n-r239"/>
    </node>
    <a label="turn" ref="n-n239" as="xces">
        <fs>
            <f name="who" value="A"/>
            <f name="id" value="t109"/>
        </fs>
    </a>
    <region xml:id="n-r240" anchors="6830 6836"/>
    <node xml:id="n-n240">
        <link targets="n-r240"/>
    </node>
    <a label="u" ref="n-n240" as="xces">
        <fs>
            <f name="id" value="sw3101A-0089"/>
            <f name="end" value="331.861625"/>
            <f name="start" value="330.412375"/>
        </fs>
    </a>
    <region xml:id="n-r241" anchors="6840 6992"/>
    <node xml:id="n-n241">
        <link targets="n-r241"/>
    </node>
    <a label="u" ref="n-n241" as="xces">
        <fs>
            <f name="id" value="sw3101A-0090"/>
            <f name="end" value="340.134375"/>
            <f name="start" value="331.861625"/>
        </fs>
    </a>
    <region xml:id="n-r242" anchors="6996 7122"/>
    <node xml:id="n-n242">
        <link targets="n-r242"/>
    </node>
    <a label="u" ref="n-n242" as="xces">
        <fs>
            <f name="id" value="sw3101A-0091"/>
            <f name="end" value="347.091125"/>
            <f name="start" value="340.134375"/>
        </fs>
    </a>
    <region xml:id="n-r243" anchors="7128 7204"/>
    <node xml:id="n-n243">
        <link targets="n-r243"/>
    </node>
    <a label="turn" ref="n-n243" as="xces">
        <fs>
            <f name="who" value="B"/>
            <f name="id" value="t110"/>
        </fs>
    </a>
    <region xml:id="n-r244" anchors="7132 7201"/>
    <node xml:id="n-n244">
        <link targets="n-r244"/>
    </node>
    <a label="u" ref="n-n244" as="xces">
        <fs>
            <f name="id" value="sw3101B-0102"/>
            <f name="end" value="349.801500"/>
            <f name="start" value="346.527500"/>
        </fs>
    </a>
    <region xml:id="n-r245" anchors="7207 7367"/>
    <node xml:id="n-n245">
        <link targets="n-r245"/>
    </node>
    <a label="turn" ref="n-n245" as="xces">
        <fs>
            <f name="who" value="A"/>
            <f name="id" value="t111"/>
        </fs>
    </a>
    <region xml:id="n-r246" anchors="7211 7364"/>
    <node xml:id="n-n246">
        <link targets="n-r246"/>
    </node>
    <a label="u" ref="n-n246" as="xces">
        <fs>
            <f name="id" value="sw3101A-0093"/>
            <f name="end" value="358.367500"/>
            <f name="start" value="349.384125"/>
        </fs>
    </a>
    <region xml:id="n-r247" anchors="7370 7404"/>
    <node xml:id="n-n247">
        <link targets="n-r247"/>
    </node>
    <a label="turn" ref="n-n247" as="xces">
        <fs>
            <f name="who" value="B"/>
            <f name="id" value="t112"/>
        </fs>
    </a>
    <region xml:id="n-r248" anchors="7374 7378"/>
    <node xml:id="n-n248">
        <link targets="n-r248"/>
    </node>
    <a label="u" ref="n-n248" as="xces">
        <fs>
            <f name="id" value="sw3101B-0104"/>
            <f name="end" value="351.992000"/>
            <f name="start" value="350.884500"/>
        </fs>
    </a>
    <region xml:id="n-r249" anchors="7382 7386"/>
    <node xml:id="n-n249">
        <link targets="n-r249"/>
    </node>
    <a label="u" ref="n-n249" as="xces">
        <fs>
            <f name="id" value="sw3101B-0106"/>
            <f name="end" value="355.537125"/>
            <f name="start" value="354.377250"/>
        </fs>
    </a>
    <region xml:id="n-r250" anchors="7390 7401"/>
    <node xml:id="n-n250">
        <link targets="n-r250"/>
    </node>
    <a label="u" ref="n-n250" as="xces">
        <fs>
            <f name="id" value="sw3101B-0108"/>
            <f name="end" value="358.575500"/>
            <f name="start" value="357.360000"/>
        </fs>
    </a>
    <region xml:id="n-r251" anchors="7407 7449"/>
    <node xml:id="n-n251">
        <link targets="n-r251"/>
    </node>
    <a label="turn" ref="n-n251" as="xces">
        <fs>
            <f name="who" value="A"/>
            <f name="id" value="t113"/>
        </fs>
    </a>
    <region xml:id="n-r252" anchors="7411 7446"/>
    <node xml:id="n-n252">
        <link targets="n-r252"/>
    </node>
    <a label="u" ref="n-n252" as="xces">
        <fs>
            <f name="id" value="sw3101A-0094"/>
            <f name="end" value="360.812375"/>
            <f name="start" value="358.367500"/>
        </fs>
    </a>
    <region xml:id="n-r253" anchors="7452 7512"/>
    <node xml:id="n-n253">
        <link targets="n-r253"/>
    </node>
    <a label="turn" ref="n-n253" as="xces">
        <fs>
            <f name="who" value="B"/>
            <f name="id" value="t114"/>
        </fs>
    </a>
    <region xml:id="n-r254" anchors="7456 7509"/>
    <node xml:id="n-n254">
        <link targets="n-r254"/>
    </node>
    <a label="u" ref="n-n254" as="xces">
        <fs>
            <f name="id" value="sw3101B-0110"/>
            <f name="end" value="363.867500"/>
            <f name="start" value="360.441875"/>
        </fs>
    </a>
    <region xml:id="n-r255" anchors="7515 7564"/>
    <node xml:id="n-n255">
        <link targets="n-r255"/>
    </node>
    <a label="turn" ref="n-n255" as="xces">
        <fs>
            <f name="who" value="A"/>
            <f name="id" value="t115"/>
        </fs>
    </a>
    <region xml:id="n-r256" anchors="7519 7561"/>
    <node xml:id="n-n256">
        <link targets="n-r256"/>
    </node>
    <a label="u" ref="n-n256" as="xces">
        <fs>
            <f name="id" value="sw3101A-0096"/>
            <f name="end" value="368.737625"/>
            <f name="start" value="362.607500"/>
        </fs>
    </a>
    <region xml:id="n-r257" anchors="7567 7585"/>
    <node xml:id="n-n257">
        <link targets="n-r257"/>
    </node>
    <a label="turn" ref="n-n257" as="xces">
        <fs>
            <f name="who" value="B"/>
            <f name="id" value="t116"/>
        </fs>
    </a>
    <region xml:id="n-r258" anchors="7571 7573"/>
    <node xml:id="n-n258">
        <link targets="n-r258"/>
    </node>
    <a label="u" ref="n-n258" as="xces">
        <fs>
            <f name="id" value="sw3101B-0111"/>
            <f name="end" value="364.669750"/>
            <f name="start" value="363.867500"/>
        </fs>
    </a>
    <region xml:id="n-r259" anchors="7577 7582"/>
    <node xml:id="n-n259">
        <link targets="n-r259"/>
    </node>
    <a label="u" ref="n-n259" as="xces">
        <fs>
            <f name="id" value="sw3101B-0113"/>
            <f name="end" value="367.778500"/>
            <f name="start" value="365.848625"/>
        </fs>
    </a>
    <region xml:id="n-r260" anchors="7588 7650"/>
    <node xml:id="n-n260">
        <link targets="n-r260"/>
    </node>
    <a label="turn" ref="n-n260" as="xces">
        <fs>
            <f name="who" value="A"/>
            <f name="id" value="t117"/>
        </fs>
    </a>
    <region xml:id="n-r261" anchors="7592 7647"/>
    <node xml:id="n-n261">
        <link targets="n-r261"/>
    </node>
    <a label="u" ref="n-n261" as="xces">
        <fs>
            <f name="id" value="sw3101A-0097"/>
            <f name="end" value="373.012125"/>
            <f name="start" value="368.737625"/>
        </fs>
    </a>
    <region xml:id="n-r262" anchors="7653 7704"/>
    <node xml:id="n-n262">
        <link targets="n-r262"/>
    </node>
    <a label="turn" ref="n-n262" as="xces">
        <fs>
            <f name="who" value="B"/>
            <f name="id" value="t118"/>
        </fs>
    </a>
    <region xml:id="n-r263" anchors="7657 7701"/>
    <node xml:id="n-n263">
        <link targets="n-r263"/>
    </node>
    <a label="u" ref="n-n263" as="xces">
        <fs>
            <f name="id" value="sw3101B-0115"/>
            <f name="end" value="375.026750"/>
            <f name="start" value="371.604125"/>
        </fs>
    </a>
    <region xml:id="n-r264" anchors="7707 7784"/>
    <node xml:id="n-n264">
        <link targets="n-r264"/>
    </node>
    <a label="turn" ref="n-n264" as="xces">
        <fs>
            <f name="who" value="A"/>
            <f name="id" value="t119"/>
        </fs>
    </a>
    <region xml:id="n-r265" anchors="7711 7781"/>
    <node xml:id="n-n265">
        <link targets="n-r265"/>
    </node>
    <a label="u" ref="n-n265" as="xces">
        <fs>
            <f name="id" value="sw3101A-0099"/>
            <f name="end" value="379.136375"/>
            <f name="start" value="374.429625"/>
        </fs>
    </a>
    <region xml:id="n-r266" anchors="7787 7822"/>
    <node xml:id="n-n266">
        <link targets="n-r266"/>
    </node>
    <a label="turn" ref="n-n266" as="xces">
        <fs>
            <f name="who" value="B"/>
            <f name="id" value="t120"/>
        </fs>
    </a>
    <region xml:id="n-r267" anchors="7791 7793"/>
    <node xml:id="n-n267">
        <link targets="n-r267"/>
    </node>
    <a label="u" ref="n-n267" as="xces">
        <fs>
            <f name="id" value="sw3101B-0116"/>
            <f name="end" value="375.891750"/>
            <f name="start" value="375.026750"/>
        </fs>
    </a>
    <region xml:id="n-r268" anchors="7797 7819"/>
    <node xml:id="n-n268">
        <link targets="n-r268"/>
    </node>
    <a label="u" ref="n-n268" as="xces">
        <fs>
            <f name="id" value="sw3101B-0118"/>
            <f name="end" value="380.260500"/>
            <f name="start" value="377.700375"/>
        </fs>
    </a>
    <region xml:id="n-r269" anchors="7825 8031"/>
    <node xml:id="n-n269">
        <link targets="n-r269"/>
    </node>
    <a label="turn" ref="n-n269" as="xces">
        <fs>
            <f name="who" value="A"/>
            <f name="id" value="t121"/>
        </fs>
    </a>
    <region xml:id="n-r270" anchors="7829 8028"/>
    <node xml:id="n-n270">
        <link targets="n-r270"/>
    </node>
    <a label="u" ref="n-n270" as="xces">
        <fs>
            <f name="id" value="sw3101A-0100"/>
            <f name="end" value="387.480000"/>
            <f name="start" value="379.136375"/>
        </fs>
    </a>
    <region xml:id="n-r271" anchors="8034 8059"/>
    <node xml:id="n-n271">
        <link targets="n-r271"/>
    </node>
    <a label="turn" ref="n-n271" as="xces">
        <fs>
            <f name="who" value="B"/>
            <f name="id" value="t122"/>
        </fs>
    </a>
    <region xml:id="n-r272" anchors="8038 8040"/>
    <node xml:id="n-n272">
        <link targets="n-r272"/>
    </node>
    <a label="u" ref="n-n272" as="xces">
        <fs>
            <f name="id" value="sw3101B-0120"/>
            <f name="end" value="384.691250"/>
            <f name="start" value="383.866375"/>
        </fs>
    </a>
    <region xml:id="n-r273" anchors="8044 8056"/>
    <node xml:id="n-n273">
        <link targets="n-r273"/>
    </node>
    <a label="u" ref="n-n273" as="xces">
        <fs>
            <f name="id" value="sw3101B-0122"/>
            <f name="end" value="387.923125"/>
            <f name="start" value="386.793750"/>
        </fs>
    </a>
    <region xml:id="n-r274" anchors="8062 8179"/>
    <node xml:id="n-n274">
        <link targets="n-r274"/>
    </node>
    <a label="turn" ref="n-n274" as="xces">
        <fs>
            <f name="who" value="A"/>
            <f name="id" value="t123"/>
        </fs>
    </a>
    <region xml:id="n-r275" anchors="8066 8176"/>
    <node xml:id="n-n275">
        <link targets="n-r275"/>
    </node>
    <a label="u" ref="n-n275" as="xces">
        <fs>
            <f name="id" value="sw3101A-0101"/>
            <f name="end" value="395.154750"/>
            <f name="start" value="387.480000"/>
        </fs>
    </a>
    <region xml:id="n-r276" anchors="8182 8212"/>
    <node xml:id="n-n276">
        <link targets="n-r276"/>
    </node>
    <a label="turn" ref="n-n276" as="xces">
        <fs>
            <f name="who" value="B"/>
            <f name="id" value="t124"/>
        </fs>
    </a>
    <region xml:id="n-r277" anchors="8186 8209"/>
    <node xml:id="n-n277">
        <link targets="n-r277"/>
    </node>
    <a label="u" ref="n-n277" as="xces">
        <fs>
            <f name="id" value="sw3101B-0124"/>
            <f name="end" value="395.604875"/>
            <f name="start" value="393.757875"/>
        </fs>
    </a>
    <region xml:id="n-r278" anchors="8215 8323"/>
    <node xml:id="n-n278">
        <link targets="n-r278"/>
    </node>
    <a label="turn" ref="n-n278" as="xces">
        <fs>
            <f name="who" value="A"/>
            <f name="id" value="t125"/>
        </fs>
    </a>
    <region xml:id="n-r279" anchors="8219 8228"/>
    <node xml:id="n-n279">
        <link targets="n-r279"/>
    </node>
    <a label="u" ref="n-n279" as="xces">
        <fs>
            <f name="id" value="sw3101A-0102"/>
            <f name="end" value="396.655625"/>
            <f name="start" value="395.154750"/>
        </fs>
    </a>
    <region xml:id="n-r280" anchors="8232 8320"/>
    <node xml:id="n-n280">
        <link targets="n-r280"/>
    </node>
    <a label="u" ref="n-n280" as="xces">
        <fs>
            <f name="id" value="sw3101A-0103"/>
            <f name="end" value="404.410125"/>
            <f name="start" value="396.655625"/>
        </fs>
    </a>
    <region xml:id="n-r281" anchors="8326 8373"/>
    <node xml:id="n-n281">
        <link targets="n-r281"/>
    </node>
    <a label="turn" ref="n-n281" as="xces">
        <fs>
            <f name="who" value="B"/>
            <f name="id" value="t126"/>
        </fs>
    </a>
    <region xml:id="n-r282" anchors="8330 8336"/>
    <node xml:id="n-n282">
        <link targets="n-r282"/>
    </node>
    <a label="u" ref="n-n282" as="xces">
        <fs>
            <f name="id" value="sw3101B-0126"/>
            <f name="end" value="400.274625"/>
            <f name="start" value="398.528125"/>
        </fs>
    </a>
    <region xml:id="n-r283" anchors="8340 8359"/>
    <node xml:id="n-n283">
        <link targets="n-r283"/>
    </node>
    <a label="u" ref="n-n283" as="xces">
        <fs>
            <f name="id" value="sw3101B-0128"/>
            <f name="end" value="403.581750"/>
            <f name="start" value="401.877000"/>
        </fs>
    </a>
    <region xml:id="n-r284" anchors="8363 8370"/>
    <node xml:id="n-n284">
        <link targets="n-r284"/>
    </node>
    <a label="u" ref="n-n284" as="xces">
        <fs>
            <f name="id" value="sw3101B-0129"/>
            <f name="end" value="404.604500"/>
            <f name="start" value="403.581750"/>
        </fs>
    </a>
    <region xml:id="n-r285" anchors="8376 8385"/>
    <node xml:id="n-n285">
        <link targets="n-r285"/>
    </node>
    <a label="turn" ref="n-n285" as="xces">
        <fs>
            <f name="who" value="A"/>
            <f name="id" value="t127"/>
        </fs>
    </a>
    <region xml:id="n-r286" anchors="8380 8382"/>
    <node xml:id="n-n286">
        <link targets="n-r286"/>
    </node>
    <a label="u" ref="n-n286" as="xces">
        <fs>
            <f name="id" value="sw3101A-0104"/>
            <f name="end" value="406.190875"/>
            <f name="start" value="404.410125"/>
        </fs>
    </a>
    <region xml:id="n-r287" anchors="8388 8398"/>
    <node xml:id="n-n287">
        <link targets="n-r287"/>
    </node>
    <a label="turn" ref="n-n287" as="xces">
        <fs>
            <f name="who" value="B"/>
            <f name="id" value="t128"/>
        </fs>
    </a>
    <region xml:id="n-r288" anchors="8392 8394"/>
    <node xml:id="n-n288">
        <link targets="n-r288"/>
    </node>
    <a label="u" ref="n-n288" as="xces">
        <fs>
            <f name="id" value="sw3101B-0130"/>
            <f name="end" value="406.190875"/>
            <f name="start" value="404.604500"/>
        </fs>
    </a>
</graph>
