{
  "title": {},
  "utterances": [
    {
      "words": [
        {
          "tags": {
            "Penn": "WP"
          },
          "transcription": "what"
        },
        {
          "tags": {
            "Penn": "NN"
          },
          "transcription": "experience"
        },
        {
          "tags": {
            "Penn": "VBP"
          },
          "transcription": "have"
        },
        {
          "tags": {
            "Penn": "PRP"
          },
          "transcription": "you"
        },
        {
          "tags": {
            "Penn": "VBD"
          },
          "transcription": "had"
        },
        {
          "tags": {
            "Penn": "IN"
          },
          "transcription": "with"
        },
        {
          "tags": {
            "Penn": "NN"
          },
          "transcription": "family"
        },
        {
          "tags": {
            "Penn": "NNS"
          },
          "transcription": "reunions"
        }
      ]
    },
    {
      "words": [
        {
          "tags": {
            "Penn": "RB"
          },
          "transcription": "well"
        },
        {
          "tags": {
            "Penn": "RB"
          },
          "transcription": "actually"
        },
        {
          "tags": {
            "Penn": "UH"
          },
          "transcription": "uh"
        },
        {
          "tags": {
            "Penn": "UH"
          },
          "transcription": "oh"
        },
        {
          "tags": {
            "Penn": "DT"
          },
          "transcription": "the"
        },
        {
          "tags": {
            "Penn": "JJ"
          },
          "transcription": "last"
        },
        {
          "tags": {
            "Penn": "CD"
          },
          "transcription": "eight"
        },
        {
          "tags": {
            "Penn": "CC"
          },
          "transcription": "or"
        },
        {
          "tags": {
            "Penn": "CD"
          },
          "transcription": "ten"
        },
        {
          "tags": {
            "Penn": "NNS"
          },
          "transcription": "years"
        },
        {
          "tags": {
            "Penn": "NNP"
          },
          "transcription": "i"
        },
        {
          "tags": {
            "Penn": "VBP"
          },
          "transcription": "have"
        }
      ]
    },
    {
      "words": [
        {
          "tags": {
            "Penn": "DT"
          },
          "transcription": "an"
        },
        {
          "tags": {
            "Penn": "NN"
          },
          "transcription": "aunt"
        },
        {
          "tags": {
            "Penn": "CC"
          },
          "transcription": "and"
        },
        {
          "tags": {
            "Penn": "NNP"
          },
          "transcription": "i"
        },
        {
          "tags": {
            "Penn": "NNP"
          },
          "transcription": "i"
        },
        {
          "tags": {
            "Penn": "MD"
          },
          "transcription": "should"
        },
        {
          "tags": {
            "Penn": "VB"
          },
          "transcription": "say"
        },
        {
          "tags": {
            "Penn": "VB"
          },
          "transcription": "have"
        },
        {
          "tags": {
            "Penn": "IN"
          },
          "transcription": "like"
        },
        {
          "tags": {
            "Penn": "VBN"
          },
          "transcription": "done"
        },
        {
          "tags": {
            "Penn": "PRP$"
          },
          "transcription": "our"
        },
        {
          "tags": {
            "Penn": "NN"
          },
          "transcription": "family"
        },
        {
          "tags": {
            "Penn": "NN"
          },
          "transcription": "reunion"
        }
      ]
    },
    {
      "words": [
        {
          "tags": {
            "Penn": "CC"
          },
          "transcription": "and"
        },
        {
          "tags": {
            "Penn": "UH"
          },
          "transcription": "uh"
        },
        {
          "tags": {
            "Penn": "UH"
          },
          "transcription": "oh"
        },
        {
          "tags": {
            "Penn": "PRP"
          },
          "transcription": "you"
        },
        {
          "tags": {
            "Penn": "VBP"
          },
          "transcription": "know"
        },
        {
          "tags": {
            "Penn": "PRP"
          },
          "transcription": "we"
        },
        {
          "tags": {
            "Penn": "VB"
          },
          "transcription": "send"
        },
        {
          "tags": {
            "Penn": "RP"
          },
          "transcription": "out"
        },
        {
          "tags": {
            "Penn": "NNS"
          },
          "transcription": "letters"
        },
        {
          "tags": {
            "Penn": "TO"
          },
          "transcription": "to"
        },
        {
          "tags": {
            "Penn": "NN"
          },
          "transcription": "everybody"
        },
        {
          "tags": {
            "Penn": "CC"
          },
          "transcription": "and"
        },
        {
          "tags": {
            "Penn": "PRP"
          },
          "transcription": "we"
        },
        {
          "tags": {
            "Penn": "NN"
          },
          "transcription": "rent"
        },
        {
          "tags": {
            "Penn": "DT"
          },
          "transcription": "a"
        },
        {
          "tags": {
            "Penn": "NN"
          },
          "transcription": "place"
        },
        {
          "tags": {
            "Penn": "IN"
          },
          "transcription": "in"
        },
        {
          "tags": {
            "Penn": "DT"
          },
          "transcription": "this"
        },
        {
          "tags": {
            "Penn": "UH"
          },
          "transcription": "uh"
        },
        {
          "tags": {
            "Penn": "NNS"
          },
          "transcription": "savings"
        },
        {
          "tags": {
            "Penn": "CC"
          },
          "transcription": "and"
        },
        {
          "tags": {
            "Penn": "NN"
          },
          "transcription": "loan"
        },
        {
          "tags": {
            "Penn": "IN"
          },
          "transcription": "in"
        },
        {
          "tags": {
            "Penn": "DT"
          },
          "transcription": "a"
        },
        {
          "tags": {
            "Penn": "IN"
          },
          "transcription": "in"
        },
        {
          "tags": {
            "Penn": "DT"
          },
          "transcription": "a"
        },
        {
          "tags": {
            "Penn": "JJ"
          },
          "transcription": "little"
        },
        {
          "tags": {
            "Penn": "NN"
          },
          "transcription": "town"
        }
      ]
    },
    {
      "words": [
        {
          "tags": {
            "Penn": "JJ"
          },
          "transcription": "uh-huh"
        }
      ]
    },
    {
      "words": [
        {
          "tags": {
            "Penn": "CC"
          },
          "transcription": "and"
        },
        {
          "tags": {
            "Penn": "UH"
          },
          "transcription": "uh"
        },
        {
          "tags": {
            "Penn": "RB"
          },
          "transcription": "then"
        },
        {
          "tags": {
            "Penn": "NN"
          },
          "transcription": "everybody"
        },
        {
          "tags": {
            "Penn": "VBZ"
          },
          "transcription": "brings"
        },
        {
          "tags": {
            "Penn": "DT"
          },
          "transcription": "a"
        },
        {
          "tags": {
            "Penn": "VBN"
          },
          "transcription": "covered"
        },
        {
          "tags": {
            "Penn": "NN"
          },
          "transcription": "dish"
        },
        {
          "tags": {
            "Penn": "CC"
          },
          "transcription": "and"
        },
        {
          "tags": {
            "Penn": "DT"
          },
          "transcription": "that"
        },
        {
          "tags": {
            "Penn": "NN"
          },
          "transcription": "sort"
        },
        {
          "tags": {
            "Penn": "IN"
          },
          "transcription": "of"
        },
        {
          "tags": {
            "Penn": "NN"
          },
          "transcription": "thing"
        },
        {
          "tags": {
            "Penn": "CC"
          },
          "transcription": "and"
        },
        {
          "tags": {
            "Penn": "UH"
          },
          "transcription": "uh"
        }
      ]
    },
    {
      "words": [
        {
          "tags": {
            "Penn": "PRP"
          },
          "transcription": "it"
        },
        {
          "tags": {
            "Penn": "VBZ"
          },
          "transcription": "'s"
        },
        {
          "tags": {
            "Penn": "JJ"
          },
          "transcription": "real"
        },
        {
          "tags": {
            "Penn": "JJ"
          },
          "transcription": "nice"
        },
        {
          "tags": {
            "Penn": "IN"
          },
          "transcription": "because"
        },
        {
          "tags": {
            "Penn": "PRP$"
          },
          "transcription": "my"
        },
        {
          "tags": {
            "Penn": "NN"
          },
          "transcription": "mother"
        },
        {
          "tags": {
            "Penn": "UH"
          },
          "transcription": "uh"
        }
      ]
    },
    {
      "words": [
        {
          "tags": {
            "Penn": "VBD"
          },
          "transcription": "had"
        },
        {
          "tags": {
            "Penn": "CD"
          },
          "transcription": "seven"
        },
        {
          "tags": {
            "Penn": "NNS"
          },
          "transcription": "brothers"
        },
        {
          "tags": {
            "Penn": "CC"
          },
          "transcription": "and"
        },
        {
          "tags": {
            "Penn": "NNS"
          },
          "transcription": "sisters"
        },
        {
          "tags": {
            "Penn": "CC"
          },
          "transcription": "and"
        },
        {
          "tags": {
            "Penn": "IN"
          },
          "transcription": "if"
        },
        {
          "tags": {
            "Penn": "PRP"
          },
          "transcription": "we"
        },
        {
          "tags": {
            "Penn": "VBD"
          },
          "transcription": "did"
        },
        {
          "tags": {
            "Penn": "RB"
          },
          "transcription": "n't"
        },
        {
          "tags": {
            "Penn": "VB"
          },
          "transcription": "do"
        },
        {
          "tags": {
            "Penn": "DT"
          },
          "transcription": "this"
        },
        {
          "tags": {
            "Penn": "IN"
          },
          "transcription": "like"
        },
        {
          "tags": {
            "Penn": "DT"
          },
          "transcription": "the"
        },
        {
          "tags": {
            "Penn": "NNS"
          },
          "transcription": "cousins"
        },
        {
          "tags": {
            "Penn": "MD"
          },
          "transcription": "would"
        },
        {
          "tags": {
            "Penn": "RB"
          },
          "transcription": "never"
        },
        {
          "tags": {
            "Penn": "VB"
          },
          "transcription": "see"
        },
        {
          "tags": {
            "Penn": "DT"
          },
          "transcription": "each"
        },
        {
          "tags": {
            "Penn": "JJ"
          },
          "transcription": "other"
        },
        {
          "tags": {
            "Penn": "DT"
          },
          "transcription": "the"
        },
        {
          "tags": {
            "Penn": "NNS"
          },
          "transcription": "aunts"
        },
        {
          "tags": {
            "Penn": "CC"
          },
          "transcription": "and"
        },
        {
          "tags": {
            "Penn": "NNS"
          },
          "transcription": "uncles"
        },
        {
          "tags": {
            "Penn": "DT"
          },
          "transcription": "that"
        },
        {
          "tags": {
            "Penn": "VBZ"
          },
          "transcription": "'s"
        },
        {
          "tags": {
            "Penn": "DT"
          },
          "transcription": "the"
        },
        {
          "tags": {
            "Penn": "NN"
          },
          "transcription": "type"
        },
        {
          "tags": {
            "Penn": "NN"
          },
          "transcription": "family"
        },
        {
          "tags": {
            "Penn": "NN"
          },
          "transcription": "reunion"
        },
        {
          "tags": {
            "Penn": "PRP"
          },
          "transcription": "we"
        },
        {
          "tags": {
            "Penn": "VBP"
          },
          "transcription": "'ve"
        },
        {
          "tags": {
            "Penn": "VBN"
          },
          "transcription": "had"
        },
        {
          "tags": {
            "Penn": "EX"
          },
          "transcription": "there"
        },
        {
          "tags": {
            "Penn": "PRP"
          },
          "transcription": "you"
        },
        {
          "tags": {
            "Penn": "VBP"
          },
          "transcription": "know"
        }
      ]
    },
    {
      "words": [
        {
          "tags": {
            "Penn": "RB"
          },
          "transcription": "so"
        },
        {
          "tags": {
            "Penn": "UH"
          },
          "transcription": "uh"
        }
      ]
    },
    {
      "words": [
        {
          "tags": {
            "Penn": "PRP"
          },
          "transcription": "you"
        },
        {
          "tags": {
            "Penn": "VBP"
          },
          "transcription": "know"
        },
        {
          "tags": {
            "Penn": "IN"
          },
          "transcription": "if"
        },
        {
          "tags": {
            "Penn": "PRP"
          },
          "transcription": "we"
        },
        {
          "tags": {
            "Penn": "VBD"
          },
          "transcription": "found"
        },
        {
          "tags": {
            "Penn": "PRP"
          },
          "transcription": "you"
        },
        {
          "tags": {
            "Penn": "VBP"
          },
          "transcription": "know"
        },
        {
          "tags": {
            "Penn": "DT"
          },
          "transcription": "the"
        },
        {
          "tags": {
            "Penn": "NNS"
          },
          "transcription": "years"
        },
        {
          "tags": {
            "Penn": "PRP"
          },
          "transcription": "we"
        },
        {
          "tags": {
            "Penn": "VBP"
          },
          "transcription": "do"
        },
        {
          "tags": {
            "Penn": "RB"
          },
          "transcription": "n't"
        },
        {
          "tags": {
            "Penn": "VB"
          },
          "transcription": "do"
        },
        {
          "tags": {
            "Penn": "DT"
          },
          "transcription": "that"
        },
        {
          "tags": {
            "Penn": "NN"
          },
          "transcription": "nobody"
        },
        {
          "tags": {
            "Penn": "NN"
          },
          "transcription": "nobody"
        },
        {
          "tags": {
            "Penn": "VBZ"
          },
          "transcription": "sees"
        },
        {
          "tags": {
            "Penn": "DT"
          },
          "transcription": "each"
        },
        {
          "tags": {
            "Penn": "JJ"
          },
          "transcription": "other"
        },
        {
          "tags": {
            "Penn": "IN"
          },
          "transcription": "because"
        },
        {
          "tags": {
            "Penn": "NN"
          },
          "transcription": "everybody"
        },
        {
          "tags": {
            "Penn": "NNS"
          },
          "transcription": "lives"
        },
        {
          "tags": {
            "Penn": "IN"
          },
          "transcription": "in"
        },
        {
          "tags": {
            "Penn": "JJ"
          },
          "transcription": "different"
        },
        {
          "tags": {
            "Penn": "NNS"
          },
          "transcription": "places"
        },
        {
          "tags": {
            "Penn": "PRP"
          },
          "transcription": "you"
        },
        {
          "tags": {
            "Penn": "VBP"
          },
          "transcription": "know"
        }
      ]
    },
    {
      "words": [
        {
          "tags": {
            "Penn": "NN"
          },
          "transcription": "huh"
        },
        {
          "tags": {
            "Penn": "WDT"
          },
          "transcription": "that"
        },
        {
          "tags": {
            "Penn": "VBZ"
          },
          "transcription": "'s"
        },
        {
          "tags": {
            "Penn": "RB"
          },
          "transcription": "really"
        },
        {
          "tags": {
            "Penn": "JJ"
          },
          "transcription": "good"
        }
      ]
    },
    {
      "words": [
        {
          "tags": {
            "Penn": "NN"
          },
          "transcription": "yeah"
        },
        {
          "tags": {
            "Penn": "PRP$"
          },
          "transcription": "my"
        },
        {
          "tags": {
            "Penn": "NN"
          },
          "transcription": "mom"
        },
        {
          "tags": {
            "Penn": "PRP$"
          },
          "transcription": "my"
        },
        {
          "tags": {
            "Penn": "NN"
          },
          "transcription": "mom"
        },
        {
          "tags": {
            "Penn": "POS"
          },
          "transcription": "'s"
        },
        {
          "tags": {
            "Penn": "NN"
          },
          "transcription": "family"
        },
        {
          "tags": {
            "Penn": "VBZ"
          },
          "transcription": "is"
        },
        {
          "tags": {
            "Penn": "DT"
          },
          "transcription": "all"
        }
      ]
    },
    {
      "words": [
        {
          "tags": {
            "Penn": "PRP$"
          },
          "transcription": "my"
        },
        {
          "tags": {
            "Penn": "NN"
          },
          "transcription": "family"
        },
        {
          "tags": {
            "Penn": "VBZ"
          },
          "transcription": "is"
        },
        {
          "tags": {
            "Penn": "RB"
          },
          "transcription": "really"
        },
        {
          "tags": {
            "Penn": "VBN"
          },
          "transcription": "scattered"
        },
        {
          "tags": {
            "Penn": "IN"
          },
          "transcription": "out"
        },
        {
          "tags": {
            "Penn": "RB"
          },
          "transcription": "so"
        },
        {
          "tags": {
            "Penn": "IN"
          },
          "transcription": "if"
        },
        {
          "tags": {
            "Penn": "PRP"
          },
          "transcription": "we"
        },
        {
          "tags": {
            "Penn": "VBD"
          },
          "transcription": "did"
        },
        {
          "tags": {
            "Penn": "RB"
          },
          "transcription": "n't"
        },
        {
          "tags": {
            "Penn": "VB"
          },
          "transcription": "have"
        },
        {
          "tags": {
            "Penn": "NN"
          },
          "transcription": "family"
        },
        {
          "tags": {
            "Penn": "NNS"
          },
          "transcription": "reunions"
        },
        {
          "tags": {
            "Penn": "PRP"
          },
          "transcription": "we"
        },
        {
          "tags": {
            "Penn": "RB"
          },
          "transcription": "simply"
        },
        {
          "tags": {
            "Penn": "MD"
          },
          "transcription": "would"
        },
        {
          "tags": {
            "Penn": "RB"
          },
          "transcription": "never"
        },
        {
          "tags": {
            "Penn": "VB"
          },
          "transcription": "see"
        },
        {
          "tags": {
            "Penn": "DT"
          },
          "transcription": "each"
        },
        {
          "tags": {
            "Penn": "JJ"
          },
          "transcription": "other"
        },
        {
          "tags": {
            "Penn": "IN"
          },
          "transcription": "for"
        },
        {
          "tags": {
            "Penn": "NN"
          },
          "transcription": "example"
        },
        {
          "tags": {
            "Penn": "NN"
          },
          "transcription": "um"
        }
      ]
    },
    {
      "words": [
        {
          "tags": {
            "Penn": "PRP$"
          },
          "transcription": "my"
        }
      ]
    },
    {
      "words": [
        {
          "tags": {
            "Penn": "PRP$"
          },
          "transcription": "my"
        },
        {
          "tags": {
            "Penn": "NNS"
          },
          "transcription": "parents"
        },
        {
          "tags": {
            "Penn": "VBP"
          },
          "transcription": "live"
        },
        {
          "tags": {
            "Penn": "IN"
          },
          "transcription": "in"
        },
        {
          "tags": {
            "Penn": "NNP"
          },
          "transcription": "Seattle"
        },
        {
          "tags": {
            "Penn": "NNP"
          },
          "transcription": "Washington"
        }
      ]
    },
    {
      "words": [
        {
          "tags": {
            "Penn": "UH"
          },
          "transcription": "oh"
        }
      ]
    },
    {
      "words": [
        {
          "tags": {
            "Penn": "RB"
          },
          "transcription": "however"
        },
        {
          "tags": {
            "Penn": "DT"
          },
          "transcription": "all"
        },
        {
          "tags": {
            "Penn": "IN"
          },
          "transcription": "of"
        },
        {
          "tags": {
            "Penn": "PRP$"
          },
          "transcription": "my"
        },
        {
          "tags": {
            "Penn": "NN"
          },
          "transcription": "mom"
        },
        {
          "tags": {
            "Penn": "POS"
          },
          "transcription": "'s"
        },
        {
          "tags": {
            "Penn": "CC"
          },
          "transcription": "and"
        },
        {
          "tags": {
            "Penn": "NNS"
          },
          "transcription": "relatives"
        },
        {
          "tags": {
            "Penn": "CC"
          },
          "transcription": "and"
        },
        {
          "tags": {
            "Penn": "NN"
          },
          "transcription": "family"
        },
        {
          "tags": {
            "Penn": "VBP"
          },
          "transcription": "are"
        },
        {
          "tags": {
            "Penn": "IN"
          },
          "transcription": "from"
        },
        {
          "tags": {
            "Penn": "NNP"
          },
          "transcription": "Utah"
        }
      ]
    },
    {
      "words": [
        {
          "tags": {
            "Penn": "JJ"
          },
          "transcription": "uh-huh"
        }
      ]
    },
    {
      "words": [
        {
          "tags": {
            "Penn": "CC"
          },
          "transcription": "and"
        },
        {
          "tags": {
            "Penn": "DT"
          },
          "transcription": "all"
        },
        {
          "tags": {
            "Penn": "IN"
          },
          "transcription": "of"
        },
        {
          "tags": {
            "Penn": "PRP$"
          },
          "transcription": "my"
        },
        {
          "tags": {
            "Penn": "NN"
          },
          "transcription": "dad"
        },
        {
          "tags": {
            "Penn": "POS"
          },
          "transcription": "'s"
        },
        {
          "tags": {
            "Penn": "UH"
          },
          "transcription": "uh"
        },
        {
          "tags": {
            "Penn": "NNS"
          },
          "transcription": "relatives"
        },
        {
          "tags": {
            "Penn": "CC"
          },
          "transcription": "and"
        },
        {
          "tags": {
            "Penn": "NN"
          },
          "transcription": "family"
        },
        {
          "tags": {
            "Penn": "VBP"
          },
          "transcription": "are"
        },
        {
          "tags": {
            "Penn": "IN"
          },
          "transcription": "from"
        },
        {
          "tags": {
            "Penn": "NNP"
          },
          "transcription": "Oregon"
        },
        {
          "tags": {
            "Penn": "IN"
          },
          "transcription": "so"
        },
        {
          "tags": {
            "Penn": "PRP"
          },
          "transcription": "we"
        },
        {
          "tags": {
            "Penn": "PRP"
          },
          "transcription": "we"
        },
        {
          "tags": {
            "Penn": "RB"
          },
          "transcription": "usually"
        },
        {
          "tags": {
            "Penn": "VBP"
          },
          "transcription": "have"
        },
        {
          "tags": {
            "Penn": "NN"
          },
          "transcription": "family"
        },
        {
          "tags": {
            "Penn": "NNS"
          },
          "transcription": "reunions"
        },
        {
          "tags": {
            "Penn": "RB"
          },
          "transcription": "once"
        },
        {
          "tags": {
            "Penn": "DT"
          },
          "transcription": "a"
        },
        {
          "tags": {
            "Penn": "NN"
          },
          "transcription": "year"
        },
        {
          "tags": {
            "Penn": "CC"
          },
          "transcription": "and"
        },
        {
          "tags": {
            "Penn": "PRP"
          },
          "transcription": "we"
        },
        {
          "tags": {
            "Penn": "MD"
          },
          "transcription": "'ll"
        },
        {
          "tags": {
            "Penn": "VB"
          },
          "transcription": "go"
        },
        {
          "tags": {
            "Penn": "TO"
          },
          "transcription": "to"
        },
        {
          "tags": {
            "Penn": "NNP"
          },
          "transcription": "Utah"
        },
        {
          "tags": {
            "Penn": "CC"
          },
          "transcription": "and"
        },
        {
          "tags": {
            "Penn": "UH"
          },
          "transcription": "uh"
        }
      ]
    },
    {
      "words": [
        {
          "tags": {
            "Penn": "VB"
          },
          "transcription": "go"
        },
        {
          "tags": {
            "Penn": "TO"
          },
          "transcription": "to"
        },
        {
          "tags": {
            "Penn": "NNP"
          },
          "transcription": "Oregon"
        },
        {
          "tags": {
            "Penn": "NN"
          },
          "transcription": "um"
        }
      ]
    },
    {
      "words": [
        {
          "tags": {
            "Penn": "PRP$"
          },
          "transcription": "my"
        },
        {
          "tags": {
            "Penn": "NN"
          },
          "transcription": "mom"
        },
        {
          "tags": {
            "Penn": "VBZ"
          },
          "transcription": "puts"
        },
        {
          "tags": {
            "Penn": "DT"
          },
          "transcription": "a"
        },
        {
          "tags": {
            "Penn": "JJ"
          },
          "transcription": "big"
        },
        {
          "tags": {
            "Penn": "NN"
          },
          "transcription": "deal"
        },
        {
          "tags": {
            "Penn": "IN"
          },
          "transcription": "into"
        },
        {
          "tags": {
            "Penn": "DT"
          },
          "transcription": "the"
        },
        {
          "tags": {
            "Penn": "NN"
          },
          "transcription": "family"
        },
        {
          "tags": {
            "Penn": "NN"
          },
          "transcription": "reunion"
        },
        {
          "tags": {
            "Penn": "WRB"
          },
          "transcription": "when"
        },
        {
          "tags": {
            "Penn": "PRP"
          },
          "transcription": "they"
        },
        {
          "tags": {
            "Penn": "VBP"
          },
          "transcription": "go"
        },
        {
          "tags": {
            "Penn": "TO"
          },
          "transcription": "to"
        },
        {
          "tags": {
            "Penn": "NNP"
          },
          "transcription": "Utah"
        },
        {
          "tags": {
            "Penn": "NN"
          },
          "transcription": "um"
        },
        {
          "tags": {
            "Penn": "CC"
          },
          "transcription": "and"
        },
        {
          "tags": {
            "Penn": "NN"
          },
          "transcription": "um"
        }
      ]
    },
    {
      "words": [
        {
          "tags": {
            "Penn": "PRP"
          },
          "transcription": "she"
        },
        {
          "tags": {
            "Penn": "RB"
          },
          "transcription": "sometimes"
        },
        {
          "tags": {
            "Penn": "VBZ"
          },
          "transcription": "plans"
        },
        {
          "tags": {
            "Penn": "PRP"
          },
          "transcription": "them"
        },
        {
          "tags": {
            "Penn": "CC"
          },
          "transcription": "and"
        },
        {
          "tags": {
            "Penn": "CC"
          },
          "transcription": "and"
        },
        {
          "tags": {
            "Penn": "RB"
          },
          "transcription": "sometimes"
        },
        {
          "tags": {
            "Penn": "VBZ"
          },
          "transcription": "helps"
        },
        {
          "tags": {
            "Penn": "IN"
          },
          "transcription": "in"
        },
        {
          "tags": {
            "Penn": "NN"
          },
          "transcription": "planning"
        },
        {
          "tags": {
            "Penn": "PRP"
          },
          "transcription": "them"
        },
        {
          "tags": {
            "Penn": "RB"
          },
          "transcription": "usually"
        },
        {
          "tags": {
            "Penn": "NN"
          },
          "transcription": "um"
        },
        {
          "tags": {
            "Penn": "NNP"
          },
          "transcription": "Southern"
        },
        {
          "tags": {
            "Penn": "NNP"
          },
          "transcription": "Utah"
        },
        {
          "tags": {
            "Penn": "VBZ"
          },
          "transcription": "is"
        },
        {
          "tags": {
            "Penn": "RB"
          },
          "transcription": "so"
        },
        {
          "tags": {
            "Penn": "JJ"
          },
          "transcription": "hot"
        },
        {
          "tags": {
            "Penn": "DT"
          },
          "transcription": "that"
        },
        {
          "tags": {
            "Penn": "NN"
          },
          "transcription": "um"
        },
        {
          "tags": {
            "Penn": "PRP"
          },
          "transcription": "we"
        },
        {
          "tags": {
            "Penn": "VBP"
          },
          "transcription": "pick"
        },
        {
          "tags": {
            "Penn": "EX"
          },
          "transcription": "there"
        },
        {
          "tags": {
            "Penn": "VBZ"
          },
          "transcription": "'s"
        },
        {
          "tags": {
            "Penn": "DT"
          },
          "transcription": "the"
        }
      ]
    },
    {
      "words": [
        {
          "tags": {
            "Penn": "PRP"
          },
          "transcription": "they"
        },
        {
          "tags": {
            "Penn": "NN"
          },
          "transcription": "rent"
        },
        {
          "tags": {
            "Penn": "RP"
          },
          "transcription": "out"
        },
        {
          "tags": {
            "Penn": "DT"
          },
          "transcription": "this"
        },
        {
          "tags": {
            "Penn": "NN"
          },
          "transcription": "cabin"
        },
        {
          "tags": {
            "Penn": "WDT"
          },
          "transcription": "that"
        },
        {
          "tags": {
            "Penn": "VBZ"
          },
          "transcription": "'s"
        },
        {
          "tags": {
            "Penn": "RB"
          },
          "transcription": "up"
        },
        {
          "tags": {
            "Penn": "IN"
          },
          "transcription": "on"
        },
        {
          "tags": {
            "Penn": "DT"
          },
          "transcription": "a"
        },
        {
          "tags": {
            "Penn": "NN"
          },
          "transcription": "mountain"
        },
        {
          "tags": {
            "Penn": "NNP"
          },
          "transcription": "i"
        },
        {
          "tags": {
            "Penn": "VB"
          },
          "transcription": "mean"
        },
        {
          "tags": {
            "Penn": "PRP"
          },
          "transcription": "you"
        },
        {
          "tags": {
            "Penn": "VBP"
          },
          "transcription": "have"
        },
        {
          "tags": {
            "Penn": "TO"
          },
          "transcription": "to"
        },
        {
          "tags": {
            "Penn": "VB"
          },
          "transcription": "go"
        },
        {
          "tags": {
            "Penn": "RP"
          },
          "transcription": "up"
        },
        {
          "tags": {
            "Penn": "IN"
          },
          "transcription": "into"
        },
        {
          "tags": {
            "Penn": "DT"
          },
          "transcription": "the"
        },
        {
          "tags": {
            "Penn": "NNS"
          },
          "transcription": "hills"
        },
        {
          "tags": {
            "Penn": "TO"
          },
          "transcription": "to"
        },
        {
          "tags": {
            "Penn": "VB"
          },
          "transcription": "get"
        },
        {
          "tags": {
            "Penn": "DT"
          },
          "transcription": "some"
        },
        {
          "tags": {
            "Penn": "JJR"
          },
          "transcription": "cooler"
        },
        {
          "tags": {
            "Penn": "NNS"
          },
          "transcription": "temperatures"
        },
        {
          "tags": {
            "Penn": "CC"
          },
          "transcription": "and"
        },
        {
          "tags": {
            "Penn": "VBP"
          },
          "transcription": "have"
        },
        {
          "tags": {
            "Penn": "DT"
          },
          "transcription": "a"
        },
        {
          "tags": {
            "Penn": "JJ"
          },
          "transcription": "enjoyable"
        },
        {
          "tags": {
            "Penn": "NN"
          },
          "transcription": "time"
        }
      ]
    },
    {
      "words": [
        {
          "tags": {
            "Penn": "UH"
          },
          "transcription": "oh"
        }
      ]
    },
    {
      "words": [
        {
          "tags": {
            "Penn": "JJ"
          },
          "transcription": "uh-huh"
        }
      ]
    },
    {
      "words": [
        {
          "tags": {
            "Penn": "CC"
          },
          "transcription": "and"
        },
        {
          "tags": {
            "Penn": "DT"
          },
          "transcription": "that"
        },
        {
          "tags": {
            "Penn": "VBZ"
          },
          "transcription": "'s"
        },
        {
          "tags": {
            "Penn": "WP"
          },
          "transcription": "what"
        },
        {
          "tags": {
            "Penn": "PRP"
          },
          "transcription": "we"
        },
        {
          "tags": {
            "Penn": "RB"
          },
          "transcription": "usually"
        },
        {
          "tags": {
            "Penn": "VBP"
          },
          "transcription": "do"
        },
        {
          "tags": {
            "Penn": "CC"
          },
          "transcription": "and"
        },
        {
          "tags": {
            "Penn": "RB"
          },
          "transcription": "then"
        },
        {
          "tags": {
            "Penn": "VBP"
          },
          "transcription": "have"
        },
        {
          "tags": {
            "Penn": "IN"
          },
          "transcription": "of"
        },
        {
          "tags": {
            "Penn": "NN"
          },
          "transcription": "course"
        },
        {
          "tags": {
            "Penn": "DT"
          },
          "transcription": "the"
        },
        {
          "tags": {
            "Penn": "NN"
          },
          "transcription": "food"
        },
        {
          "tags": {
            "Penn": "VBZ"
          },
          "transcription": "is"
        },
        {
          "tags": {
            "Penn": "CD"
          },
          "transcription": "one"
        },
        {
          "tags": {
            "Penn": "IN"
          },
          "transcription": "of"
        },
        {
          "tags": {
            "Penn": "DT"
          },
          "transcription": "the"
        },
        {
          "tags": {
            "Penn": "NNS"
          },
          "transcription": "highlights"
        },
        {
          "tags": {
            "Penn": "RB"
          },
          "transcription": "also"
        }
      ]
    },
    {
      "words": [
        {
          "tags": {
            "Penn": "JJ"
          },
          "transcription": "uh-huh"
        },
        {
          "tags": {
            "Penn": "NN"
          },
          "transcription": "yeah"
        },
        {
          "tags": {
            "Penn": "NN"
          },
          "transcription": "everybody"
        },
        {
          "tags": {
            "Penn": "NNS"
          },
          "transcription": "fixes"
        },
        {
          "tags": {
            "Penn": "PRP$"
          },
          "transcription": "their"
        },
        {
          "tags": {
            "Penn": "NN"
          },
          "transcription": "specialty"
        },
        {
          "tags": {
            "Penn": "CC"
          },
          "transcription": "or"
        },
        {
          "tags": {
            "Penn": "WDT"
          },
          "transcription": "whatever"
        }
      ]
    },
    {
      "words": [
        {
          "tags": {
            "Penn": "UH"
          },
          "transcription": "uh"
        }
      ]
    },
    {
      "words": [
        {
          "tags": {
            "Penn": "NN"
          },
          "transcription": "yeah"
        }
      ]
    },
    {
      "words": [
        {
          "tags": {
            "Penn": "NN"
          },
          "transcription": "yeah"
        },
        {
          "tags": {
            "Penn": "RB"
          },
          "transcription": "well"
        },
        {
          "tags": {
            "Penn": "PRP"
          },
          "transcription": "it"
        },
        {
          "tags": {
            "Penn": "RB"
          },
          "transcription": "really"
        },
        {
          "tags": {
            "Penn": "IN"
          },
          "transcription": "in"
        },
        {
          "tags": {
            "Penn": "PRP$"
          },
          "transcription": "your"
        },
        {
          "tags": {
            "Penn": "NN"
          },
          "transcription": "case"
        },
        {
          "tags": {
            "Penn": "CC"
          },
          "transcription": "and"
        },
        {
          "tags": {
            "Penn": "NN"
          },
          "transcription": "mine"
        },
        {
          "tags": {
            "Penn": "RB"
          },
          "transcription": "too"
        },
        {
          "tags": {
            "Penn": "UH"
          },
          "transcription": "uh"
        },
        {
          "tags": {
            "Penn": "NNP"
          },
          "transcription": "i"
        },
        {
          "tags": {
            "Penn": "VBP"
          },
          "transcription": "guess"
        },
        {
          "tags": {
            "Penn": "IN"
          },
          "transcription": "in"
        },
        {
          "tags": {
            "Penn": "JJS"
          },
          "transcription": "most"
        },
        {
          "tags": {
            "Penn": "NN"
          },
          "transcription": "everybody"
        },
        {
          "tags": {
            "Penn": "POS"
          },
          "transcription": "'s"
        },
        {
          "tags": {
            "Penn": "RB"
          },
          "transcription": "as"
        },
        {
          "tags": {
            "Penn": "RB"
          },
          "transcription": "far"
        },
        {
          "tags": {
            "Penn": "RB"
          },
          "transcription": "as"
        },
        {
          "tags": {
            "Penn": "RB"
          },
          "transcription": "especially"
        },
        {
          "tags": {
            "Penn": "RBR"
          },
          "transcription": "more"
        },
        {
          "tags": {
            "Penn": "JJ"
          },
          "transcription": "distant"
        },
        {
          "tags": {
            "Penn": "NNS"
          },
          "transcription": "relatives"
        },
        {
          "tags": {
            "Penn": "PRP"
          },
          "transcription": "you"
        },
        {
          "tags": {
            "Penn": "VBP"
          },
          "transcription": "know"
        },
        {
          "tags": {
            "Penn": "UH"
          },
          "transcription": "uh"
        },
        {
          "tags": {
            "Penn": "NNS"
          },
          "transcription": "cousins"
        },
        {
          "tags": {
            "Penn": "NNS"
          },
          "transcription": "aunts"
        },
        {
          "tags": {
            "Penn": "CC"
          },
          "transcription": "and"
        },
        {
          "tags": {
            "Penn": "NNS"
          },
          "transcription": "uncles"
        },
        {
          "tags": {
            "Penn": "CC"
          },
          "transcription": "and"
        },
        {
          "tags": {
            "Penn": "RB"
          },
          "transcription": "so"
        },
        {
          "tags": {
            "Penn": "IN"
          },
          "transcription": "on"
        }
      ]
    },
    {
      "words": [
        {
          "tags": {
            "Penn": "PRP"
          },
          "transcription": "you"
        },
        {
          "tags": {
            "Penn": "RB"
          },
          "transcription": "just"
        },
        {
          "tags": {
            "Penn": "MD"
          },
          "transcription": "would"
        },
        {
          "tags": {
            "Penn": "RB"
          },
          "transcription": "n't"
        },
        {
          "tags": {
            "Penn": "VB"
          },
          "transcription": "see"
        },
        {
          "tags": {
            "Penn": "PRP"
          },
          "transcription": "them"
        },
        {
          "tags": {
            "Penn": "IN"
          },
          "transcription": "if"
        },
        {
          "tags": {
            "Penn": "PRP"
          },
          "transcription": "you"
        },
        {
          "tags": {
            "Penn": "VBD"
          },
          "transcription": "did"
        },
        {
          "tags": {
            "Penn": "RB"
          },
          "transcription": "n't"
        },
        {
          "tags": {
            "Penn": "VB"
          },
          "transcription": "do"
        },
        {
          "tags": {
            "Penn": "NN"
          },
          "transcription": "something"
        },
        {
          "tags": {
            "Penn": "IN"
          },
          "transcription": "like"
        },
        {
          "tags": {
            "Penn": "DT"
          },
          "transcription": "that"
        }
      ]
    },
    {
      "words": [
        {
          "tags": {
            "Penn": "RB"
          },
          "transcription": "well"
        },
        {
          "tags": {
            "Penn": "PRP$"
          },
          "transcription": "my"
        },
        {
          "tags": {
            "Penn": "JJ"
          },
          "transcription": "immediate"
        },
        {
          "tags": {
            "Penn": "NN"
          },
          "transcription": "family"
        },
        {
          "tags": {
            "Penn": "IN"
          },
          "transcription": "like"
        },
        {
          "tags": {
            "Penn": "IN"
          },
          "transcription": "on"
        },
        {
          "tags": {
            "Penn": "PRP$"
          },
          "transcription": "my"
        },
        {
          "tags": {
            "Penn": "NN"
          },
          "transcription": "side"
        },
        {
          "tags": {
            "Penn": "UH"
          },
          "transcription": "uh"
        },
        {
          "tags": {
            "Penn": "VBZ"
          },
          "transcription": "has"
        },
        {
          "tags": {
            "Penn": "VBN"
          },
          "transcription": "gotten"
        },
        {
          "tags": {
            "Penn": "JJ"
          },
          "transcription": "large"
        },
        {
          "tags": {
            "Penn": "IN"
          },
          "transcription": "because"
        },
        {
          "tags": {
            "Penn": "EX"
          },
          "transcription": "there"
        },
        {
          "tags": {
            "Penn": "VBZ"
          },
          "transcription": "'s"
        },
        {
          "tags": {
            "Penn": "CD"
          },
          "transcription": "four"
        },
        {
          "tags": {
            "Penn": "IN"
          },
          "transcription": "of"
        },
        {
          "tags": {
            "Penn": "PRP"
          },
          "transcription": "us"
        },
        {
          "tags": {
            "Penn": "CC"
          },
          "transcription": "and"
        },
        {
          "tags": {
            "Penn": "RB"
          },
          "transcription": "now"
        },
        {
          "tags": {
            "Penn": "PRP"
          },
          "transcription": "we"
        },
        {
          "tags": {
            "Penn": "VBP"
          },
          "transcription": "'ve"
        },
        {
          "tags": {
            "Penn": "DT"
          },
          "transcription": "all"
        },
        {
          "tags": {
            "Penn": "VBN"
          },
          "transcription": "had"
        },
        {
          "tags": {
            "Penn": "NNS"
          },
          "transcription": "children"
        },
        {
          "tags": {
            "Penn": "CC"
          },
          "transcription": "and"
        },
        {
          "tags": {
            "Penn": "RB"
          },
          "transcription": "now"
        },
        {
          "tags": {
            "Penn": "PRP"
          },
          "transcription": "we"
        },
        {
          "tags": {
            "Penn": "DT"
          },
          "transcription": "all"
        },
        {
          "tags": {
            "Penn": "VBP"
          },
          "transcription": "have"
        },
        {
          "tags": {
            "Penn": "NNS"
          },
          "transcription": "grandchildren"
        }
      ]
    },
    {
      "words": [
        {
          "tags": {
            "Penn": "IN"
          },
          "transcription": "so"
        },
        {
          "tags": {
            "Penn": "WDT"
          },
          "transcription": "that"
        },
        {
          "tags": {
            "Penn": "VBZ"
          },
          "transcription": "makes"
        },
        {
          "tags": {
            "Penn": "RB"
          },
          "transcription": "just"
        },
        {
          "tags": {
            "Penn": "PRP$"
          },
          "transcription": "my"
        },
        {
          "tags": {
            "Penn": "JJ"
          },
          "transcription": "immediate"
        },
        {
          "tags": {
            "Penn": "NN"
          },
          "transcription": "family"
        },
        {
          "tags": {
            "Penn": "IN"
          },
          "transcription": "like"
        },
        {
          "tags": {
            "Penn": "CD"
          },
          "transcription": "thirty"
        },
        {
          "tags": {
            "Penn": "NNS"
          },
          "transcription": "people"
        },
        {
          "tags": {
            "Penn": "IN"
          },
          "transcription": "so"
        },
        {
          "tags": {
            "Penn": "PRP"
          },
          "transcription": "we"
        },
        {
          "tags": {
            "Penn": "VBP"
          },
          "transcription": "do"
        },
        {
          "tags": {
            "Penn": "DT"
          },
          "transcription": "a"
        },
        {
          "tags": {
            "Penn": "JJ"
          },
          "transcription": "separate"
        },
        {
          "tags": {
            "Penn": "NN"
          },
          "transcription": "reunion"
        },
        {
          "tags": {
            "Penn": "CC"
          },
          "transcription": "and"
        },
        {
          "tags": {
            "Penn": "PRP"
          },
          "transcription": "we"
        },
        {
          "tags": {
            "Penn": "VBP"
          },
          "transcription": "have"
        },
        {
          "tags": {
            "Penn": "DT"
          },
          "transcription": "a"
        },
        {
          "tags": {
            "Penn": "NN"
          },
          "transcription": "lake"
        },
        {
          "tags": {
            "Penn": "NN"
          },
          "transcription": "house"
        },
        {
          "tags": {
            "Penn": "UH"
          },
          "transcription": "uh"
        },
        {
          "tags": {
            "Penn": "IN"
          },
          "transcription": "about"
        },
        {
          "tags": {
            "Penn": "NN"
          },
          "transcription": "seventy"
        },
        {
          "tags": {
            "Penn": "NNS"
          },
          "transcription": "miles"
        },
        {
          "tags": {
            "Penn": "IN"
          },
          "transcription": "from"
        },
        {
          "tags": {
            "Penn": "RB"
          },
          "transcription": "here"
        }
      ]
    },
    {
      "words": [
        {
          "tags": {
            "Penn": "IN"
          },
          "transcription": "so"
        },
        {
          "tags": {
            "Penn": "PRP"
          },
          "transcription": "we"
        },
        {
          "tags": {
            "Penn": "PRP"
          },
          "transcription": "we"
        },
        {
          "tags": {
            "Penn": "VBP"
          },
          "transcription": "'ve"
        },
        {
          "tags": {
            "Penn": "VBN"
          },
          "transcription": "done"
        },
        {
          "tags": {
            "Penn": "PRP"
          },
          "transcription": "it"
        },
        {
          "tags": {
            "Penn": "RB"
          },
          "transcription": "once"
        },
        {
          "tags": {
            "Penn": "PRP"
          },
          "transcription": "we"
        },
        {
          "tags": {
            "Penn": "DT"
          },
          "transcription": "all"
        },
        {
          "tags": {
            "Penn": "VBP"
          },
          "transcription": "get"
        },
        {
          "tags": {
            "Penn": "RB"
          },
          "transcription": "together"
        },
        {
          "tags": {
            "Penn": "RB"
          },
          "transcription": "down"
        },
        {
          "tags": {
            "Penn": "EX"
          },
          "transcription": "there"
        }
      ]
    },
    {
      "words": [
        {
          "tags": {
            "Penn": "CC"
          },
          "transcription": "and"
        },
        {
          "tags": {
            "Penn": "NN"
          },
          "transcription": "um"
        },
        {
          "tags": {
            "Penn": "WDT"
          },
          "transcription": "that"
        },
        {
          "tags": {
            "Penn": "VBZ"
          },
          "transcription": "works"
        },
        {
          "tags": {
            "Penn": "IN"
          },
          "transcription": "out"
        },
        {
          "tags": {
            "Penn": "JJ"
          },
          "transcription": "real"
        },
        {
          "tags": {
            "Penn": "RB"
          },
          "transcription": "well"
        },
        {
          "tags": {
            "Penn": "IN"
          },
          "transcription": "because"
        },
        {
          "tags": {
            "Penn": "EX"
          },
          "transcription": "there"
        },
        {
          "tags": {
            "Penn": "VBZ"
          },
          "transcription": "'s"
        },
        {
          "tags": {
            "Penn": "DT"
          },
          "transcription": "a"
        },
        {
          "tags": {
            "Penn": "NN"
          },
          "transcription": "lot"
        }
      ]
    },
    {
      "words": [
        {
          "tags": {
            "Penn": "RB"
          },
          "transcription": "well"
        },
        {
          "tags": {
            "Penn": "NN"
          },
          "transcription": "lot"
        },
        {
          "tags": {
            "Penn": "IN"
          },
          "transcription": "of"
        },
        {
          "tags": {
            "Penn": "NNS"
          },
          "transcription": "things"
        },
        {
          "tags": {
            "Penn": "NN"
          },
          "transcription": "everybody"
        },
        {
          "tags": {
            "Penn": "MD"
          },
          "transcription": "can"
        },
        {
          "tags": {
            "Penn": "VB"
          },
          "transcription": "do"
        },
        {
          "tags": {
            "Penn": "PRP"
          },
          "transcription": "they"
        },
        {
          "tags": {
            "Penn": "MD"
          },
          "transcription": "can"
        },
        {
          "tags": {
            "Penn": "NN"
          },
          "transcription": "fish"
        },
        {
          "tags": {
            "Penn": "CC"
          },
          "transcription": "or"
        },
        {
          "tags": {
            "Penn": "PRP"
          },
          "transcription": "they"
        },
        {
          "tags": {
            "Penn": "MD"
          },
          "transcription": "can"
        },
        {
          "tags": {
            "Penn": "PRP"
          },
          "transcription": "you"
        },
        {
          "tags": {
            "Penn": "VB"
          },
          "transcription": "know"
        },
        {
          "tags": {
            "Penn": "VBP"
          },
          "transcription": "swim"
        },
        {
          "tags": {
            "Penn": "CC"
          },
          "transcription": "or"
        },
        {
          "tags": {
            "Penn": "NNS"
          },
          "transcription": "things"
        },
        {
          "tags": {
            "Penn": "IN"
          },
          "transcription": "like"
        },
        {
          "tags": {
            "Penn": "DT"
          },
          "transcription": "that"
        }
      ]
    },
    {
      "words": [
        {
          "tags": {
            "Penn": "NN"
          },
          "transcription": "yeah"
        },
        {
          "tags": {
            "Penn": "NNP"
          },
          "transcription": "i"
        },
        {
          "tags": {
            "Penn": "VB"
          },
          "transcription": "know"
        },
        {
          "tags": {
            "Penn": "IN"
          },
          "transcription": "at"
        },
        {
          "tags": {
            "Penn": "DT"
          },
          "transcription": "the"
        },
        {
          "tags": {
            "Penn": "DT"
          },
          "transcription": "the"
        },
        {
          "tags": {
            "Penn": "NN"
          },
          "transcription": "family"
        },
        {
          "tags": {
            "Penn": "NNS"
          },
          "transcription": "reunions"
        },
        {
          "tags": {
            "Penn": "IN"
          },
          "transcription": "on"
        },
        {
          "tags": {
            "Penn": "PRP$"
          },
          "transcription": "my"
        },
        {
          "tags": {
            "Penn": "NN"
          },
          "transcription": "dad"
        },
        {
          "tags": {
            "Penn": "POS"
          },
          "transcription": "'s"
        },
        {
          "tags": {
            "Penn": "NN"
          },
          "transcription": "side"
        },
        {
          "tags": {
            "Penn": "IN"
          },
          "transcription": "that"
        },
        {
          "tags": {
            "Penn": "PRP"
          },
          "transcription": "we"
        },
        {
          "tags": {
            "Penn": "VBP"
          },
          "transcription": "go"
        },
        {
          "tags": {
            "Penn": "TO"
          },
          "transcription": "to"
        },
        {
          "tags": {
            "Penn": "IN"
          },
          "transcription": "in"
        },
        {
          "tags": {
            "Penn": "NNP"
          },
          "transcription": "Oregon"
        },
        {
          "tags": {
            "Penn": "NN"
          },
          "transcription": "um"
        },
        {
          "tags": {
            "Penn": "PRP"
          },
          "transcription": "we"
        },
        {
          "tags": {
            "Penn": "RB"
          },
          "transcription": "usually"
        },
        {
          "tags": {
            "Penn": "NN"
          },
          "transcription": "um"
        }
      ]
    },
    {
      "words": [
        {
          "tags": {
            "Penn": "VBP"
          },
          "transcription": "have"
        },
        {
          "tags": {
            "Penn": "PRP"
          },
          "transcription": "it"
        },
        {
          "tags": {
            "Penn": "IN"
          },
          "transcription": "at"
        },
        {
          "tags": {
            "Penn": "DT"
          },
          "transcription": "a"
        },
        {
          "tags": {
            "Penn": "NN"
          },
          "transcription": "park"
        },
        {
          "tags": {
            "Penn": "CC"
          },
          "transcription": "and"
        },
        {
          "tags": {
            "Penn": "IN"
          },
          "transcription": "so"
        },
        {
          "tags": {
            "Penn": "PRP"
          },
          "transcription": "you"
        },
        {
          "tags": {
            "Penn": "VBP"
          },
          "transcription": "know"
        },
        {
          "tags": {
            "Penn": "NN"
          },
          "transcription": "swimming"
        },
        {
          "tags": {
            "Penn": "VBZ"
          },
          "transcription": "is"
        },
        {
          "tags": {
            "Penn": "RB"
          },
          "transcription": "always"
        },
        {
          "tags": {
            "Penn": "NN"
          },
          "transcription": "part"
        },
        {
          "tags": {
            "Penn": "IN"
          },
          "transcription": "of"
        },
        {
          "tags": {
            "Penn": "CD"
          },
          "transcription": "one"
        },
        {
          "tags": {
            "Penn": "IN"
          },
          "transcription": "of"
        },
        {
          "tags": {
            "Penn": "DT"
          },
          "transcription": "the"
        },
        {
          "tags": {
            "Penn": "NNS"
          },
          "transcription": "activities"
        },
        {
          "tags": {
            "Penn": "RB"
          },
          "transcription": "so"
        }
      ]
    },
    {
      "words": [
        {
          "tags": {
            "Penn": "JJ"
          },
          "transcription": "uh-huh"
        }
      ]
    },
    {
      "words": [
        {
          "tags": {
            "Penn": "JJ"
          },
          "transcription": "uh-huh"
        }
      ]
    },
    {
      "words": [
        {
          "tags": {
            "Penn": "RB"
          },
          "transcription": "well"
        },
        {
          "tags": {
            "Penn": "PRP"
          },
          "transcription": "it"
        },
        {
          "tags": {
            "Penn": "RB"
          },
          "transcription": "really"
        },
        {
          "tags": {
            "Penn": "VBZ"
          },
          "transcription": "does"
        },
        {
          "tags": {
            "Penn": "RB"
          },
          "transcription": "n't"
        },
        {
          "tags": {
            "Penn": "JJ"
          },
          "transcription": "much"
        },
        {
          "tags": {
            "Penn": "NN"
          },
          "transcription": "matter"
        },
        {
          "tags": {
            "Penn": "WRB"
          },
          "transcription": "where"
        },
        {
          "tags": {
            "Penn": "WRB"
          },
          "transcription": "where"
        },
        {
          "tags": {
            "Penn": "CC"
          },
          "transcription": "or"
        },
        {
          "tags": {
            "Penn": "WRB"
          },
          "transcription": "how"
        },
        {
          "tags": {
            "Penn": "PRP"
          },
          "transcription": "you"
        },
        {
          "tags": {
            "Penn": "VBP"
          },
          "transcription": "do"
        },
        {
          "tags": {
            "Penn": "PRP"
          },
          "transcription": "it"
        },
        {
          "tags": {
            "Penn": "RB"
          },
          "transcription": "as"
        },
        {
          "tags": {
            "Penn": "RB"
          },
          "transcription": "long"
        },
        {
          "tags": {
            "Penn": "IN"
          },
          "transcription": "as"
        },
        {
          "tags": {
            "Penn": "PRP"
          },
          "transcription": "you"
        },
        {
          "tags": {
            "Penn": "VBP"
          },
          "transcription": "manage"
        },
        {
          "tags": {
            "Penn": "TO"
          },
          "transcription": "to"
        },
        {
          "tags": {
            "Penn": "VB"
          },
          "transcription": "do"
        },
        {
          "tags": {
            "Penn": "PRP"
          },
          "transcription": "it"
        },
        {
          "tags": {
            "Penn": "DT"
          },
          "transcription": "every"
        },
        {
          "tags": {
            "Penn": "WRB"
          },
          "transcription": "how"
        },
        {
          "tags": {
            "Penn": "RB"
          },
          "transcription": "often"
        },
        {
          "tags": {
            "Penn": "VBD"
          },
          "transcription": "did"
        },
        {
          "tags": {
            "Penn": "IN"
          },
          "transcription": "like"
        },
        {
          "tags": {
            "Penn": "PRP$"
          },
          "transcription": "your"
        },
        {
          "tags": {
            "Penn": "NNS"
          },
          "transcription": "families"
        },
        {
          "tags": {
            "Penn": "RB"
          },
          "transcription": "up"
        },
        {
          "tags": {
            "Penn": "EX"
          },
          "transcription": "there"
        },
        {
          "tags": {
            "Penn": "VBP"
          },
          "transcription": "have"
        },
        {
          "tags": {
            "Penn": "PRP"
          },
          "transcription": "them"
        }
      ]
    },
    {
      "words": [
        {
          "tags": {
            "Penn": "UH"
          },
          "transcription": "oh"
        },
        {
          "tags": {
            "Penn": "EX"
          },
          "transcription": "there"
        },
        {
          "tags": {
            "Penn": "VBZ"
          },
          "transcription": "'s"
        },
        {
          "tags": {
            "Penn": "DT"
          },
          "transcription": "a"
        },
        {
          "tags": {
            "Penn": "EX"
          },
          "transcription": "there"
        },
        {
          "tags": {
            "Penn": "VBZ"
          },
          "transcription": "'s"
        },
        {
          "tags": {
            "Penn": "DT"
          },
          "transcription": "a"
        },
        {
          "tags": {
            "Penn": "NN"
          },
          "transcription": "family"
        },
        {
          "tags": {
            "Penn": "NN"
          },
          "transcription": "reunion"
        },
        {
          "tags": {
            "Penn": "NN"
          },
          "transcription": "reunion"
        },
        {
          "tags": {
            "Penn": "NN"
          },
          "transcription": "um"
        },
        {
          "tags": {
            "Penn": "RB"
          },
          "transcription": "once"
        },
        {
          "tags": {
            "Penn": "DT"
          },
          "transcription": "a"
        },
        {
          "tags": {
            "Penn": "NN"
          },
          "transcription": "year"
        },
        {
          "tags": {
            "Penn": "NN"
          },
          "transcription": "um"
        }
      ]
    },
    {
      "words": [
        {
          "tags": {
            "Penn": "IN"
          },
          "transcription": "for"
        },
        {
          "tags": {
            "Penn": "IN"
          },
          "transcription": "for"
        },
        {
          "tags": {
            "Penn": "DT"
          },
          "transcription": "each"
        },
        {
          "tags": {
            "Penn": "IN"
          },
          "transcription": "for"
        },
        {
          "tags": {
            "Penn": "PRP$"
          },
          "transcription": "my"
        },
        {
          "tags": {
            "Penn": "NN"
          },
          "transcription": "father"
        },
        {
          "tags": {
            "Penn": "POS"
          },
          "transcription": "'s"
        },
        {
          "tags": {
            "Penn": "NN"
          },
          "transcription": "side"
        },
        {
          "tags": {
            "Penn": "CC"
          },
          "transcription": "and"
        },
        {
          "tags": {
            "Penn": "IN"
          },
          "transcription": "for"
        },
        {
          "tags": {
            "Penn": "PRP$"
          },
          "transcription": "my"
        },
        {
          "tags": {
            "Penn": "NN"
          },
          "transcription": "mother"
        },
        {
          "tags": {
            "Penn": "POS"
          },
          "transcription": "'s"
        },
        {
          "tags": {
            "Penn": "NN"
          },
          "transcription": "side"
        },
        {
          "tags": {
            "Penn": "NNP"
          },
          "transcription": "i"
        },
        {
          "tags": {
            "Penn": "VB"
          },
          "transcription": "know"
        },
        {
          "tags": {
            "Penn": "CC"
          },
          "transcription": "and"
        },
        {
          "tags": {
            "Penn": "PRP$"
          },
          "transcription": "my"
        },
        {
          "tags": {
            "Penn": "NN"
          },
          "transcription": "wife"
        },
        {
          "tags": {
            "Penn": "RB"
          },
          "transcription": "also"
        },
        {
          "tags": {
            "Penn": "NN"
          },
          "transcription": "um"
        }
      ]
    },
    {
      "words": [
        {
          "tags": {
            "Penn": "IN"
          },
          "transcription": "so"
        },
        {
          "tags": {
            "Penn": "PRP"
          },
          "transcription": "they"
        },
        {
          "tags": {
            "Penn": "VBP"
          },
          "transcription": "try"
        },
        {
          "tags": {
            "Penn": "WRB"
          },
          "transcription": "when"
        },
        {
          "tags": {
            "Penn": "PRP"
          },
          "transcription": "they"
        },
        {
          "tags": {
            "Penn": "VBP"
          },
          "transcription": "have"
        },
        {
          "tags": {
            "Penn": "NN"
          },
          "transcription": "family"
        },
        {
          "tags": {
            "Penn": "NNS"
          },
          "transcription": "reunions"
        },
        {
          "tags": {
            "Penn": "PRP"
          },
          "transcription": "they"
        },
        {
          "tags": {
            "Penn": "VBP"
          },
          "transcription": "do"
        },
        {
          "tags": {
            "Penn": "RB"
          },
          "transcription": "n't"
        },
        {
          "tags": {
            "Penn": "VB"
          },
          "transcription": "have"
        },
        {
          "tags": {
            "Penn": "PRP"
          },
          "transcription": "them"
        },
        {
          "tags": {
            "Penn": "RB"
          },
          "transcription": "as"
        },
        {
          "tags": {
            "Penn": "RB"
          },
          "transcription": "regularly"
        },
        {
          "tags": {
            "Penn": "CC"
          },
          "transcription": "but"
        },
        {
          "tags": {
            "Penn": "WRB"
          },
          "transcription": "when"
        },
        {
          "tags": {
            "Penn": "PRP"
          },
          "transcription": "they"
        },
        {
          "tags": {
            "Penn": "VBP"
          },
          "transcription": "do"
        },
        {
          "tags": {
            "Penn": "PRP"
          },
          "transcription": "they"
        },
        {
          "tags": {
            "Penn": "VBP"
          },
          "transcription": "try"
        },
        {
          "tags": {
            "Penn": "CC"
          },
          "transcription": "and"
        },
        {
          "tags": {
            "Penn": "VB"
          },
          "transcription": "make"
        },
        {
          "tags": {
            "Penn": "JJ"
          },
          "transcription": "big"
        },
        {
          "tags": {
            "Penn": "NN"
          },
          "transcription": "deal"
        },
        {
          "tags": {
            "Penn": "IN"
          },
          "transcription": "out"
        },
        {
          "tags": {
            "Penn": "IN"
          },
          "transcription": "of"
        },
        {
          "tags": {
            "Penn": "PRP"
          },
          "transcription": "it"
        },
        {
          "tags": {
            "Penn": "CC"
          },
          "transcription": "and"
        },
        {
          "tags": {
            "Penn": "RB"
          },
          "transcription": "usually"
        },
        {
          "tags": {
            "Penn": "VBP"
          },
          "transcription": "have"
        },
        {
          "tags": {
            "Penn": "PRP"
          },
          "transcription": "you"
        },
        {
          "tags": {
            "Penn": "VBP"
          },
          "transcription": "know"
        },
        {
          "tags": {
            "Penn": "NN"
          },
          "transcription": "something"
        },
        {
          "tags": {
            "Penn": "IN"
          },
          "transcription": "like"
        },
        {
          "tags": {
            "Penn": "DT"
          },
          "transcription": "a"
        },
        {
          "tags": {
            "Penn": "NN"
          },
          "transcription": "talent"
        },
        {
          "tags": {
            "Penn": "NN"
          },
          "transcription": "show"
        },
        {
          "tags": {
            "Penn": "CC"
          },
          "transcription": "or"
        }
      ]
    },
    {
      "words": [
        {
          "tags": {
            "Penn": "NN"
          },
          "transcription": "yeah"
        }
      ]
    },
    {
      "words": [
        {
          "tags": {
            "Penn": "NN"
          },
          "transcription": "um"
        },
        {
          "tags": {
            "Penn": "DT"
          },
          "transcription": "each"
        },
        {
          "tags": {
            "Penn": "NN"
          },
          "transcription": "family"
        },
        {
          "tags": {
            "Penn": "NN"
          },
          "transcription": "um"
        },
        {
          "tags": {
            "Penn": "VBZ"
          },
          "transcription": "does"
        },
        {
          "tags": {
            "Penn": "NN"
          },
          "transcription": "something"
        }
      ]
    },
    {
      "words": [
        {
          "tags": {
            "Penn": "NN"
          },
          "transcription": "um"
        }
      ]
    },
    {
      "words": [
        {
          "tags": {
            "Penn": "NN"
          },
          "transcription": "yeah"
        }
      ]
    },
    {
      "words": [
        {
          "tags": {
            "Penn": "NN"
          },
          "transcription": "yeah"
        },
        {
          "tags": {
            "Penn": "PRP"
          },
          "transcription": "we"
        },
        {
          "tags": {
            "Penn": "VBP"
          },
          "transcription": "have"
        },
        {
          "tags": {
            "Penn": "VBN"
          },
          "transcription": "taken"
        },
        {
          "tags": {
            "Penn": "IN"
          },
          "transcription": "like"
        },
        {
          "tags": {
            "Penn": "JJ"
          },
          "transcription": "old"
        },
        {
          "tags": {
            "Penn": "NN"
          },
          "transcription": "home"
        },
        {
          "tags": {
            "Penn": "NNS"
          },
          "transcription": "movies"
        },
        {
          "tags": {
            "Penn": "IN"
          },
          "transcription": "from"
        },
        {
          "tags": {
            "Penn": "PRP"
          },
          "transcription": "you"
        },
        {
          "tags": {
            "Penn": "VBP"
          },
          "transcription": "know"
        },
        {
          "tags": {
            "Penn": "CD"
          },
          "transcription": "twenty"
        },
        {
          "tags": {
            "Penn": "CD"
          },
          "transcription": "five"
        },
        {
          "tags": {
            "Penn": "CD"
          },
          "transcription": "thirty"
        },
        {
          "tags": {
            "Penn": "NNS"
          },
          "transcription": "years"
        },
        {
          "tags": {
            "Penn": "RB"
          },
          "transcription": "ago"
        },
        {
          "tags": {
            "Penn": "CC"
          },
          "transcription": "and"
        },
        {
          "tags": {
            "Penn": "CC"
          },
          "transcription": "and"
        },
        {
          "tags": {
            "Penn": "VBN"
          },
          "transcription": "shown"
        },
        {
          "tags": {
            "Penn": "PRP"
          },
          "transcription": "them"
        },
        {
          "tags": {
            "Penn": "IN"
          },
          "transcription": "at"
        },
        {
          "tags": {
            "Penn": "DT"
          },
          "transcription": "the"
        },
        {
          "tags": {
            "Penn": "NN"
          },
          "transcription": "family"
        },
        {
          "tags": {
            "Penn": "NN"
          },
          "transcription": "reunion"
        }
      ]
    },
    {
      "words": [
        {
          "tags": {
            "Penn": "NN"
          },
          "transcription": "yeah"
        },
        {
          "tags": {
            "Penn": "PRP$"
          },
          "transcription": "my"
        },
        {
          "tags": {
            "Penn": "NN"
          },
          "transcription": "mom"
        },
        {
          "tags": {
            "Penn": "PRP$"
          },
          "transcription": "my"
        },
        {
          "tags": {
            "Penn": "NN"
          },
          "transcription": "grandma"
        },
        {
          "tags": {
            "Penn": "RB"
          },
          "transcription": "also"
        },
        {
          "tags": {
            "Penn": "VBZ"
          },
          "transcription": "has"
        },
        {
          "tags": {
            "Penn": "DT"
          },
          "transcription": "some"
        }
      ]
    },
    {
      "words": [
        {
          "tags": {
            "Penn": "PRP"
          },
          "transcription": "we"
        },
        {
          "tags": {
            "Penn": "VBP"
          },
          "transcription": "have"
        },
        {
          "tags": {
            "Penn": "RB"
          },
          "transcription": "n't"
        },
        {
          "tags": {
            "Penn": "RB"
          },
          "transcription": "particularly"
        },
        {
          "tags": {
            "Penn": "VBN"
          },
          "transcription": "shown"
        },
        {
          "tags": {
            "Penn": "DT"
          },
          "transcription": "those"
        },
        {
          "tags": {
            "Penn": "IN"
          },
          "transcription": "at"
        },
        {
          "tags": {
            "Penn": "DT"
          },
          "transcription": "the"
        },
        {
          "tags": {
            "Penn": "NNS"
          },
          "transcription": "reunions"
        },
        {
          "tags": {
            "Penn": "CC"
          },
          "transcription": "but"
        },
        {
          "tags": {
            "Penn": "PRP$"
          },
          "transcription": "my"
        },
        {
          "tags": {
            "Penn": "NN"
          },
          "transcription": "grandma"
        },
        {
          "tags": {
            "Penn": "VBZ"
          },
          "transcription": "has"
        },
        {
          "tags": {
            "Penn": "DT"
          },
          "transcription": "some"
        },
        {
          "tags": {
            "Penn": "NN"
          },
          "transcription": "home"
        },
        {
          "tags": {
            "Penn": "NNS"
          },
          "transcription": "movies"
        },
        {
          "tags": {
            "Penn": "CC"
          },
          "transcription": "and"
        },
        {
          "tags": {
            "Penn": "PRP"
          },
          "transcription": "we"
        },
        {
          "tags": {
            "Penn": "RB"
          },
          "transcription": "ever"
        },
        {
          "tags": {
            "Penn": "WRB"
          },
          "transcription": "whenever"
        },
        {
          "tags": {
            "Penn": "PRP"
          },
          "transcription": "we"
        },
        {
          "tags": {
            "Penn": "VBP"
          },
          "transcription": "go"
        },
        {
          "tags": {
            "Penn": "TO"
          },
          "transcription": "to"
        },
        {
          "tags": {
            "Penn": "PRP$"
          },
          "transcription": "her"
        },
        {
          "tags": {
            "Penn": "NN"
          },
          "transcription": "house"
        },
        {
          "tags": {
            "Penn": "PRP"
          },
          "transcription": "we"
        },
        {
          "tags": {
            "Penn": "VBP"
          },
          "transcription": "like"
        },
        {
          "tags": {
            "Penn": "TO"
          },
          "transcription": "to"
        }
      ]
    },
    {
      "words": [
        {
          "tags": {
            "Penn": "VB"
          },
          "transcription": "see"
        },
        {
          "tags": {
            "Penn": "DT"
          },
          "transcription": "those"
        },
        {
          "tags": {
            "Penn": "DT"
          },
          "transcription": "those"
        },
        {
          "tags": {
            "Penn": "VBP"
          },
          "transcription": "are"
        }
      ]
    },
    {
      "words": [
        {
          "tags": {
            "Penn": "PRP"
          },
          "transcription": "you"
        },
        {
          "tags": {
            "Penn": "VBP"
          },
          "transcription": "know"
        },
        {
          "tags": {
            "Penn": "JJ"
          },
          "transcription": "nice"
        },
        {
          "tags": {
            "Penn": "IN"
          },
          "transcription": "for"
        },
        {
          "tags": {
            "Penn": "NNS"
          },
          "transcription": "memories"
        }
      ]
    },
    {
      "words": [
        {
          "tags": {
            "Penn": "JJ"
          },
          "transcription": "uh-huh"
        },
        {
          "tags": {
            "Penn": "PRP"
          },
          "transcription": "we"
        },
        {
          "tags": {
            "Penn": "RB"
          },
          "transcription": "finally"
        },
        {
          "tags": {
            "Penn": "VBP"
          },
          "transcription": "put"
        },
        {
          "tags": {
            "Penn": "PRP"
          },
          "transcription": "ours"
        },
        {
          "tags": {
            "Penn": "IN"
          },
          "transcription": "on"
        },
        {
          "tags": {
            "Penn": "NN"
          },
          "transcription": "tape"
        },
        {
          "tags": {
            "Penn": "DT"
          },
          "transcription": "a"
        },
        {
          "tags": {
            "Penn": "JJ"
          },
          "transcription": "few"
        },
        {
          "tags": {
            "Penn": "NNS"
          },
          "transcription": "years"
        },
        {
          "tags": {
            "Penn": "RB"
          },
          "transcription": "ago"
        },
        {
          "tags": {
            "Penn": "EX"
          },
          "transcription": "there"
        },
        {
          "tags": {
            "Penn": "VBZ"
          },
          "transcription": "'s"
        },
        {
          "tags": {
            "Penn": "NNS"
          },
          "transcription": "places"
        },
        {
          "tags": {
            "Penn": "RB"
          },
          "transcription": "now"
        },
        {
          "tags": {
            "Penn": "WDT"
          },
          "transcription": "that"
        },
        {
          "tags": {
            "Penn": "VBP"
          },
          "transcription": "do"
        },
        {
          "tags": {
            "Penn": "DT"
          },
          "transcription": "that"
        }
      ]
    },
    {
      "words": [
        {
          "tags": {
            "Penn": "CC"
          },
          "transcription": "and"
        },
        {
          "tags": {
            "Penn": "UH"
          },
          "transcription": "uh"
        },
        {
          "tags": {
            "Penn": "PRP"
          },
          "transcription": "it"
        },
        {
          "tags": {
            "Penn": "RB"
          },
          "transcription": "really"
        },
        {
          "tags": {
            "Penn": "VBZ"
          },
          "transcription": "is"
        },
        {
          "tags": {
            "Penn": "JJ"
          },
          "transcription": "nice"
        },
        {
          "tags": {
            "Penn": "WRB"
          },
          "transcription": "when"
        },
        {
          "tags": {
            "Penn": "PRP"
          },
          "transcription": "you"
        },
        {
          "tags": {
            "Penn": "WRB"
          },
          "transcription": "when"
        },
        {
          "tags": {
            "Penn": "IN"
          },
          "transcription": "because"
        },
        {
          "tags": {
            "Penn": "PRP"
          },
          "transcription": "you"
        },
        {
          "tags": {
            "Penn": "MD"
          },
          "transcription": "can"
        },
        {
          "tags": {
            "Penn": "VB"
          },
          "transcription": "get"
        },
        {
          "tags": {
            "Penn": "IN"
          },
          "transcription": "on"
        },
        {
          "tags": {
            "Penn": "CD"
          },
          "transcription": "one"
        },
        {
          "tags": {
            "Penn": "NN"
          },
          "transcription": "tape"
        },
        {
          "tags": {
            "Penn": "PRP"
          },
          "transcription": "you"
        },
        {
          "tags": {
            "Penn": "MD"
          },
          "transcription": "can"
        },
        {
          "tags": {
            "Penn": "VB"
          },
          "transcription": "get"
        },
        {
          "tags": {
            "Penn": "IN"
          },
          "transcription": "about"
        },
        {
          "tags": {
            "Penn": "CD"
          },
          "transcription": "thirty"
        },
        {
          "tags": {
            "Penn": "CC"
          },
          "transcription": "or"
        },
        {
          "tags": {
            "Penn": "NN"
          },
          "transcription": "forty"
        },
        {
          "tags": {
            "Penn": "JJ"
          },
          "transcription": "old"
        },
        {
          "tags": {
            "Penn": "NNS"
          },
          "transcription": "reels"
        },
        {
          "tags": {
            "Penn": "PRP"
          },
          "transcription": "you"
        },
        {
          "tags": {
            "Penn": "VBP"
          },
          "transcription": "know"
        }
      ]
    },
    {
      "words": [
        {
          "tags": {
            "Penn": "JJ"
          },
          "transcription": "uh-huh"
        }
      ]
    },
    {
      "words": [
        {
          "tags": {
            "Penn": "IN"
          },
          "transcription": "on"
        },
        {
          "tags": {
            "Penn": "EX"
          },
          "transcription": "there"
        },
        {
          "tags": {
            "Penn": "CC"
          },
          "transcription": "and"
        },
        {
          "tags": {
            "Penn": "PRP"
          },
          "transcription": "it"
        },
        {
          "tags": {
            "Penn": "CC"
          },
          "transcription": "and"
        },
        {
          "tags": {
            "Penn": "RB"
          },
          "transcription": "then"
        },
        {
          "tags": {
            "Penn": "PRP"
          },
          "transcription": "you"
        },
        {
          "tags": {
            "Penn": "MD"
          },
          "transcription": "can"
        },
        {
          "tags": {
            "Penn": "VB"
          },
          "transcription": "skip"
        },
        {
          "tags": {
            "Penn": "IN"
          },
          "transcription": "around"
        },
        {
          "tags": {
            "Penn": "CC"
          },
          "transcription": "and"
        },
        {
          "tags": {
            "Penn": "VB"
          },
          "transcription": "find"
        },
        {
          "tags": {
            "Penn": "WP"
          },
          "transcription": "what"
        },
        {
          "tags": {
            "Penn": "PRP"
          },
          "transcription": "you"
        },
        {
          "tags": {
            "Penn": "VBP"
          },
          "transcription": "want"
        },
        {
          "tags": {
            "Penn": "CC"
          },
          "transcription": "and"
        },
        {
          "tags": {
            "Penn": "DT"
          },
          "transcription": "all"
        },
        {
          "tags": {
            "Penn": "IN"
          },
          "transcription": "that"
        },
        {
          "tags": {
            "Penn": "PRP"
          },
          "transcription": "it"
        },
        {
          "tags": {
            "Penn": "RB"
          },
          "transcription": "really"
        },
        {
          "tags": {
            "Penn": "VBZ"
          },
          "transcription": "has"
        },
        {
          "tags": {
            "Penn": "UH"
          },
          "transcription": "uh"
        },
        {
          "tags": {
            "Penn": "VBN"
          },
          "transcription": "worked"
        },
        {
          "tags": {
            "Penn": "IN"
          },
          "transcription": "out"
        },
        {
          "tags": {
            "Penn": "JJ"
          },
          "transcription": "good"
        }
      ]
    },
    {
      "words": [
        {
          "tags": {
            "Penn": "JJ"
          },
          "transcription": "uh-huh"
        }
      ]
    },
    {
      "words": [
        {
          "tags": {
            "Penn": "RB"
          },
          "transcription": "so"
        },
        {
          "tags": {
            "Penn": "UH"
          },
          "transcription": "uh"
        }
      ]
    },
    {
      "words": [
        {
          "tags": {
            "Penn": "RB"
          },
          "transcription": "so"
        },
        {
          "tags": {
            "Penn": "WRB"
          },
          "transcription": "how"
        },
        {
          "tags": {
            "Penn": "VBD"
          },
          "transcription": "did"
        },
        {
          "tags": {
            "Penn": "PRP"
          },
          "transcription": "you"
        },
        {
          "tags": {
            "Penn": "VBP"
          },
          "transcription": "get"
        },
        {
          "tags": {
            "Penn": "IN"
          },
          "transcription": "on"
        },
        {
          "tags": {
            "Penn": "DT"
          },
          "transcription": "the"
        },
        {
          "tags": {
            "Penn": "NNP"
          },
          "transcription": "TI"
        },
        {
          "tags": {
            "Penn": "NN"
          },
          "transcription": "thing"
        }
      ]
    }
  ]
}